{
  "type": "Feature", 
  "properties": {
    "iso:country": "US", 
    "media:created": 1352158528, 
    "media:fingerprint": "e2bd6bc5063252d46f539a56b21cb898e29fce27", 
    "media:medium": "image", 
    "media:mimetype": "image/jpeg", 
    "media:properties": {
      "colours": [
        {
          "hex": "#c0b04a", 
          "name": "#c0b04a", 
          "reference": "vibrant"
        }, 
        {
          "hex": "#9a3223", 
          "name": "#9a3223", 
          "reference": "vibrant"
        }, 
        {
          "hex": "#9e8459", 
          "name": "#9e8459", 
          "reference": "vibrant"
        }, 
        {
          "hex": "#cfbea7", 
          "name": "#cfbea7", 
          "reference": "vibrant"
        }, 
        {
          "hex": "#3b3523", 
          "name": "#3b3523", 
          "reference": "vibrant"
        }
      ], 
      "depicts": [1159160347], 
      "sizes": {
        "b": {
          "extension": "jpg", 
          "height": 682, 
          "mimetype": "image/jpeg", 
          "secret": "zOFPXWEs2FRzFCD0xQYoKLzZe41ilxTP", 
          "width": 1024
        }, 
        "c": {
          "extension": "jpg", 
          "height": 533, 
          "mimetype": "image/jpeg", 
          "secret": "zOFPXWEs2FRzFCD0xQYoKLzZe41ilxTP", 
          "width": 800
        }, 
        "dc": {
          "extension": "jpg", 
          "height": 533, 
          "mimetype": "image/jpeg", 
          "secret": "zOFPXWEs2FRzFCD0xQYoKLzZe41ilxTP", 
          "width": 800
        }, 
        "ds": {
          "extension": "jpg", 
          "height": 320, 
          "mimetype": "image/jpeg", 
          "secret": "zOFPXWEs2FRzFCD0xQYoKLzZe41ilxTP", 
          "width": 320
        }, 
        "k": {
          "extension": "jpg", 
          "height": 1365, 
          "mimetype": "image/jpeg", 
          "secret": "zOFPXWEs2FRzFCD0xQYoKLzZe41ilxTP", 
          "width": 2048
        }, 
        "n": {
          "extension": "jpg", 
          "height": 213, 
          "mimetype": "image/jpeg", 
          "secret": "zOFPXWEs2FRzFCD0xQYoKLzZe41ilxTP", 
          "width": 320
        }, 
        "o": {
          "extension": "jpg", 
          "height": 2400, 
          "mimetype": "image/jpeg", 
          "secret": "Alz2IFjRSiOujbELDY8CMUThT02uAG0A", 
          "width": 3600
        }, 
        "s": {
          "extension": "jpg", 
          "height": 320, 
          "mimetype": "image/jpeg", 
          "secret": "zOFPXWEs2FRzFCD0xQYoKLzZe41ilxTP", 
          "width": 320
        }, 
        "z": {
          "extension": "jpg", 
          "height": 426, 
          "mimetype": "image/jpeg", 
          "secret": "zOFPXWEs2FRzFCD0xQYoKLzZe41ilxTP", 
          "width": 640
        }
      }
    }, 
    "sfomuseum:placetype": "image", 
    "wof:depicts": [
      1159396109, 
      1159396333, 
      102527513, 
      1360516259, 
      1159160347, 
      1159396261
    ], 
    "wof:name": "Installation view of \"Let’s Play! 100 Years of Board Games\"", 
    "wof:placetype": "media" 
  }, 
  "geometry": {"coordinates":[-122.382712,37.617422],"type":"Point"}
}
