{
  "type": "Feature",
  "properties": {
    "date:cessation_lower": "2017-12-11",
    "date:cessation_upper": "2017-12-11",
    "date:inception_lower": "2017-04-21",
    "date:inception_upper": "2017-04-21",
    "iso:country": "US",
    "media:created": 1493400596,
    "media:fingerprint": "03e974903f83c79db19f27dfee5ecc76e2877c94",
    "media:imagehash_avg": "a:ff7f5f9c87838181",
    "media:imagehash_diff": "d:babab4393f3b9b1b",
    "media:medium": "image",
    "media:mimetype": "image/jpeg",
    "media:properties": {
      "colours": [
        {
          "hex": "#d92c4e",
          "name": "#d92c4e",
          "reference": "vibrant"
        },
        {
          "hex": "#a17058",
          "name": "#a17058",
          "reference": "vibrant"
        },
        {
          "hex": "#cbbcaa",
          "name": "#cbbcaa",
          "reference": "vibrant"
        },
        {
          "hex": "#4b4642",
          "name": "#4b4642",
          "reference": "vibrant"
        }
      ],
      "depicts": [
        1159160703
      ],
      "sizes": {
        "b": {
          "extension": "jpg",
          "height": 682,
          "mimetype": "image/jpeg",
          "secret": "aFhBuvN265QObSMlpsWDnRg0ph2vkU7i",
          "width": 1024
        },
        "c": {
          "extension": "jpg",
          "height": 533,
          "mimetype": "image/jpeg",
          "secret": "aFhBuvN265QObSMlpsWDnRg0ph2vkU7i",
          "width": 800
        },
        "dc": {
          "extension": "jpg",
          "height": 533,
          "mimetype": "image/jpeg",
          "secret": "aFhBuvN265QObSMlpsWDnRg0ph2vkU7i",
          "width": 800
        },
        "ds": {
          "extension": "jpg",
          "height": 320,
          "mimetype": "image/jpeg",
          "secret": "aFhBuvN265QObSMlpsWDnRg0ph2vkU7i",
          "width": 320
        },
        "k": {
          "extension": "jpg",
          "height": 1365,
          "mimetype": "image/jpeg",
          "secret": "aFhBuvN265QObSMlpsWDnRg0ph2vkU7i",
          "width": 2048
        },
        "n": {
          "extension": "jpg",
          "height": 213,
          "mimetype": "image/jpeg",
          "secret": "aFhBuvN265QObSMlpsWDnRg0ph2vkU7i",
          "width": 320
        },
        "o": {
          "extension": "jpg",
          "height": 2400,
          "mimetype": "image/jpeg",
          "secret": "WPoSkpny3RDyfFCfeMwLrDf9My0qF8jO",
          "width": 3600
        },
        "s": {
          "extension": "jpg",
          "height": 320,
          "mimetype": "image/jpeg",
          "secret": "aFhBuvN265QObSMlpsWDnRg0ph2vkU7i",
          "width": 320
        },
        "z": {
          "extension": "jpg",
          "height": 426,
          "mimetype": "image/jpeg",
          "secret": "aFhBuvN265QObSMlpsWDnRg0ph2vkU7i",
          "width": 640
        }
      }
    },
    "sfomuseum:placetype": "image",
    "wof:depicts": [
      1159157333,
      1159157335,
      1159268871,
      102527513,
      1159157037,
      1159160703,
      1159157271
    ],
    "wof:name": "Installation view of \"At Home with Arts and Crafts\"",
    "wof:placetype": "media"
  },
  "geometry": {"coordinates":[-122.389537,37.616642],"type":"Point"}
}
