{
  "type": "Feature",
  "properties": {
    "date:cessation_lower": "2012-08-06",
    "date:cessation_upper": "2012-08-06",
    "date:inception_lower": "2012-03-02",
    "date:inception_upper": "2012-03-02",
    "iso:country": "US",
    "media:created": 1342206752,
    "media:fingerprint": "2e2db13f90d7c49d0bfaf6f867861f1d59e985ac",
    "media:imagehash_avg": "a:00003fffffff0700",
    "media:imagehash_diff": "d:fefcece4ade9edff",
    "media:medium": "image",
    "media:mimetype": "image/jpeg",
    "media:placetype": "installation",
    "media:properties": {
      "colours": [
        {
          "hex": "#8b3a31",
          "name": "#8b3a31",
          "reference": "vibrant"
        },
        {
          "hex": "#7d7e84",
          "name": "#7d7e84",
          "reference": "vibrant"
        },
        {
          "hex": "#c2c1bb",
          "name": "#c2c1bb",
          "reference": "vibrant"
        },
        {
          "hex": "#3f3e45",
          "name": "#3f3e45",
          "reference": "vibrant"
        }
      ],
      "depicts": [
        1159160321
      ],
      "sizes": {
        "b": {
          "extension": "jpg",
          "height": 682,
          "mimetype": "image/jpeg",
          "secret": "pFbpKQYKgOPaRkUgEFgUO8M9mBf9fOQ7",
          "width": 1024
        },
        "c": {
          "extension": "jpg",
          "height": 533,
          "mimetype": "image/jpeg",
          "secret": "pFbpKQYKgOPaRkUgEFgUO8M9mBf9fOQ7",
          "width": 800
        },
        "dc": {
          "extension": "jpg",
          "height": 533,
          "mimetype": "image/jpeg",
          "secret": "pFbpKQYKgOPaRkUgEFgUO8M9mBf9fOQ7",
          "width": 800
        },
        "ds": {
          "extension": "jpg",
          "height": 320,
          "mimetype": "image/jpeg",
          "secret": "pFbpKQYKgOPaRkUgEFgUO8M9mBf9fOQ7",
          "width": 320
        },
        "k": {
          "extension": "jpg",
          "height": 1365,
          "mimetype": "image/jpeg",
          "secret": "pFbpKQYKgOPaRkUgEFgUO8M9mBf9fOQ7",
          "width": 2048
        },
        "n": {
          "extension": "jpg",
          "height": 213,
          "mimetype": "image/jpeg",
          "secret": "pFbpKQYKgOPaRkUgEFgUO8M9mBf9fOQ7",
          "width": 320
        },
        "o": {
          "extension": "jpg",
          "height": 2400,
          "mimetype": "image/jpeg",
          "secret": "AHdAPGHMRQFe5qW4C7j0w0u4bB9ic1KI",
          "width": 3600
        },
        "s": {
          "extension": "jpg",
          "height": 320,
          "mimetype": "image/jpeg",
          "secret": "pFbpKQYKgOPaRkUgEFgUO8M9mBf9fOQ7",
          "width": 320
        },
        "z": {
          "extension": "jpg",
          "height": 426,
          "mimetype": "image/jpeg",
          "secret": "pFbpKQYKgOPaRkUgEFgUO8M9mBf9fOQ7",
          "width": 640
        }
      }
    },
    "sfomuseum:placetype": "image",
    "wof:depicts": [
      1360516121,
      1159160321,
      1159396141,
      1159396333,
      102527513,
      1159396295
    ],
    "wof:name": "Installation view of \"Threading the Needle: Sewing in the Machine Age\"",
    "wof:placetype": "custom",
    "wof:placetype_alt": [
      "image"
    ]
  },
  "geometry": {"type":"Point","coordinates":[-122.387197,37.619087]}
}
