{
  "type": "Feature", 
  "properties": {
    "iso:country": "US", 
    "media:created": -1, 
    "media:fingerprint": "38e740eb8af80c9d7a2a72807a163c93c4d42f66", 
    "media:medium": "image", 
    "media:mimetype": "image/tiff", 
    "media:properties": {
      "colours": [
        {
          "hex": "#e2d6ab", 
          "name": "#e2d6ab", 
          "reference": "vibrant"
        }, 
        {
          "hex": "#8c7c74", 
          "name": "#8c7c74", 
          "reference": "vibrant"
        }, 
        {
          "hex": "#c6caaf", 
          "name": "#c6caaf", 
          "reference": "vibrant"
        }, 
        {
          "hex": "#41363f", 
          "name": "#41363f", 
          "reference": "vibrant"
        }
      ], 
      "depicts": [1226607773], 
      "sizes": {
        "b": {
          "extension": "jpg", 
          "height": 768, 
          "mimetype": "image/jpeg", 
          "secret": "oZLREJhrojOgYWpibumaeaY7SH5LzvRg", 
          "width": 544
        }, 
        "c": {
          "extension": "jpg", 
          "height": 600, 
          "mimetype": "image/jpeg", 
          "secret": "oZLREJhrojOgYWpibumaeaY7SH5LzvRg", 
          "width": 425
        }, 
        "dc": {
          "extension": "jpg", 
          "height": 600, 
          "mimetype": "image/jpeg", 
          "secret": "oZLREJhrojOgYWpibumaeaY7SH5LzvRg", 
          "width": 425
        }, 
        "ds": {
          "extension": "jpg", 
          "height": 320, 
          "mimetype": "image/jpeg", 
          "secret": "oZLREJhrojOgYWpibumaeaY7SH5LzvRg", 
          "width": 320
        }, 
        "k": {
          "extension": "jpg", 
          "height": 1536, 
          "mimetype": "image/jpeg", 
          "secret": "oZLREJhrojOgYWpibumaeaY7SH5LzvRg", 
          "width": 1089
        }, 
        "n": {
          "extension": "jpg", 
          "height": 240, 
          "mimetype": "image/jpeg", 
          "secret": "oZLREJhrojOgYWpibumaeaY7SH5LzvRg", 
          "width": 170
        }, 
        "o": {
          "extension": "jpg", 
          "height": 4251, 
          "mimetype": "image/jpeg", 
          "secret": "VU1TXeZBeopGc5Ne1rfo6CVwpX2nrgIk", 
          "width": 3014
        }, 
        "s": {
          "extension": "jpg", 
          "height": 320, 
          "mimetype": "image/jpeg", 
          "secret": "oZLREJhrojOgYWpibumaeaY7SH5LzvRg", 
          "width": 320
        }, 
        "z": {
          "extension": "jpg", 
          "height": 480, 
          "mimetype": "image/jpeg", 
          "secret": "oZLREJhrojOgYWpibumaeaY7SH5LzvRg", 
          "width": 340
        }
      }
    }, 
    "sfomuseum:placetype": "image", 
    "wof:depicts": [1226607773, 1159554829, 1360516471, 102527513, 1159554803], 
    "wof:name": "Installation view of \"Bowling: A Unique American Art Form\"", 
    "wof:placetype": "media" 
  }, 
  "geometry": {"coordinates":[-122.38274,37.617227],"type":"Point"}
}
