{
  "type": "Feature", 
  "properties": {
    "iso:country": "US", 
    "media:created": 1038005721, 
    "media:fingerprint": "3f1eb0c1f2667f22dd63f21b71c3f682c40b07b8", 
    "media:medium": "image", 
    "media:mimetype": "image/jpeg", 
    "media:properties": {
      "colours": [
        {
          "hex": "#a04d38", 
          "name": "#a04d38", 
          "reference": "vibrant"
        }, 
        {
          "hex": "#9b745e", 
          "name": "#9b745e", 
          "reference": "vibrant"
        }, 
        {
          "hex": "#c5cbc0", 
          "name": "#c5cbc0", 
          "reference": "vibrant"
        }, 
        {
          "hex": "#43463b", 
          "name": "#43463b", 
          "reference": "vibrant"
        }
      ], 
      "depicts": [1159159445], 
      "sizes": {
        "b": {
          "extension": "jpg", 
          "height": 768, 
          "mimetype": "image/jpeg", 
          "secret": "MDXNWtmIu3qw7viG1VnSXcIdyY5yQ6ZC", 
          "width": 1024
        }, 
        "c": {
          "extension": "jpg", 
          "height": 600, 
          "mimetype": "image/jpeg", 
          "secret": "MDXNWtmIu3qw7viG1VnSXcIdyY5yQ6ZC", 
          "width": 800
        }, 
        "dc": {
          "extension": "jpg", 
          "height": 600, 
          "mimetype": "image/jpeg", 
          "secret": "MDXNWtmIu3qw7viG1VnSXcIdyY5yQ6ZC", 
          "width": 800
        }, 
        "ds": {
          "extension": "jpg", 
          "height": 320, 
          "mimetype": "image/jpeg", 
          "secret": "MDXNWtmIu3qw7viG1VnSXcIdyY5yQ6ZC", 
          "width": 320
        }, 
        "k": {
          "extension": "jpg", 
          "height": 1536, 
          "mimetype": "image/jpeg", 
          "secret": "MDXNWtmIu3qw7viG1VnSXcIdyY5yQ6ZC", 
          "width": 2048
        }, 
        "n": {
          "extension": "jpg", 
          "height": 240, 
          "mimetype": "image/jpeg", 
          "secret": "MDXNWtmIu3qw7viG1VnSXcIdyY5yQ6ZC", 
          "width": 320
        }, 
        "o": {
          "extension": "jpg", 
          "height": 1200, 
          "mimetype": "image/jpeg", 
          "secret": "fvZXDHGyuVKBdhiBhCYZKhsJ9DuzRXH5", 
          "width": 1600
        }, 
        "s": {
          "extension": "jpg", 
          "height": 320, 
          "mimetype": "image/jpeg", 
          "secret": "MDXNWtmIu3qw7viG1VnSXcIdyY5yQ6ZC", 
          "width": 320
        }, 
        "z": {
          "extension": "jpg", 
          "height": 480, 
          "mimetype": "image/jpeg", 
          "secret": "MDXNWtmIu3qw7viG1VnSXcIdyY5yQ6ZC", 
          "width": 640
        }
      }
    }, 
    "sfomuseum:placetype": "image", 
    "wof:depicts": [1159159445, 1360521543, 1159396319, 102527513, 1360521557], 
    "wof:name": "Installation view of \"Mapping America\"", 
    "wof:placetype": "media" 
  }, 
  "geometry": {"coordinates":[-122.38274,37.617227],"type":"Point"}
}
