{
  "type": "Feature", 
  "properties": {
    "iso:country": "US", 
    "media:created": 1521670110, 
    "media:fingerprint": "def76db8a9bb2095e9896099e0b4528c9d6193e4", 
    "media:medium": "image", 
    "media:mimetype": "image/jpeg", 
    "media:properties": {
      "colours": [
        {
          "hex": "#d63838", 
          "name": "#d63838", 
          "reference": "vibrant"
        }, 
        {
          "hex": "#ebbb4e", 
          "name": "#ebbb4e", 
          "reference": "vibrant"
        }, 
        {
          "hex": "#b82a31", 
          "name": "#b82a31", 
          "reference": "vibrant"
        }, 
        {
          "hex": "#9e7668", 
          "name": "#9e7668", 
          "reference": "vibrant"
        }, 
        {
          "hex": "#b1bdc5", 
          "name": "#b1bdc5", 
          "reference": "vibrant"
        }
      ], 
      "depicts": [1159160853], 
      "sizes": {
        "b": {
          "extension": "jpg", 
          "height": 682, 
          "mimetype": "image/jpeg", 
          "secret": "lh97KW5qR7BE2JMiWMGhOchakqwfTrSn", 
          "width": 1024
        }, 
        "c": {
          "extension": "jpg", 
          "height": 533, 
          "mimetype": "image/jpeg", 
          "secret": "lh97KW5qR7BE2JMiWMGhOchakqwfTrSn", 
          "width": 800
        }, 
        "dc": {
          "extension": "jpg", 
          "height": 533, 
          "mimetype": "image/jpeg", 
          "secret": "lh97KW5qR7BE2JMiWMGhOchakqwfTrSn", 
          "width": 800
        }, 
        "ds": {
          "extension": "jpg", 
          "height": 320, 
          "mimetype": "image/jpeg", 
          "secret": "lh97KW5qR7BE2JMiWMGhOchakqwfTrSn", 
          "width": 320
        }, 
        "k": {
          "extension": "jpg", 
          "height": 1365, 
          "mimetype": "image/jpeg", 
          "secret": "lh97KW5qR7BE2JMiWMGhOchakqwfTrSn", 
          "width": 2048
        }, 
        "n": {
          "extension": "jpg", 
          "height": 213, 
          "mimetype": "image/jpeg", 
          "secret": "lh97KW5qR7BE2JMiWMGhOchakqwfTrSn", 
          "width": 320
        }, 
        "o": {
          "extension": "jpg", 
          "height": 2400, 
          "mimetype": "image/jpeg", 
          "secret": "jhT2pF7rHOzx5Sfd8r9cOvCaeSWvAj87", 
          "width": 3600
        }, 
        "s": {
          "extension": "jpg", 
          "height": 320, 
          "mimetype": "image/jpeg", 
          "secret": "lh97KW5qR7BE2JMiWMGhOchakqwfTrSn", 
          "width": 320
        }, 
        "z": {
          "extension": "jpg", 
          "height": 426, 
          "mimetype": "image/jpeg", 
          "secret": "lh97KW5qR7BE2JMiWMGhOchakqwfTrSn", 
          "width": 640
        }
      }
    }, 
    "sfomuseum:placetype": "image", 
    "wof:depicts": [
      1159160853, 
      1159157307, 
      102527513, 
      1159157053, 
      1159396301, 
      1159157271
    ], 
    "wof:name": "Installation view of \"On the Radio\"", 
    "wof:placetype": "media" 
  }, 
  "geometry": {"coordinates":[-122.387197,37.619087],"type":"Point"}
}
