{
  "type": "Feature",
  "properties": {
    "iso:country": "US",
    "media:created": 1093628361,
    "media:fingerprint": "5b1536628a83750bdcdb49f4bdff4d94ed3399cd",
    "media:imagehash_avg": "a:061f3d1b1f083c3e",
    "media:imagehash_diff": "d:fcfcf1f7f7f5f8f8",
    "media:medium": "image",
    "media:mimetype": "image/jpeg",
    "media:properties": {
      "colours": [
        {
          "hex": "#b95c31",
          "name": "#b95c31",
          "reference": "vibrant"
        }, 
        {
          "hex": "#923a1f",
          "name": "#923a1f",
          "reference": "vibrant"
        }, 
        {
          "hex": "#84785b",
          "name": "#84785b",
          "reference": "vibrant"
        }, 
        {
          "hex": "#bebfb2",
          "name": "#bebfb2",
          "reference": "vibrant"
        }, 
        {
          "hex": "#464540",
          "name": "#464540",
          "reference": "vibrant"
        }
      ],
      "depicts": [
        1159159593
      ],
      "sizes": {
        "b": {
          "extension": "jpg",
          "height": 768,
          "mimetype": "image/jpeg",
          "secret": "d8FBbtEcrmi1p2pvFfNJtAScmtsQf0JF",
          "width": 1024
        },
        "c": {
          "extension": "jpg",
          "height": 600,
          "mimetype": "image/jpeg",
          "secret": "d8FBbtEcrmi1p2pvFfNJtAScmtsQf0JF",
          "width": 800
        },
        "dc": {
          "extension": "jpg",
          "height": 600,
          "mimetype": "image/jpeg",
          "secret": "d8FBbtEcrmi1p2pvFfNJtAScmtsQf0JF",
          "width": 800
        },
        "ds": {
          "extension": "jpg",
          "height": 320,
          "mimetype": "image/jpeg",
          "secret": "d8FBbtEcrmi1p2pvFfNJtAScmtsQf0JF",
          "width": 320
        },
        "k": {
          "extension": "jpg",
          "height": 1536,
          "mimetype": "image/jpeg",
          "secret": "d8FBbtEcrmi1p2pvFfNJtAScmtsQf0JF",
          "width": 2048
        },
        "n": {
          "extension": "jpg",
          "height": 240,
          "mimetype": "image/jpeg",
          "secret": "d8FBbtEcrmi1p2pvFfNJtAScmtsQf0JF",
          "width": 320
        },
        "o": {
          "extension": "jpg",
          "height": 1920,
          "mimetype": "image/jpeg",
          "secret": "lrETv2EM2pXxak0blNgjGtXxJOzWrvQ5",
          "width": 2560
        },
        "s": {
          "extension": "jpg",
          "height": 320,
          "mimetype": "image/jpeg",
          "secret": "d8FBbtEcrmi1p2pvFfNJtAScmtsQf0JF",
          "width": 320
        },
        "z": {
          "extension": "jpg",
          "height": 480,
          "mimetype": "image/jpeg",
          "secret": "d8FBbtEcrmi1p2pvFfNJtAScmtsQf0JF",
          "width": 640
        }
      }
    },
    "sfomuseum:placetype": "image",
    "wof:depicts": [
      1360516477, 
      1159159593, 
      1159396115, 
      1159396319, 
      102527513
    ],
    "wof:name": "Installation view of \"The Flight Bag: Icon of Air Travel\"",
    "wof:placetype": "media"
  },
  "geometry": {"coordinates":[-122.385472,37.613926],"type":"Point"}
}
