{
  "type": "Feature", 
  "properties": {
    "iso:country": "US", 
    "media:created": 1502476811, 
    "media:fingerprint": "f6bd4fe5cc2d454058bfc405a57ae0a3ae8eefab", 
    "media:medium": "image", 
    "media:mimetype": "image/jpeg", 
    "media:properties": {
      "colours": [
        {
          "hex": "#d34f39", 
          "name": "#d34f39", 
          "reference": "vibrant"
        }, 
        {
          "hex": "#d6ba94", 
          "name": "#d6ba94", 
          "reference": "vibrant"
        }, 
        {
          "hex": "#154a72", 
          "name": "#154a72", 
          "reference": "vibrant"
        }, 
        {
          "hex": "#a08056", 
          "name": "#a08056", 
          "reference": "vibrant"
        }, 
        {
          "hex": "#d8c8ac", 
          "name": "#d8c8ac", 
          "reference": "vibrant"
        }
      ], 
      "depicts": [1159160129], 
      "sizes": {
        "b": {
          "extension": "jpg", 
          "height": 768, 
          "mimetype": "image/jpeg", 
          "secret": "5tbQh3rFPpjNqMHRMpRdRkuzdQ3XRbYB", 
          "width": 512
        }, 
        "c": {
          "extension": "jpg", 
          "height": 600, 
          "mimetype": "image/jpeg", 
          "secret": "5tbQh3rFPpjNqMHRMpRdRkuzdQ3XRbYB", 
          "width": 400
        }, 
        "dc": {
          "extension": "jpg", 
          "height": 600, 
          "mimetype": "image/jpeg", 
          "secret": "5tbQh3rFPpjNqMHRMpRdRkuzdQ3XRbYB", 
          "width": 400
        }, 
        "ds": {
          "extension": "jpg", 
          "height": 320, 
          "mimetype": "image/jpeg", 
          "secret": "5tbQh3rFPpjNqMHRMpRdRkuzdQ3XRbYB", 
          "width": 320
        }, 
        "k": {
          "extension": "jpg", 
          "height": 1536, 
          "mimetype": "image/jpeg", 
          "secret": "5tbQh3rFPpjNqMHRMpRdRkuzdQ3XRbYB", 
          "width": 1024
        }, 
        "n": {
          "extension": "jpg", 
          "height": 240, 
          "mimetype": "image/jpeg", 
          "secret": "5tbQh3rFPpjNqMHRMpRdRkuzdQ3XRbYB", 
          "width": 160
        }, 
        "o": {
          "extension": "jpg", 
          "height": 2400, 
          "mimetype": "image/jpeg", 
          "secret": "gRfQupOXw5jzWDryMequUR53GHZTpSCG", 
          "width": 1600
        }, 
        "s": {
          "extension": "jpg", 
          "height": 320, 
          "mimetype": "image/jpeg", 
          "secret": "5tbQh3rFPpjNqMHRMpRdRkuzdQ3XRbYB", 
          "width": 320
        }, 
        "z": {
          "extension": "jpg", 
          "height": 480, 
          "mimetype": "image/jpeg", 
          "secret": "5tbQh3rFPpjNqMHRMpRdRkuzdQ3XRbYB", 
          "width": 320
        }
      }
    }, 
    "sfomuseum:placetype": "image", 
    "wof:depicts": [1159160129, 1159396321, 1159396153, 1360516199, 102527513], 
    "wof:name": "Installation view of \"Fashion in Flight: A History of Airline Uniform Design\"", 
    "wof:placetype": "media" 
  }, 
  "geometry": {"coordinates":[-122.389267,37.615645],"type":"Point"}
}
