{
  "type": "Feature", 
  "properties": {
    "iso:country": "US", 
    "media:created": -1, 
    "media:fingerprint": "0d813929cae9ca5dfa83cf2fe6994120b33e37d6", 
    "media:medium": "image", 
    "media:mimetype": "image/tiff", 
    "media:properties": {
      "colours": [
        {
          "hex": "#7e8870", 
          "name": "#7e8870", 
          "reference": "vibrant"
        }, 
        {
          "hex": "#b1bdc0", 
          "name": "#b1bdc0", 
          "reference": "vibrant"
        }, 
        {
          "hex": "#3e3a4b", 
          "name": "#3e3a4b", 
          "reference": "vibrant"
        }
      ], 
      "depicts": [1376812951], 
      "sizes": {
        "b": {
          "extension": "jpg", 
          "height": 726, 
          "mimetype": "image/jpeg", 
          "secret": "fn9EVlXmfiGAc47nwJCr3gRo2GsLN8Fx", 
          "width": 1024
        }, 
        "c": {
          "extension": "jpg", 
          "height": 567, 
          "mimetype": "image/jpeg", 
          "secret": "fn9EVlXmfiGAc47nwJCr3gRo2GsLN8Fx", 
          "width": 800
        }, 
        "dc": {
          "extension": "jpg", 
          "height": 567, 
          "mimetype": "image/jpeg", 
          "secret": "fn9EVlXmfiGAc47nwJCr3gRo2GsLN8Fx", 
          "width": 800
        }, 
        "ds": {
          "extension": "jpg", 
          "height": 320, 
          "mimetype": "image/jpeg", 
          "secret": "fn9EVlXmfiGAc47nwJCr3gRo2GsLN8Fx", 
          "width": 320
        }, 
        "k": {
          "extension": "jpg", 
          "height": 1452, 
          "mimetype": "image/jpeg", 
          "secret": "fn9EVlXmfiGAc47nwJCr3gRo2GsLN8Fx", 
          "width": 2048
        }, 
        "n": {
          "extension": "jpg", 
          "height": 226, 
          "mimetype": "image/jpeg", 
          "secret": "fn9EVlXmfiGAc47nwJCr3gRo2GsLN8Fx", 
          "width": 320
        }, 
        "o": {
          "extension": "jpg", 
          "height": 3014, 
          "mimetype": "image/jpeg", 
          "secret": "WyPaBzMS3bYJFJKDxlDQlbWvZRMPbpr4", 
          "width": 4251
        }, 
        "s": {
          "extension": "jpg", 
          "height": 320, 
          "mimetype": "image/jpeg", 
          "secret": "fn9EVlXmfiGAc47nwJCr3gRo2GsLN8Fx", 
          "width": 320
        }, 
        "z": {
          "extension": "jpg", 
          "height": 453, 
          "mimetype": "image/jpeg", 
          "secret": "fn9EVlXmfiGAc47nwJCr3gRo2GsLN8Fx", 
          "width": 640
        }
      }
    }, 
    "sfomuseum:placetype": "image", 
    "wof:depicts": [
      1159554803, 
      1376812951, 
      102527513, 
      1159554855, 
      1159554821, 
      1360516127
    ], 
    "wof:name": "Installation view of \"Before the 21st Century: An Ode to Boats, Cars, Motorcycles, Planes, and Trains\"", 
    "wof:placetype": "media" 
  }, 
  "geometry": {"coordinates":[-122.387197,37.619087],"type":"Point"}
}
