{
  "type": "Feature",
  "properties": {
    "date:cessation_lower": "1997-04-24",
    "date:cessation_upper": "1997-04-24",
    "date:inception_lower": "1996-11-07",
    "date:inception_upper": "1996-11-07",
    "iso:country": "US",
    "media:created": -1,
    "media:fingerprint": "098c5b55f452990620ea40aa50c459fa676c8e6d",
    "media:imagehash_avg": "a:0038383c3f321000",
    "media:imagehash_diff": "d:f0e0f2e4e6e6f0e0",
    "media:medium": "image",
    "media:mimetype": "image/tiff",
    "media:placetype": "installation",
    "media:properties": {
      "colours": [
        {
          "hex": "#77898b",
          "name": "#77898b",
          "reference": "vibrant"
        },
        {
          "hex": "#acb9bd",
          "name": "#acb9bd",
          "reference": "vibrant"
        },
        {
          "hex": "#67513b",
          "name": "#67513b",
          "reference": "vibrant"
        }
      ],
      "depicts": [
        1226603769
      ],
      "sizes": {
        "b": {
          "extension": "jpg",
          "height": 726,
          "mimetype": "image/jpeg",
          "secret": "9Fx4wlpBDVlTAyKjGzFkPen6q8g2NwWs",
          "width": 1024
        },
        "c": {
          "extension": "jpg",
          "height": 567,
          "mimetype": "image/jpeg",
          "secret": "9Fx4wlpBDVlTAyKjGzFkPen6q8g2NwWs",
          "width": 800
        },
        "dc": {
          "extension": "jpg",
          "height": 567,
          "mimetype": "image/jpeg",
          "secret": "9Fx4wlpBDVlTAyKjGzFkPen6q8g2NwWs",
          "width": 800
        },
        "ds": {
          "extension": "jpg",
          "height": 320,
          "mimetype": "image/jpeg",
          "secret": "9Fx4wlpBDVlTAyKjGzFkPen6q8g2NwWs",
          "width": 320
        },
        "k": {
          "extension": "jpg",
          "height": 1452,
          "mimetype": "image/jpeg",
          "secret": "9Fx4wlpBDVlTAyKjGzFkPen6q8g2NwWs",
          "width": 2048
        },
        "n": {
          "extension": "jpg",
          "height": 226,
          "mimetype": "image/jpeg",
          "secret": "9Fx4wlpBDVlTAyKjGzFkPen6q8g2NwWs",
          "width": 320
        },
        "o": {
          "extension": "jpg",
          "height": 3014,
          "mimetype": "image/jpeg",
          "secret": "fMr75tqSAQtxnJ5AdjpMswuzvzIK3PTy",
          "width": 4251
        },
        "s": {
          "extension": "jpg",
          "height": 320,
          "mimetype": "image/jpeg",
          "secret": "9Fx4wlpBDVlTAyKjGzFkPen6q8g2NwWs",
          "width": 320
        },
        "z": {
          "extension": "jpg",
          "height": 453,
          "mimetype": "image/jpeg",
          "secret": "9Fx4wlpBDVlTAyKjGzFkPen6q8g2NwWs",
          "width": 640
        }
      }
    },
    "sfomuseum:placetype": "image",
    "wof:depicts": [
      1226603769,
      102527513,
      1159554817,
      1159554803,
      1159157883
    ],
    "wof:name": "Installation view of \"Barbie® Takes A Vacation to Exotic Places\"",
    "wof:placetype": "media",
    "wof:placetype_alt": [
      "image"
    ]
  },
  "geometry": {"coordinates":[-122.385472,37.613926],"type":"Point"}
}
