{
  "type": "Feature", 
  "properties": {
    "iso:country": "US", 
    "media:created": 1477414835, 
    "media:fingerprint": "766dff692cc13940422f26edd9ac0459ed688fe8", 
    "media:medium": "image", 
    "media:mimetype": "image/jpeg", 
    "media:properties": {
      "colours": [
        {
          "hex": "#ad6e29", 
          "name": "#ad6e29", 
          "reference": "vibrant"
        }, 
        {
          "hex": "#d3ab77", 
          "name": "#d3ab77", 
          "reference": "vibrant"
        }, 
        {
          "hex": "#623a1d", 
          "name": "#623a1d", 
          "reference": "vibrant"
        }, 
        {
          "hex": "#b08655", 
          "name": "#b08655", 
          "reference": "vibrant"
        }, 
        {
          "hex": "#d4c3b4", 
          "name": "#d4c3b4", 
          "reference": "vibrant"
        }
      ], 
      "depicts": [1226619799], 
      "sizes": {
        "b": {
          "extension": "jpg", 
          "height": 682, 
          "mimetype": "image/jpeg", 
          "secret": "ad31wHrzVEhF3nybWvzmI51GRlWReEDQ", 
          "width": 1024
        }, 
        "c": {
          "extension": "jpg", 
          "height": 533, 
          "mimetype": "image/jpeg", 
          "secret": "ad31wHrzVEhF3nybWvzmI51GRlWReEDQ", 
          "width": 800
        }, 
        "dc": {
          "extension": "jpg", 
          "height": 533, 
          "mimetype": "image/jpeg", 
          "secret": "ad31wHrzVEhF3nybWvzmI51GRlWReEDQ", 
          "width": 800
        }, 
        "ds": {
          "extension": "jpg", 
          "height": 320, 
          "mimetype": "image/jpeg", 
          "secret": "ad31wHrzVEhF3nybWvzmI51GRlWReEDQ", 
          "width": 320
        }, 
        "k": {
          "extension": "jpg", 
          "height": 1365, 
          "mimetype": "image/jpeg", 
          "secret": "ad31wHrzVEhF3nybWvzmI51GRlWReEDQ", 
          "width": 2048
        }, 
        "n": {
          "extension": "jpg", 
          "height": 213, 
          "mimetype": "image/jpeg", 
          "secret": "ad31wHrzVEhF3nybWvzmI51GRlWReEDQ", 
          "width": 320
        }, 
        "o": {
          "extension": "jpg", 
          "height": 2400, 
          "mimetype": "image/jpeg", 
          "secret": "QpJf8R1ZBrtDxuW9gtDFJyj8cANVMOV8", 
          "width": 3600
        }, 
        "s": {
          "extension": "jpg", 
          "height": 320, 
          "mimetype": "image/jpeg", 
          "secret": "ad31wHrzVEhF3nybWvzmI51GRlWReEDQ", 
          "width": 320
        }, 
        "z": {
          "extension": "jpg", 
          "height": 426, 
          "mimetype": "image/jpeg", 
          "secret": "ad31wHrzVEhF3nybWvzmI51GRlWReEDQ", 
          "width": 640
        }
      }
    }, 
    "sfomuseum:placetype": "image", 
    "wof:depicts": [
      1159157325, 
      1159396321, 
      1226619799, 
      102527513, 
      1159396193, 
      1360516255
    ], 
    "wof:name": "Installation view of \"The Mysterious Talking Board: Ouija and Beyond\"", 
    "wof:placetype": "media" 
  }, 
  "geometry": {"coordinates":[-122.382712,37.617422],"type":"Point"}
}
