{
  "type": "Feature", 
  "properties": {
    "iso:country": "US", 
    "media:created": 1455292912, 
    "media:fingerprint": "062bd6ac1597c5e181fc59395a73fb8db8855b6f", 
    "media:medium": "image", 
    "media:mimetype": "image/jpeg", 
    "media:properties": {
      "colours": [
        {
          "hex": "#bbaa48", 
          "name": "#bbaa48", 
          "reference": "vibrant"
        }, 
        {
          "hex": "#655a24", 
          "name": "#655a24", 
          "reference": "vibrant"
        }, 
        {
          "hex": "#b1a557", 
          "name": "#b1a557", 
          "reference": "vibrant"
        }, 
        {
          "hex": "#c8bf99", 
          "name": "#c8bf99", 
          "reference": "vibrant"
        }, 
        {
          "hex": "#47432f", 
          "name": "#47432f", 
          "reference": "vibrant"
        }
      ], 
      "depicts": [1159160545], 
      "sizes": {
        "b": {
          "extension": "jpg", 
          "height": 768, 
          "mimetype": "image/jpeg", 
          "secret": "1mXafQCslZUwjksLMcE9kcer1dslFYgW", 
          "width": 614
        }, 
        "c": {
          "extension": "jpg", 
          "height": 600, 
          "mimetype": "image/jpeg", 
          "secret": "1mXafQCslZUwjksLMcE9kcer1dslFYgW", 
          "width": 480
        }, 
        "dc": {
          "extension": "jpg", 
          "height": 600, 
          "mimetype": "image/jpeg", 
          "secret": "1mXafQCslZUwjksLMcE9kcer1dslFYgW", 
          "width": 480
        }, 
        "ds": {
          "extension": "jpg", 
          "height": 320, 
          "mimetype": "image/jpeg", 
          "secret": "1mXafQCslZUwjksLMcE9kcer1dslFYgW", 
          "width": 320
        }, 
        "k": {
          "extension": "jpg", 
          "height": 1536, 
          "mimetype": "image/jpeg", 
          "secret": "1mXafQCslZUwjksLMcE9kcer1dslFYgW", 
          "width": 1228
        }, 
        "n": {
          "extension": "jpg", 
          "height": 240, 
          "mimetype": "image/jpeg", 
          "secret": "1mXafQCslZUwjksLMcE9kcer1dslFYgW", 
          "width": 192
        }, 
        "o": {
          "extension": "jpg", 
          "height": 3600, 
          "mimetype": "image/jpeg", 
          "secret": "Wnew7lG9OgTYXwRqcRkz5OFrHif2Tg6h", 
          "width": 2880
        }, 
        "s": {
          "extension": "jpg", 
          "height": 320, 
          "mimetype": "image/jpeg", 
          "secret": "1mXafQCslZUwjksLMcE9kcer1dslFYgW", 
          "width": 320
        }, 
        "z": {
          "extension": "jpg", 
          "height": 480, 
          "mimetype": "image/jpeg", 
          "secret": "1mXafQCslZUwjksLMcE9kcer1dslFYgW", 
          "width": 384
        }
      }
    }, 
    "sfomuseum:placetype": "image", 
    "wof:depicts": [102527513, 1360516281, 1159396153, 1159160545, 1159396321], 
    "wof:name": "Installation view of \"The Allure of Art Nouveau:1890-1914\"", 
    "wof:placetype": "media" 
  }, 
  "geometry": {"coordinates":[-122.389725,37.616594],"type":"Point"}
}
