{
  "type": "Feature", 
  "properties": {
    "iso:country": "US", 
    "media:created": -1, 
    "media:fingerprint": "9e5c74dc81093675ddc3bcdb641f5a6ffad4e01e", 
    "media:medium": "image", 
    "media:mimetype": "image/tiff", 
    "media:properties": {
      "colours": [
        {
          "hex": "#65362e", 
          "name": "#65362e", 
          "reference": "vibrant"
        }, 
        {
          "hex": "#7b8186", 
          "name": "#7b8186", 
          "reference": "vibrant"
        }, 
        {
          "hex": "#c4b8bf", 
          "name": "#c4b8bf", 
          "reference": "vibrant"
        }, 
        {
          "hex": "#533736", 
          "name": "#533736", 
          "reference": "vibrant"
        }
      ], 
      "depicts": [1226611157], 
      "sizes": {
        "b": {
          "extension": "jpg", 
          "height": 726, 
          "mimetype": "image/jpeg", 
          "secret": "UhpCpeDQBAMLnD1Y1Z8j3pz4TMSVoy2F", 
          "width": 1024
        }, 
        "c": {
          "extension": "jpg", 
          "height": 567, 
          "mimetype": "image/jpeg", 
          "secret": "UhpCpeDQBAMLnD1Y1Z8j3pz4TMSVoy2F", 
          "width": 800
        }, 
        "dc": {
          "extension": "jpg", 
          "height": 567, 
          "mimetype": "image/jpeg", 
          "secret": "UhpCpeDQBAMLnD1Y1Z8j3pz4TMSVoy2F", 
          "width": 800
        }, 
        "ds": {
          "extension": "jpg", 
          "height": 320, 
          "mimetype": "image/jpeg", 
          "secret": "UhpCpeDQBAMLnD1Y1Z8j3pz4TMSVoy2F", 
          "width": 320
        }, 
        "k": {
          "extension": "jpg", 
          "height": 1452, 
          "mimetype": "image/jpeg", 
          "secret": "UhpCpeDQBAMLnD1Y1Z8j3pz4TMSVoy2F", 
          "width": 2048
        }, 
        "n": {
          "extension": "jpg", 
          "height": 226, 
          "mimetype": "image/jpeg", 
          "secret": "UhpCpeDQBAMLnD1Y1Z8j3pz4TMSVoy2F", 
          "width": 320
        }, 
        "o": {
          "extension": "jpg", 
          "height": 3014, 
          "mimetype": "image/jpeg", 
          "secret": "Vt1s0VrpliI56A8Ppk8EOEWKEbUyTnzK", 
          "width": 4251
        }, 
        "s": {
          "extension": "jpg", 
          "height": 320, 
          "mimetype": "image/jpeg", 
          "secret": "UhpCpeDQBAMLnD1Y1Z8j3pz4TMSVoy2F", 
          "width": 320
        }, 
        "z": {
          "extension": "jpg", 
          "height": 453, 
          "mimetype": "image/jpeg", 
          "secret": "UhpCpeDQBAMLnD1Y1Z8j3pz4TMSVoy2F", 
          "width": 640
        }
      }
    }, 
    "sfomuseum:placetype": "image", 
    "wof:depicts": [
      1159554803, 
      1159554821, 
      1159554855, 
      1360516127, 
      102527513, 
      1226611157
    ], 
    "wof:name": "Installation view of \"Boomerang\"", 
    "wof:placetype": "media" 
  }, 
  "geometry": {"coordinates":[-122.387197,37.619087],"type":"Point"}
}
