{
  "type": "Feature",
  "properties": {
    "date:cessation_lower": "1996-09-15",
    "date:cessation_upper": "1996-09-15",
    "date:inception_lower": "1996-03-15",
    "date:inception_upper": "1996-03-15",
    "iso:country": "US",
    "media:created": -1,
    "media:fingerprint": "35f860a6297582a0ae4ac0e1666c1432af055184",
    "media:imagehash_avg": "a:60fcfcfc7c000000",
    "media:imagehash_diff": "d:8088a0a0e8f8bc8a",
    "media:medium": "image",
    "media:mimetype": "image/tiff",
    "media:placetype": "installation",
    "media:properties": {
      "colours": [
        {
          "hex": "#451e1d",
          "name": "#451e1d",
          "reference": "vibrant"
        },
        {
          "hex": "#767888",
          "name": "#767888",
          "reference": "vibrant"
        },
        {
          "hex": "#b2b5c2",
          "name": "#b2b5c2",
          "reference": "vibrant"
        },
        {
          "hex": "#4f382c",
          "name": "#4f382c",
          "reference": "vibrant"
        }
      ],
      "depicts": [
        1226611157
      ],
      "sizes": {
        "b": {
          "extension": "jpg",
          "height": 768,
          "mimetype": "image/jpeg",
          "secret": "068grg96WoIz9kHMSHXmFwL828Q8zAL0",
          "width": 544
        },
        "c": {
          "extension": "jpg",
          "height": 600,
          "mimetype": "image/jpeg",
          "secret": "068grg96WoIz9kHMSHXmFwL828Q8zAL0",
          "width": 425
        },
        "dc": {
          "extension": "jpg",
          "height": 600,
          "mimetype": "image/jpeg",
          "secret": "068grg96WoIz9kHMSHXmFwL828Q8zAL0",
          "width": 425
        },
        "ds": {
          "extension": "jpg",
          "height": 320,
          "mimetype": "image/jpeg",
          "secret": "068grg96WoIz9kHMSHXmFwL828Q8zAL0",
          "width": 320
        },
        "k": {
          "extension": "jpg",
          "height": 1536,
          "mimetype": "image/jpeg",
          "secret": "068grg96WoIz9kHMSHXmFwL828Q8zAL0",
          "width": 1089
        },
        "n": {
          "extension": "jpg",
          "height": 240,
          "mimetype": "image/jpeg",
          "secret": "068grg96WoIz9kHMSHXmFwL828Q8zAL0",
          "width": 170
        },
        "o": {
          "extension": "jpg",
          "height": 4251,
          "mimetype": "image/jpeg",
          "secret": "DU2bvd5jmim42SZQeMjRNuYhFwqa26Dm",
          "width": 3014
        },
        "s": {
          "extension": "jpg",
          "height": 320,
          "mimetype": "image/jpeg",
          "secret": "068grg96WoIz9kHMSHXmFwL828Q8zAL0",
          "width": 320
        },
        "z": {
          "extension": "jpg",
          "height": 480,
          "mimetype": "image/jpeg",
          "secret": "068grg96WoIz9kHMSHXmFwL828Q8zAL0",
          "width": 340
        }
      }
    },
    "sfomuseum:placetype": "image",
    "wof:depicts": [
      1159554821,
      1226611157,
      102527513,
      1159554803,
      1159554855,
      1360516127
    ],
    "wof:name": "Installation view of \"Boomerang\"",
    "wof:placetype": "media"
  },
  "geometry": {"coordinates":[-122.387197,37.619087],"type":"Point"}
}
