{
  "type": "Feature",
  "properties": {
    "iso:country": "US",
    "media:created": -1,
    "media:fingerprint": "f5363cecd541b2076a730e8ea37eb74db93ac977",
    "media:imagehash_avg": "a:007e7e7e767e7e00",
    "media:imagehash_diff": "d:f0f4f4d496d6ccec",
    "media:medium": "image",
    "media:mimetype": "image/tiff",
    "media:properties": {
      "colours": [
        {
          "hex": "#bf8372",
          "name": "#bf8372",
          "reference": "vibrant"
        }, 
        {
          "hex": "#edc6a6",
          "name": "#edc6a6",
          "reference": "vibrant"
        }, 
        {
          "hex": "#081814",
          "name": "#081814",
          "reference": "vibrant"
        }, 
        {
          "hex": "#938078",
          "name": "#938078",
          "reference": "vibrant"
        }, 
        {
          "hex": "#c9b7af",
          "name": "#c9b7af",
          "reference": "vibrant"
        }
      ],
      "depicts": [
        1226612107
      ],
      "sizes": {
        "b": {
          "extension": "jpg",
          "height": 724,
          "mimetype": "image/jpeg",
          "secret": "Ya0cnHtZD4szheKAH83kI2BjtuhrxQ5v",
          "width": 1024
        },
        "c": {
          "extension": "jpg",
          "height": 565,
          "mimetype": "image/jpeg",
          "secret": "Ya0cnHtZD4szheKAH83kI2BjtuhrxQ5v",
          "width": 800
        },
        "dc": {
          "extension": "jpg",
          "height": 565,
          "mimetype": "image/jpeg",
          "secret": "Ya0cnHtZD4szheKAH83kI2BjtuhrxQ5v",
          "width": 800
        },
        "ds": {
          "extension": "jpg",
          "height": 320,
          "mimetype": "image/jpeg",
          "secret": "Ya0cnHtZD4szheKAH83kI2BjtuhrxQ5v",
          "width": 320
        },
        "k": {
          "extension": "jpg",
          "height": 1448,
          "mimetype": "image/jpeg",
          "secret": "Ya0cnHtZD4szheKAH83kI2BjtuhrxQ5v",
          "width": 2048
        },
        "n": {
          "extension": "jpg",
          "height": 226,
          "mimetype": "image/jpeg",
          "secret": "Ya0cnHtZD4szheKAH83kI2BjtuhrxQ5v",
          "width": 320
        },
        "o": {
          "extension": "jpg",
          "height": 3014,
          "mimetype": "image/jpeg",
          "secret": "ldsgqRCpGBSNZElPsrYDd2Mpl70wBz5z",
          "width": 4262
        },
        "s": {
          "extension": "jpg",
          "height": 320,
          "mimetype": "image/jpeg",
          "secret": "Ya0cnHtZD4szheKAH83kI2BjtuhrxQ5v",
          "width": 320
        },
        "z": {
          "extension": "jpg",
          "height": 452,
          "mimetype": "image/jpeg",
          "secret": "Ya0cnHtZD4szheKAH83kI2BjtuhrxQ5v",
          "width": 640
        }
      }
    },
    "sfomuseum:placetype": "image",
    "wof:depicts": [
      1159554819, 
      1360516129, 
      1159554841, 
      102527513, 
      1226612107, 
      1159554801
    ],
    "wof:name": "Installation view of \"Airport Cafe\"",
    "wof:placetype": "media"
  },
  "geometry": {"coordinates":[-122.387197,37.619087],"type":"Point"}
}
