{
  "type": "Feature", 
  "properties": {
    "iso:country": "US", 
    "media:created": -1, 
    "media:fingerprint": "3e4cfffcc4b0db4ed7f7bb42d0273ed234070249", 
    "media:medium": "image", 
    "media:mimetype": "image/tiff", 
    "media:properties": {
      "colours": [
        {
          "hex": "#8d573a", 
          "name": "#8d573a", 
          "reference": "vibrant"
        }, 
        {
          "hex": "#efcda9", 
          "name": "#efcda9", 
          "reference": "vibrant"
        }, 
        {
          "hex": "#543b28", 
          "name": "#543b28", 
          "reference": "vibrant"
        }, 
        {
          "hex": "#9a8160", 
          "name": "#9a8160", 
          "reference": "vibrant"
        }, 
        {
          "hex": "#ba9c79", 
          "name": "#ba9c79", 
          "reference": "vibrant"
        }
      ], 
      "depicts": [1226608683], 
      "sizes": {
        "b": {
          "extension": "jpg", 
          "height": 726, 
          "mimetype": "image/jpeg", 
          "secret": "WdKPgU6GSosBL9xkRgdgZbXTFSRp6kXc", 
          "width": 1024
        }, 
        "c": {
          "extension": "jpg", 
          "height": 567, 
          "mimetype": "image/jpeg", 
          "secret": "WdKPgU6GSosBL9xkRgdgZbXTFSRp6kXc", 
          "width": 800
        }, 
        "dc": {
          "extension": "jpg", 
          "height": 567, 
          "mimetype": "image/jpeg", 
          "secret": "WdKPgU6GSosBL9xkRgdgZbXTFSRp6kXc", 
          "width": 800
        }, 
        "ds": {
          "extension": "jpg", 
          "height": 320, 
          "mimetype": "image/jpeg", 
          "secret": "WdKPgU6GSosBL9xkRgdgZbXTFSRp6kXc", 
          "width": 320
        }, 
        "k": {
          "extension": "jpg", 
          "height": 1452, 
          "mimetype": "image/jpeg", 
          "secret": "WdKPgU6GSosBL9xkRgdgZbXTFSRp6kXc", 
          "width": 2048
        }, 
        "n": {
          "extension": "jpg", 
          "height": 226, 
          "mimetype": "image/jpeg", 
          "secret": "WdKPgU6GSosBL9xkRgdgZbXTFSRp6kXc", 
          "width": 320
        }, 
        "o": {
          "extension": "jpg", 
          "height": 3014, 
          "mimetype": "image/jpeg", 
          "secret": "r4IJoUejUFnEFBZeP0Y7HqTOs1qWscWN", 
          "width": 4251
        }, 
        "s": {
          "extension": "jpg", 
          "height": 320, 
          "mimetype": "image/jpeg", 
          "secret": "WdKPgU6GSosBL9xkRgdgZbXTFSRp6kXc", 
          "width": 320
        }, 
        "z": {
          "extension": "jpg", 
          "height": 453, 
          "mimetype": "image/jpeg", 
          "secret": "WdKPgU6GSosBL9xkRgdgZbXTFSRp6kXc", 
          "width": 640
        }
      }
    }, 
    "sfomuseum:placetype": "image", 
    "wof:depicts": [1360516467, 1226608683, 1159554829, 1159554803, 102527513], 
    "wof:name": "Installation view of \"Ancestor Figures from New Guinea\"", 
    "wof:placetype": "media" 
  }, 
  "geometry": {"coordinates":[-122.38274,37.617227],"type":"Point"}
}
