{
  "type": "Feature", 
  "properties": {
    "iso:country": "US", 
    "media:created": 1342738494, 
    "media:fingerprint": "a4784abe1d917dc6d51dea5461c810c4154b39f6", 
    "media:medium": "image", 
    "media:mimetype": "image/jpeg", 
    "media:properties": {
      "colours": [
        {
          "hex": "#bd3a24", 
          "name": "#bd3a24", 
          "reference": "vibrant"
        }, 
        {
          "hex": "#922f27", 
          "name": "#922f27", 
          "reference": "vibrant"
        }, 
        {
          "hex": "#5583aa", 
          "name": "#5583aa", 
          "reference": "vibrant"
        }, 
        {
          "hex": "#c5c2b8", 
          "name": "#c5c2b8", 
          "reference": "vibrant"
        }, 
        {
          "hex": "#434746", 
          "name": "#434746", 
          "reference": "vibrant"
        }
      ], 
      "depicts": [1159160327], 
      "sizes": {
        "b": {
          "extension": "jpg", 
          "height": 682, 
          "mimetype": "image/jpeg", 
          "secret": "A470vEAoY5BvsnwL1RT64bxmKTRLbExj", 
          "width": 1024
        }, 
        "c": {
          "extension": "jpg", 
          "height": 533, 
          "mimetype": "image/jpeg", 
          "secret": "A470vEAoY5BvsnwL1RT64bxmKTRLbExj", 
          "width": 800
        }, 
        "dc": {
          "extension": "jpg", 
          "height": 533, 
          "mimetype": "image/jpeg", 
          "secret": "A470vEAoY5BvsnwL1RT64bxmKTRLbExj", 
          "width": 800
        }, 
        "ds": {
          "extension": "jpg", 
          "height": 320, 
          "mimetype": "image/jpeg", 
          "secret": "A470vEAoY5BvsnwL1RT64bxmKTRLbExj", 
          "width": 320
        }, 
        "k": {
          "extension": "jpg", 
          "height": 1365, 
          "mimetype": "image/jpeg", 
          "secret": "A470vEAoY5BvsnwL1RT64bxmKTRLbExj", 
          "width": 2048
        }, 
        "n": {
          "extension": "jpg", 
          "height": 213, 
          "mimetype": "image/jpeg", 
          "secret": "A470vEAoY5BvsnwL1RT64bxmKTRLbExj", 
          "width": 320
        }, 
        "o": {
          "extension": "jpg", 
          "height": 2400, 
          "mimetype": "image/jpeg", 
          "secret": "krRQrq1Jz8yLyi5GlEem28nRwTWN8mjd", 
          "width": 3600
        }, 
        "s": {
          "extension": "jpg", 
          "height": 320, 
          "mimetype": "image/jpeg", 
          "secret": "A470vEAoY5BvsnwL1RT64bxmKTRLbExj", 
          "width": 320
        }, 
        "z": {
          "extension": "jpg", 
          "height": 426, 
          "mimetype": "image/jpeg", 
          "secret": "A470vEAoY5BvsnwL1RT64bxmKTRLbExj", 
          "width": 640
        }
      }
    }, 
    "sfomuseum:placetype": "image", 
    "wof:depicts": [
      1159396333, 
      1360516183, 
      1159396159, 
      1159160327, 
      102527513, 
      1360516193
    ], 
    "wof:name": "Installation view of \"From Repack to Rwanda, The Origins, Evolution and Global Reach of the Mountain Bike\"", 
    "wof:placetype": "media" 
  }, 
  "geometry": {"coordinates":[-122.389131,37.616029],"type":"Point"}
}
