{
  "type": "Feature", 
  "properties": {
    "iso:country": "US", 
    "media:created": 1194376104, 
    "media:fingerprint": "ebf93e19bf8b641fa060fc4468cc279062b1e1a4", 
    "media:medium": "image", 
    "media:mimetype": "image/jpeg", 
    "media:properties": {
      "colours": [
        {
          "hex": "#c1a92c", 
          "name": "#c1a92c", 
          "reference": "vibrant"
        }, 
        {
          "hex": "#a87f28", 
          "name": "#a87f28", 
          "reference": "vibrant"
        }, 
        {
          "hex": "#8d8771", 
          "name": "#8d8771", 
          "reference": "vibrant"
        }, 
        {
          "hex": "#c9c4a4", 
          "name": "#c9c4a4", 
          "reference": "vibrant"
        }, 
        {
          "hex": "#504c32", 
          "name": "#504c32", 
          "reference": "vibrant"
        }
      ], 
      "depicts": [1159159879], 
      "sizes": {
        "b": {
          "extension": "jpg", 
          "height": 768, 
          "mimetype": "image/jpeg", 
          "secret": "Gs08TEVH6CVbLTbVO5phMgBC3SI56W8J", 
          "width": 514
        }, 
        "c": {
          "extension": "jpg", 
          "height": 600, 
          "mimetype": "image/jpeg", 
          "secret": "Gs08TEVH6CVbLTbVO5phMgBC3SI56W8J", 
          "width": 401
        }, 
        "dc": {
          "extension": "jpg", 
          "height": 600, 
          "mimetype": "image/jpeg", 
          "secret": "Gs08TEVH6CVbLTbVO5phMgBC3SI56W8J", 
          "width": 401
        }, 
        "ds": {
          "extension": "jpg", 
          "height": 320, 
          "mimetype": "image/jpeg", 
          "secret": "Gs08TEVH6CVbLTbVO5phMgBC3SI56W8J", 
          "width": 320
        }, 
        "k": {
          "extension": "jpg", 
          "height": 1536, 
          "mimetype": "image/jpeg", 
          "secret": "Gs08TEVH6CVbLTbVO5phMgBC3SI56W8J", 
          "width": 1028
        }, 
        "n": {
          "extension": "jpg", 
          "height": 240, 
          "mimetype": "image/jpeg", 
          "secret": "Gs08TEVH6CVbLTbVO5phMgBC3SI56W8J", 
          "width": 160
        }, 
        "o": {
          "extension": "jpg", 
          "height": 3872, 
          "mimetype": "image/jpeg", 
          "secret": "XgzSuoYd5UQKCNzgAbtUGs1PMtWsGaH6", 
          "width": 2592
        }, 
        "s": {
          "extension": "jpg", 
          "height": 320, 
          "mimetype": "image/jpeg", 
          "secret": "Gs08TEVH6CVbLTbVO5phMgBC3SI56W8J", 
          "width": 320
        }, 
        "z": {
          "extension": "jpg", 
          "height": 480, 
          "mimetype": "image/jpeg", 
          "secret": "Gs08TEVH6CVbLTbVO5phMgBC3SI56W8J", 
          "width": 321
        }
      }
    }, 
    "sfomuseum:placetype": "image", 
    "wof:depicts": [1159159879, 102527513, 1159396139, 1159396337, 1360516479], 
    "wof:name": "Installation view of \"Baseball by the Bay: San Francisco, Oakland, and the National Pastime\"", 
    "wof:placetype": "media" 
  }, 
  "geometry": {"coordinates":[-122.385472,37.613926],"type":"Point"}
}
