{
  "type": "Feature",
  "properties": {
    "date:cessation_lower": "1993-04-30",
    "date:cessation_upper": "1993-04-30",
    "date:inception_lower": "1992-12-01",
    "date:inception_upper": "1992-12-01",
    "iso:country": "US",
    "media:created": -1,
    "media:fingerprint": "f7cdfabc9d0da9d3ffad9739daa2f08ec0969a15",
    "media:imagehash_avg": "a:007c7e7e7e7e7c00",
    "media:imagehash_diff": "d:c6c0c0c0c0c0c080",
    "media:medium": "image",
    "media:mimetype": "image/tiff",
    "media:placetype": "installation",
    "media:properties": {
      "colours": [
        {
          "hex": "#777c7c",
          "name": "#777c7c",
          "reference": "vibrant"
        },
        {
          "hex": "#b9c6c8",
          "name": "#b9c6c8",
          "reference": "vibrant"
        },
        {
          "hex": "#433a35",
          "name": "#433a35",
          "reference": "vibrant"
        }
      ],
      "depicts": [
        1376812951
      ],
      "sizes": {
        "b": {
          "extension": "jpg",
          "height": 768,
          "mimetype": "image/jpeg",
          "secret": "FR6qgY1vdk3RhboKfsuPjWGWKXsgYsan",
          "width": 544
        },
        "c": {
          "extension": "jpg",
          "height": 600,
          "mimetype": "image/jpeg",
          "secret": "FR6qgY1vdk3RhboKfsuPjWGWKXsgYsan",
          "width": 425
        },
        "dc": {
          "extension": "jpg",
          "height": 600,
          "mimetype": "image/jpeg",
          "secret": "FR6qgY1vdk3RhboKfsuPjWGWKXsgYsan",
          "width": 425
        },
        "ds": {
          "extension": "jpg",
          "height": 320,
          "mimetype": "image/jpeg",
          "secret": "FR6qgY1vdk3RhboKfsuPjWGWKXsgYsan",
          "width": 320
        },
        "k": {
          "extension": "jpg",
          "height": 1536,
          "mimetype": "image/jpeg",
          "secret": "FR6qgY1vdk3RhboKfsuPjWGWKXsgYsan",
          "width": 1089
        },
        "n": {
          "extension": "jpg",
          "height": 240,
          "mimetype": "image/jpeg",
          "secret": "FR6qgY1vdk3RhboKfsuPjWGWKXsgYsan",
          "width": 170
        },
        "o": {
          "extension": "jpg",
          "height": 4251,
          "mimetype": "image/jpeg",
          "secret": "uLyO4WU2qNOCUKRIH6AR6HacUx98zjqt",
          "width": 3014
        },
        "s": {
          "extension": "jpg",
          "height": 320,
          "mimetype": "image/jpeg",
          "secret": "FR6qgY1vdk3RhboKfsuPjWGWKXsgYsan",
          "width": 320
        },
        "z": {
          "extension": "jpg",
          "height": 480,
          "mimetype": "image/jpeg",
          "secret": "FR6qgY1vdk3RhboKfsuPjWGWKXsgYsan",
          "width": 340
        }
      }
    },
    "sfomuseum:placetype": "image",
    "wof:depicts": [
      1360516127,
      1159554821,
      1159554855,
      1376812951,
      1159554803,
      102527513
    ],
    "wof:name": "Installation view of \"Before the 21st Century: An Ode to Boats, Cars, Motorcycles, Planes, and Trains\"",
    "wof:placetype": "media",
    "wof:placetype_alt": [
      "image"
    ]
  },
  "geometry": {"coordinates":[-122.387197,37.619087],"type":"Point"}
}
