{
  "type": "Feature",
  "properties": {
    "iso:country": "US",
    "media:created": 1545308562,
    "media:fingerprint": "84d9c55eb4d51bb880d663ea528cf47caaa70580",
    "media:imagehash_avg": "a:fffe1c1c183c3c00",
    "media:imagehash_diff": "d:0616a8e8e8e0ecf0",
    "media:medium": "image",
    "media:mimetype": "image/jpeg",
    "media:properties": {
      "colours": [
        {
          "hex": "#c7ae66",
          "name": "#c7ae66",
          "reference": "vibrant"
        }, 
        {
          "hex": "#978969",
          "name": "#978969",
          "reference": "vibrant"
        }, 
        {
          "hex": "#9bb4c2",
          "name": "#9bb4c2",
          "reference": "vibrant"
        }, 
        {
          "hex": "#4f4941",
          "name": "#4f4941",
          "reference": "vibrant"
        }
      ],
      "depicts": [
        1360702457
      ],
      "sizes": {
        "b": {
          "extension": "jpg",
          "height": 683,
          "mimetype": "image/jpeg",
          "secret": "8zAMunamfpYR32awB0uOMHgB3AFzJsLh",
          "width": 1024
        },
        "c": {
          "extension": "jpg",
          "height": 533,
          "mimetype": "image/jpeg",
          "secret": "8zAMunamfpYR32awB0uOMHgB3AFzJsLh",
          "width": 800
        },
        "dc": {
          "extension": "jpg",
          "height": 533,
          "mimetype": "image/jpeg",
          "secret": "8zAMunamfpYR32awB0uOMHgB3AFzJsLh",
          "width": 800
        },
        "ds": {
          "extension": "jpg",
          "height": 320,
          "mimetype": "image/jpeg",
          "secret": "8zAMunamfpYR32awB0uOMHgB3AFzJsLh",
          "width": 320
        },
        "k": {
          "extension": "jpg",
          "height": 1366,
          "mimetype": "image/jpeg",
          "secret": "8zAMunamfpYR32awB0uOMHgB3AFzJsLh",
          "width": 2048
        },
        "n": {
          "extension": "jpg",
          "height": 213,
          "mimetype": "image/jpeg",
          "secret": "8zAMunamfpYR32awB0uOMHgB3AFzJsLh",
          "width": 320
        },
        "o": {
          "extension": "jpg",
          "height": 2402,
          "mimetype": "image/jpeg",
          "secret": "OVz9MDGItG69O9jqsVXwQjQOPlP2u0Ei",
          "width": 3600
        },
        "s": {
          "extension": "jpg",
          "height": 320,
          "mimetype": "image/jpeg",
          "secret": "8zAMunamfpYR32awB0uOMHgB3AFzJsLh",
          "width": 320
        },
        "z": {
          "extension": "jpg",
          "height": 427,
          "mimetype": "image/jpeg",
          "secret": "8zAMunamfpYR32awB0uOMHgB3AFzJsLh",
          "width": 640
        }
      }
    },
    "sfomuseum:placetype": "image",
    "wof:depicts": [
      1360702457, 
      102527513, 
      1159157053, 
      1159157307, 
      1159157271, 
      1159396301
    ],
    "wof:name": "Installation view of \"The Modern Consumer – 1950s Products and Styles\"",
    "wof:placetype": "media"
  },
  "geometry": {"coordinates":[-122.387197,37.619087],"type":"Point"}
}
