{
  "type": "Feature", 
  "properties": {
    "iso:country": "US", 
    "media:created": -1, 
    "media:fingerprint": "74bd47acf4576e795b55c735de3b0a49444b687c", 
    "media:medium": "image", 
    "media:mimetype": "image/tiff", 
    "media:properties": {
      "colours": [
        {
          "hex": "#997867", 
          "name": "#997867", 
          "reference": "vibrant"
        }, 
        {
          "hex": "#d0c1b9", 
          "name": "#d0c1b9", 
          "reference": "vibrant"
        }, 
        {
          "hex": "#454344", 
          "name": "#454344", 
          "reference": "vibrant"
        }
      ], 
      "depicts": [1226608827], 
      "sizes": {
        "b": {
          "extension": "jpg", 
          "height": 726, 
          "mimetype": "image/jpeg", 
          "secret": "ZQzfTCSe64IEKNAwtMhwa80d8syH1Sf6", 
          "width": 1024
        }, 
        "c": {
          "extension": "jpg", 
          "height": 567, 
          "mimetype": "image/jpeg", 
          "secret": "ZQzfTCSe64IEKNAwtMhwa80d8syH1Sf6", 
          "width": 800
        }, 
        "dc": {
          "extension": "jpg", 
          "height": 567, 
          "mimetype": "image/jpeg", 
          "secret": "ZQzfTCSe64IEKNAwtMhwa80d8syH1Sf6", 
          "width": 800
        }, 
        "ds": {
          "extension": "jpg", 
          "height": 320, 
          "mimetype": "image/jpeg", 
          "secret": "ZQzfTCSe64IEKNAwtMhwa80d8syH1Sf6", 
          "width": 320
        }, 
        "k": {
          "extension": "jpg", 
          "height": 1452, 
          "mimetype": "image/jpeg", 
          "secret": "ZQzfTCSe64IEKNAwtMhwa80d8syH1Sf6", 
          "width": 2048
        }, 
        "n": {
          "extension": "jpg", 
          "height": 226, 
          "mimetype": "image/jpeg", 
          "secret": "ZQzfTCSe64IEKNAwtMhwa80d8syH1Sf6", 
          "width": 320
        }, 
        "o": {
          "extension": "jpg", 
          "height": 3014, 
          "mimetype": "image/jpeg", 
          "secret": "D68VHnRV2fdyINHytZXiOXgKwW5OmBAr", 
          "width": 4251
        }, 
        "s": {
          "extension": "jpg", 
          "height": 320, 
          "mimetype": "image/jpeg", 
          "secret": "ZQzfTCSe64IEKNAwtMhwa80d8syH1Sf6", 
          "width": 320
        }, 
        "z": {
          "extension": "jpg", 
          "height": 453, 
          "mimetype": "image/jpeg", 
          "secret": "ZQzfTCSe64IEKNAwtMhwa80d8syH1Sf6", 
          "width": 640
        }
      }
    }, 
    "sfomuseum:placetype": "image", 
    "wof:depicts": [1159554829, 1159554803, 1226608827, 102527513, 1360516467], 
    "wof:name": "Installation view of \"Architectural Building Blocks\"", 
    "wof:placetype": "media" 
  }, 
  "geometry": {"coordinates":[-122.38274,37.617227],"type":"Point"}
}
