{
  "type": "Feature", 
  "properties": {
    "iso:country": "US", 
    "media:created": -1, 
    "media:fingerprint": "03bd8394ce5294fc697be1f5c34a34ba9d7eb6ca", 
    "media:medium": "image", 
    "media:mimetype": "image/tiff", 
    "media:properties": {
      "colours": [
        {
          "hex": "#d8d0a9", 
          "name": "#d8d0a9", 
          "reference": "vibrant"
        }, 
        {
          "hex": "#8c7a6d", 
          "name": "#8c7a6d", 
          "reference": "vibrant"
        }, 
        {
          "hex": "#abbfd2", 
          "name": "#abbfd2", 
          "reference": "vibrant"
        }, 
        {
          "hex": "#42342e", 
          "name": "#42342e", 
          "reference": "vibrant"
        }
      ], 
      "depicts": [1226607773], 
      "sizes": {
        "b": {
          "extension": "jpg", 
          "height": 768, 
          "mimetype": "image/jpeg", 
          "secret": "nCSuljqWb1AkCuag9EPVXsWsk0PcG3Mq", 
          "width": 544
        }, 
        "c": {
          "extension": "jpg", 
          "height": 600, 
          "mimetype": "image/jpeg", 
          "secret": "nCSuljqWb1AkCuag9EPVXsWsk0PcG3Mq", 
          "width": 425
        }, 
        "dc": {
          "extension": "jpg", 
          "height": 600, 
          "mimetype": "image/jpeg", 
          "secret": "nCSuljqWb1AkCuag9EPVXsWsk0PcG3Mq", 
          "width": 425
        }, 
        "ds": {
          "extension": "jpg", 
          "height": 320, 
          "mimetype": "image/jpeg", 
          "secret": "nCSuljqWb1AkCuag9EPVXsWsk0PcG3Mq", 
          "width": 320
        }, 
        "k": {
          "extension": "jpg", 
          "height": 1536, 
          "mimetype": "image/jpeg", 
          "secret": "nCSuljqWb1AkCuag9EPVXsWsk0PcG3Mq", 
          "width": 1089
        }, 
        "n": {
          "extension": "jpg", 
          "height": 240, 
          "mimetype": "image/jpeg", 
          "secret": "nCSuljqWb1AkCuag9EPVXsWsk0PcG3Mq", 
          "width": 170
        }, 
        "o": {
          "extension": "jpg", 
          "height": 4251, 
          "mimetype": "image/jpeg", 
          "secret": "1qMIAYXq4GBwZWNlQ5dDX19GHO5yKaHJ", 
          "width": 3014
        }, 
        "s": {
          "extension": "jpg", 
          "height": 320, 
          "mimetype": "image/jpeg", 
          "secret": "nCSuljqWb1AkCuag9EPVXsWsk0PcG3Mq", 
          "width": 320
        }, 
        "z": {
          "extension": "jpg", 
          "height": 480, 
          "mimetype": "image/jpeg", 
          "secret": "nCSuljqWb1AkCuag9EPVXsWsk0PcG3Mq", 
          "width": 340
        }
      }
    }, 
    "sfomuseum:placetype": "image", 
    "wof:depicts": [1159554803, 102527513, 1159554829, 1226607773, 1360516471], 
    "wof:name": "Installation view of \"Bowling: A Unique American Art Form\"", 
    "wof:placetype": "media" 
  }, 
  "geometry": {"coordinates":[-122.38274,37.617227],"type":"Point"}
}
