{
  "type": "Feature", 
  "properties": {
    "iso:country": "US", 
    "media:created": 1511809049, 
    "media:fingerprint": "3f86920ed5c188d3bf48a02583a7686dbc7c9f8e", 
    "media:medium": "image", 
    "media:mimetype": "image/jpeg", 
    "media:properties": {
      "colours": [
        {
          "hex": "#a6403c", 
          "name": "#a6403c", 
          "reference": "vibrant"
        }, 
        {
          "hex": "#c1a079", 
          "name": "#c1a079", 
          "reference": "vibrant"
        }, 
        {
          "hex": "#916740", 
          "name": "#916740", 
          "reference": "vibrant"
        }, 
        {
          "hex": "#a58a61", 
          "name": "#a58a61", 
          "reference": "vibrant"
        }, 
        {
          "hex": "#cdbaa9", 
          "name": "#cdbaa9", 
          "reference": "vibrant"
        }
      ], 
      "depicts": [1159160603], 
      "sizes": {
        "b": {
          "extension": "jpg", 
          "height": 768, 
          "mimetype": "image/jpeg", 
          "secret": "q2yMcogKiuIX9vpWGj8mYiu8JV9cgHWf", 
          "width": 512
        }, 
        "c": {
          "extension": "jpg", 
          "height": 600, 
          "mimetype": "image/jpeg", 
          "secret": "q2yMcogKiuIX9vpWGj8mYiu8JV9cgHWf", 
          "width": 400
        }, 
        "dc": {
          "extension": "jpg", 
          "height": 600, 
          "mimetype": "image/jpeg", 
          "secret": "q2yMcogKiuIX9vpWGj8mYiu8JV9cgHWf", 
          "width": 400
        }, 
        "ds": {
          "extension": "jpg", 
          "height": 320, 
          "mimetype": "image/jpeg", 
          "secret": "q2yMcogKiuIX9vpWGj8mYiu8JV9cgHWf", 
          "width": 320
        }, 
        "k": {
          "extension": "jpg", 
          "height": 1536, 
          "mimetype": "image/jpeg", 
          "secret": "q2yMcogKiuIX9vpWGj8mYiu8JV9cgHWf", 
          "width": 1024
        }, 
        "n": {
          "extension": "jpg", 
          "height": 240, 
          "mimetype": "image/jpeg", 
          "secret": "q2yMcogKiuIX9vpWGj8mYiu8JV9cgHWf", 
          "width": 160
        }, 
        "o": {
          "extension": "jpg", 
          "height": 3600, 
          "mimetype": "image/jpeg", 
          "secret": "iNIptDBWgD9PqeWi0w4a8wakZ9v0N8qK", 
          "width": 2400
        }, 
        "s": {
          "extension": "jpg", 
          "height": 320, 
          "mimetype": "image/jpeg", 
          "secret": "q2yMcogKiuIX9vpWGj8mYiu8JV9cgHWf", 
          "width": 320
        }, 
        "z": {
          "extension": "jpg", 
          "height": 480, 
          "mimetype": "image/jpeg", 
          "secret": "q2yMcogKiuIX9vpWGj8mYiu8JV9cgHWf", 
          "width": 320
        }
      }
    }, 
    "sfomuseum:placetype": "image", 
    "wof:depicts": [
      102527513, 
      1159268871, 
      1159157335, 
      1159157039, 
      1159160603, 
      1159157333, 
      1159157271
    ], 
    "wof:name": "Installation view of \"American Folk Art: An Enduring Legacy\"", 
    "wof:placetype": "media" 
  }, 
  "geometry": {"coordinates":[-122.388743,37.614609],"type":"Point"}
}
