{
  "type": "Feature",
  "properties": {
    "date:cessation_lower": "2018-07-09",
    "date:cessation_upper": "2018-07-09",
    "date:inception_lower": "2017-11-17",
    "date:inception_upper": "2017-11-17",
    "iso:country": "US",
    "media:created": 1511809049,
    "media:fingerprint": "3f86920ed5c188d3bf48a02583a7686dbc7c9f8e",
    "media:imagehash_avg": "a:01ffe3fcdb81013c",
    "media:imagehash_diff": "d:31170fc8b31779e0",
    "media:medium": "image",
    "media:mimetype": "image/jpeg",
    "media:placetype": "installation",
    "media:properties": {
      "colours": [
        {
          "hex": "#a6403c",
          "name": "#a6403c",
          "reference": "vibrant"
        },
        {
          "hex": "#c1a079",
          "name": "#c1a079",
          "reference": "vibrant"
        },
        {
          "hex": "#916740",
          "name": "#916740",
          "reference": "vibrant"
        },
        {
          "hex": "#a58a61",
          "name": "#a58a61",
          "reference": "vibrant"
        },
        {
          "hex": "#cdbaa9",
          "name": "#cdbaa9",
          "reference": "vibrant"
        }
      ],
      "depicts": [
        1159160603
      ],
      "sizes": {
        "b": {
          "extension": "jpg",
          "height": 768,
          "mimetype": "image/jpeg",
          "secret": "q2yMcogKiuIX9vpWGj8mYiu8JV9cgHWf",
          "width": 512
        },
        "c": {
          "extension": "jpg",
          "height": 600,
          "mimetype": "image/jpeg",
          "secret": "q2yMcogKiuIX9vpWGj8mYiu8JV9cgHWf",
          "width": 400
        },
        "dc": {
          "extension": "jpg",
          "height": 600,
          "mimetype": "image/jpeg",
          "secret": "q2yMcogKiuIX9vpWGj8mYiu8JV9cgHWf",
          "width": 400
        },
        "ds": {
          "extension": "jpg",
          "height": 320,
          "mimetype": "image/jpeg",
          "secret": "q2yMcogKiuIX9vpWGj8mYiu8JV9cgHWf",
          "width": 320
        },
        "k": {
          "extension": "jpg",
          "height": 1536,
          "mimetype": "image/jpeg",
          "secret": "q2yMcogKiuIX9vpWGj8mYiu8JV9cgHWf",
          "width": 1024
        },
        "n": {
          "extension": "jpg",
          "height": 240,
          "mimetype": "image/jpeg",
          "secret": "q2yMcogKiuIX9vpWGj8mYiu8JV9cgHWf",
          "width": 160
        },
        "o": {
          "extension": "jpg",
          "height": 3600,
          "mimetype": "image/jpeg",
          "secret": "iNIptDBWgD9PqeWi0w4a8wakZ9v0N8qK",
          "width": 2400
        },
        "s": {
          "extension": "jpg",
          "height": 320,
          "mimetype": "image/jpeg",
          "secret": "q2yMcogKiuIX9vpWGj8mYiu8JV9cgHWf",
          "width": 320
        },
        "z": {
          "extension": "jpg",
          "height": 480,
          "mimetype": "image/jpeg",
          "secret": "q2yMcogKiuIX9vpWGj8mYiu8JV9cgHWf",
          "width": 320
        }
      }
    },
    "sfomuseum:placetype": "image",
    "wof:depicts": [
      1159157039,
      1159160603,
      1159157333,
      1159157271,
      102527513,
      1159268871,
      1159157335
    ],
    "wof:name": "Installation view of \"American Folk Art: An Enduring Legacy\"",
    "wof:placetype": "media"
  },
  "geometry": {"coordinates":[-122.388743,37.614609],"type":"Point"}
}
