{
  "type": "Feature", 
  "properties": {
    "iso:country": "US", 
    "media:created": -1, 
    "media:fingerprint": "302cad3e3f9b51bf954f7fe5f582e7f5f52922c6", 
    "media:medium": "image", 
    "media:mimetype": "image/tiff", 
    "media:properties": {
      "colours": [
        {
          "hex": "#dfba0b", 
          "name": "#dfba0b", 
          "reference": "vibrant"
        }, 
        {
          "hex": "#cc6c53", 
          "name": "#cc6c53", 
          "reference": "vibrant"
        }, 
        {
          "hex": "#c29007", 
          "name": "#c29007", 
          "reference": "vibrant"
        }, 
        {
          "hex": "#9e735e", 
          "name": "#9e735e", 
          "reference": "vibrant"
        }, 
        {
          "hex": "#a0bcc9", 
          "name": "#a0bcc9", 
          "reference": "vibrant"
        }
      ], 
      "depicts": [1159159931], 
      "sizes": {
        "b": {
          "extension": "jpg", 
          "height": 685, 
          "mimetype": "image/jpeg", 
          "secret": "vu7FLv4vL8SMQSDxVTLZ36HJHJENoXJO", 
          "width": 1024
        }, 
        "c": {
          "extension": "jpg", 
          "height": 535, 
          "mimetype": "image/jpeg", 
          "secret": "vu7FLv4vL8SMQSDxVTLZ36HJHJENoXJO", 
          "width": 800
        }, 
        "dc": {
          "extension": "jpg", 
          "height": 535, 
          "mimetype": "image/jpeg", 
          "secret": "vu7FLv4vL8SMQSDxVTLZ36HJHJENoXJO", 
          "width": 800
        }, 
        "ds": {
          "extension": "jpg", 
          "height": 320, 
          "mimetype": "image/jpeg", 
          "secret": "vu7FLv4vL8SMQSDxVTLZ36HJHJENoXJO", 
          "width": 320
        }, 
        "k": {
          "extension": "jpg", 
          "height": 1370, 
          "mimetype": "image/jpeg", 
          "secret": "vu7FLv4vL8SMQSDxVTLZ36HJHJENoXJO", 
          "width": 2048
        }, 
        "n": {
          "extension": "jpg", 
          "height": 214, 
          "mimetype": "image/jpeg", 
          "secret": "vu7FLv4vL8SMQSDxVTLZ36HJHJENoXJO", 
          "width": 320
        }, 
        "o": {
          "extension": "jpg", 
          "height": 2592, 
          "mimetype": "image/jpeg", 
          "secret": "N0xNqdA6lN60XQXZHEaQl4W5atv1LepL", 
          "width": 3872
        }, 
        "s": {
          "extension": "jpg", 
          "height": 320, 
          "mimetype": "image/jpeg", 
          "secret": "vu7FLv4vL8SMQSDxVTLZ36HJHJENoXJO", 
          "width": 320
        }, 
        "z": {
          "extension": "jpg", 
          "height": 428, 
          "mimetype": "image/jpeg", 
          "secret": "vu7FLv4vL8SMQSDxVTLZ36HJHJENoXJO", 
          "width": 640
        }
      }
    }, 
    "sfomuseum:placetype": "image", 
    "wof:depicts": [
      1360521569, 
      1159396337, 
      102527513, 
      1159159931, 
      1159396147, 
      1360541661
    ], 
    "wof:name": "Installation view of \"Young Eyes on the Skies: The Golden Age of Aviation Toys\"", 
    "wof:placetype": "media" 
  }, 
  "geometry": {"coordinates":[-122.38622,37.616463],"type":"Point"}
}
