{
  "type": "Feature", 
  "properties": {
    "iso:country": "US", 
    "media:created": 1538413430, 
    "media:fingerprint": "62e0bde0d0fa1f89d3a0c1e8ebbc0d534f069b23", 
    "media:medium": "image", 
    "media:mimetype": "image/jpeg", 
    "media:properties": {
      "colours": [
        {
          "hex": "#2c8dbe", 
          "name": "#2c8dbe", 
          "reference": "vibrant"
        }, 
        {
          "hex": "#e4d5c3", 
          "name": "#e4d5c3", 
          "reference": "vibrant"
        }, 
        {
          "hex": "#38231a", 
          "name": "#38231a", 
          "reference": "vibrant"
        }, 
        {
          "hex": "#9d7761", 
          "name": "#9d7761", 
          "reference": "vibrant"
        }, 
        {
          "hex": "#bfc4c3", 
          "name": "#bfc4c3", 
          "reference": "vibrant"
        }
      ], 
      "depicts": [1360664647], 
      "sizes": {
        "b": {
          "extension": "jpg", 
          "height": 682, 
          "mimetype": "image/jpeg", 
          "secret": "8DA73NvhOeGyK5Nf3vFSMDjyEBbeaDRH", 
          "width": 1024
        }, 
        "c": {
          "extension": "jpg", 
          "height": 533, 
          "mimetype": "image/jpeg", 
          "secret": "8DA73NvhOeGyK5Nf3vFSMDjyEBbeaDRH", 
          "width": 800
        }, 
        "dc": {
          "extension": "jpg", 
          "height": 533, 
          "mimetype": "image/jpeg", 
          "secret": "8DA73NvhOeGyK5Nf3vFSMDjyEBbeaDRH", 
          "width": 800
        }, 
        "ds": {
          "extension": "jpg", 
          "height": 320, 
          "mimetype": "image/jpeg", 
          "secret": "8DA73NvhOeGyK5Nf3vFSMDjyEBbeaDRH", 
          "width": 320
        }, 
        "k": {
          "extension": "jpg", 
          "height": 1365, 
          "mimetype": "image/jpeg", 
          "secret": "8DA73NvhOeGyK5Nf3vFSMDjyEBbeaDRH", 
          "width": 2048
        }, 
        "n": {
          "extension": "jpg", 
          "height": 213, 
          "mimetype": "image/jpeg", 
          "secret": "8DA73NvhOeGyK5Nf3vFSMDjyEBbeaDRH", 
          "width": 320
        }, 
        "o": {
          "extension": "jpg", 
          "height": 2400, 
          "mimetype": "image/jpeg", 
          "secret": "sopbsdue6nHXDOqewz4QH67DfFnMDQfw", 
          "width": 3600
        }, 
        "s": {
          "extension": "jpg", 
          "height": 320, 
          "mimetype": "image/jpeg", 
          "secret": "8DA73NvhOeGyK5Nf3vFSMDjyEBbeaDRH", 
          "width": 320
        }, 
        "z": {
          "extension": "jpg", 
          "height": 426, 
          "mimetype": "image/jpeg", 
          "secret": "8DA73NvhOeGyK5Nf3vFSMDjyEBbeaDRH", 
          "width": 640
        }
      }
    }, 
    "sfomuseum:placetype": "image", 
    "wof:depicts": [
      1159396181, 
      1159396121, 
      1159157067, 
      1360664647, 
      1159157271, 
      102527513
    ], 
    "wof:name": "Installation view of \"Down-Home Music: The Story of Arhoolie Records\"", 
    "wof:placetype": "media" 
  }, 
  "geometry": {"coordinates":[-122.382712,37.617422],"type":"Point"}
}
