{
  "type": "Feature", 
  "properties": {
    "iso:country": "US", 
    "media:created": 1498753597, 
    "media:fingerprint": "cb4fd973649aa196ec934ccbb34e7a4f336d04e0", 
    "media:medium": "image", 
    "media:mimetype": "image/jpeg", 
    "media:properties": {
      "colours": [
        {
          "hex": "#bdad5d", 
          "name": "#bdad5d", 
          "reference": "vibrant"
        }, 
        {
          "hex": "#cfc382", 
          "name": "#cfc382", 
          "reference": "vibrant"
        }, 
        {
          "hex": "#a89a60", 
          "name": "#a89a60", 
          "reference": "vibrant"
        }, 
        {
          "hex": "#cbc6b9", 
          "name": "#cbc6b9", 
          "reference": "vibrant"
        }, 
        {
          "hex": "#423e35", 
          "name": "#423e35", 
          "reference": "vibrant"
        }
      ], 
      "depicts": [1159160725], 
      "sizes": {
        "b": {
          "extension": "jpg", 
          "height": 682, 
          "mimetype": "image/jpeg", 
          "secret": "A4Alxp8ujbiPfotY82vxQ0zYdGOMfAz6", 
          "width": 1024
        }, 
        "c": {
          "extension": "jpg", 
          "height": 533, 
          "mimetype": "image/jpeg", 
          "secret": "A4Alxp8ujbiPfotY82vxQ0zYdGOMfAz6", 
          "width": 800
        }, 
        "dc": {
          "extension": "jpg", 
          "height": 533, 
          "mimetype": "image/jpeg", 
          "secret": "A4Alxp8ujbiPfotY82vxQ0zYdGOMfAz6", 
          "width": 800
        }, 
        "ds": {
          "extension": "jpg", 
          "height": 320, 
          "mimetype": "image/jpeg", 
          "secret": "A4Alxp8ujbiPfotY82vxQ0zYdGOMfAz6", 
          "width": 320
        }, 
        "k": {
          "extension": "jpg", 
          "height": 1365, 
          "mimetype": "image/jpeg", 
          "secret": "A4Alxp8ujbiPfotY82vxQ0zYdGOMfAz6", 
          "width": 2048
        }, 
        "n": {
          "extension": "jpg", 
          "height": 213, 
          "mimetype": "image/jpeg", 
          "secret": "A4Alxp8ujbiPfotY82vxQ0zYdGOMfAz6", 
          "width": 320
        }, 
        "o": {
          "extension": "jpg", 
          "height": 2400, 
          "mimetype": "image/jpeg", 
          "secret": "mavirp96XavwAEGHzUCOoBWTK9IJcKcb", 
          "width": 3600
        }, 
        "s": {
          "extension": "jpg", 
          "height": 320, 
          "mimetype": "image/jpeg", 
          "secret": "A4Alxp8ujbiPfotY82vxQ0zYdGOMfAz6", 
          "width": 320
        }, 
        "z": {
          "extension": "jpg", 
          "height": 426, 
          "mimetype": "image/jpeg", 
          "secret": "A4Alxp8ujbiPfotY82vxQ0zYdGOMfAz6", 
          "width": 640
        }
      }
    }, 
    "sfomuseum:placetype": "image", 
    "wof:depicts": [
      1159396301, 
      1159160725, 
      1159268871, 
      1159157053, 
      1159157307, 
      1159157271, 
      102527513
    ], 
    "wof:name": "Installation view of \"Flying the Main Line: A History of United Airlines\"", 
    "wof:placetype": "media" 
  }, 
  "geometry": {"coordinates":[-122.387109,37.618847],"type":"Point"}
}
