{
  "type": "Feature", 
  "properties": {
    "iso:country": "US", 
    "media:created": -1, 
    "media:fingerprint": "621178bb4454773ca1ff5605d3cc9eda6ef75368", 
    "media:medium": "image", 
    "media:mimetype": "image/tiff", 
    "media:properties": {
      "colours": [
        {
          "hex": "#738389", 
          "name": "#738389", 
          "reference": "vibrant"
        }, 
        {
          "hex": "#adb7c7", 
          "name": "#adb7c7", 
          "reference": "vibrant"
        }, 
        {
          "hex": "#4d463e", 
          "name": "#4d463e", 
          "reference": "vibrant"
        }
      ], 
      "depicts": [1376812951], 
      "sizes": {
        "b": {
          "extension": "jpg", 
          "height": 726, 
          "mimetype": "image/jpeg", 
          "secret": "pJYGlb10QTBr6dhXmAcfmA1S1G3xQBwL", 
          "width": 1024
        }, 
        "c": {
          "extension": "jpg", 
          "height": 567, 
          "mimetype": "image/jpeg", 
          "secret": "pJYGlb10QTBr6dhXmAcfmA1S1G3xQBwL", 
          "width": 800
        }, 
        "dc": {
          "extension": "jpg", 
          "height": 567, 
          "mimetype": "image/jpeg", 
          "secret": "pJYGlb10QTBr6dhXmAcfmA1S1G3xQBwL", 
          "width": 800
        }, 
        "ds": {
          "extension": "jpg", 
          "height": 320, 
          "mimetype": "image/jpeg", 
          "secret": "pJYGlb10QTBr6dhXmAcfmA1S1G3xQBwL", 
          "width": 320
        }, 
        "k": {
          "extension": "jpg", 
          "height": 1452, 
          "mimetype": "image/jpeg", 
          "secret": "pJYGlb10QTBr6dhXmAcfmA1S1G3xQBwL", 
          "width": 2048
        }, 
        "n": {
          "extension": "jpg", 
          "height": 226, 
          "mimetype": "image/jpeg", 
          "secret": "pJYGlb10QTBr6dhXmAcfmA1S1G3xQBwL", 
          "width": 320
        }, 
        "o": {
          "extension": "jpg", 
          "height": 3014, 
          "mimetype": "image/jpeg", 
          "secret": "0nej8SMljftk0QAHi2HfwbH2UGPWNzXc", 
          "width": 4251
        }, 
        "s": {
          "extension": "jpg", 
          "height": 320, 
          "mimetype": "image/jpeg", 
          "secret": "pJYGlb10QTBr6dhXmAcfmA1S1G3xQBwL", 
          "width": 320
        }, 
        "z": {
          "extension": "jpg", 
          "height": 453, 
          "mimetype": "image/jpeg", 
          "secret": "pJYGlb10QTBr6dhXmAcfmA1S1G3xQBwL", 
          "width": 640
        }
      }
    }, 
    "sfomuseum:placetype": "image", 
    "wof:depicts": [
      1159554855, 
      1376812951, 
      102527513, 
      1360516127, 
      1159554821, 
      1159554803
    ], 
    "wof:name": "Installation view of \"Before the 21st Century: An Ode to Boats, Cars, Motorcycles, Planes, and Trains\"", 
    "wof:placetype": "media" 
  }, 
  "geometry": {"coordinates":[-122.387197,37.619087],"type":"Point"}
}
