{
  "type": "Feature", 
  "properties": {
    "iso:country": "US", 
    "media:created": -1, 
    "media:fingerprint": "74bc960eadb583ada19ad4475b7794b62b017d24", 
    "media:medium": "image", 
    "media:mimetype": "image/tiff", 
    "media:properties": {
      "colours": [
        {
          "hex": "#94bed5", 
          "name": "#94bed5", 
          "reference": "vibrant"
        }, 
        {
          "hex": "#6f728e", 
          "name": "#6f728e", 
          "reference": "vibrant"
        }, 
        {
          "hex": "#acc8d1", 
          "name": "#acc8d1", 
          "reference": "vibrant"
        }, 
        {
          "hex": "#3a3e54", 
          "name": "#3a3e54", 
          "reference": "vibrant"
        }
      ], 
      "depicts": [1226612011], 
      "sizes": {
        "b": {
          "extension": "jpg", 
          "height": 726, 
          "mimetype": "image/jpeg", 
          "secret": "65CtbNe1JY6ibGrjU0KmarnTQ3bSwiA7", 
          "width": 1024
        }, 
        "c": {
          "extension": "jpg", 
          "height": 567, 
          "mimetype": "image/jpeg", 
          "secret": "65CtbNe1JY6ibGrjU0KmarnTQ3bSwiA7", 
          "width": 800
        }, 
        "dc": {
          "extension": "jpg", 
          "height": 567, 
          "mimetype": "image/jpeg", 
          "secret": "65CtbNe1JY6ibGrjU0KmarnTQ3bSwiA7", 
          "width": 800
        }, 
        "ds": {
          "extension": "jpg", 
          "height": 320, 
          "mimetype": "image/jpeg", 
          "secret": "65CtbNe1JY6ibGrjU0KmarnTQ3bSwiA7", 
          "width": 320
        }, 
        "k": {
          "extension": "jpg", 
          "height": 1452, 
          "mimetype": "image/jpeg", 
          "secret": "65CtbNe1JY6ibGrjU0KmarnTQ3bSwiA7", 
          "width": 2048
        }, 
        "n": {
          "extension": "jpg", 
          "height": 226, 
          "mimetype": "image/jpeg", 
          "secret": "65CtbNe1JY6ibGrjU0KmarnTQ3bSwiA7", 
          "width": 320
        }, 
        "o": {
          "extension": "jpg", 
          "height": 3014, 
          "mimetype": "image/jpeg", 
          "secret": "R4zIVfBWXI1mDmhmz3Q3VO10QvCBaXjF", 
          "width": 4251
        }, 
        "s": {
          "extension": "jpg", 
          "height": 320, 
          "mimetype": "image/jpeg", 
          "secret": "65CtbNe1JY6ibGrjU0KmarnTQ3bSwiA7", 
          "width": 320
        }, 
        "z": {
          "extension": "jpg", 
          "height": 453, 
          "mimetype": "image/jpeg", 
          "secret": "65CtbNe1JY6ibGrjU0KmarnTQ3bSwiA7", 
          "width": 640
        }
      }
    }, 
    "sfomuseum:placetype": "image", 
    "wof:depicts": [
      1226612011, 
      1159396129, 
      1159396327, 
      1360516133, 
      102527513, 
      1159396233
    ], 
    "wof:name": "Installation view of \"Artist's Furniture: New Dimensions and Statements in Design\"", 
    "wof:placetype": "media" 
  }, 
  "geometry": {"coordinates":[-122.387197,37.619087],"type":"Point"}
}
