{
  "type": "Feature", 
  "properties": {
    "iso:country": "US", 
    "media:created": -1, 
    "media:fingerprint": "c9ea332ec1ba2116730166b61e7199be3676ae69", 
    "media:medium": "image", 
    "media:mimetype": "image/tiff", 
    "media:properties": {
      "colours": [
        {
          "hex": "#6b7f94", 
          "name": "#6b7f94", 
          "reference": "vibrant"
        }, 
        {
          "hex": "#b8bfbe", 
          "name": "#b8bfbe", 
          "reference": "vibrant"
        }, 
        {
          "hex": "#353e51", 
          "name": "#353e51", 
          "reference": "vibrant"
        }
      ], 
      "depicts": [1226606173], 
      "sizes": {
        "b": {
          "extension": "jpg", 
          "height": 726, 
          "mimetype": "image/jpeg", 
          "secret": "2UcWTrNMCsvBW2Rp9p8lCcZDhdMdP08V", 
          "width": 1024
        }, 
        "c": {
          "extension": "jpg", 
          "height": 567, 
          "mimetype": "image/jpeg", 
          "secret": "2UcWTrNMCsvBW2Rp9p8lCcZDhdMdP08V", 
          "width": 800
        }, 
        "dc": {
          "extension": "jpg", 
          "height": 567, 
          "mimetype": "image/jpeg", 
          "secret": "2UcWTrNMCsvBW2Rp9p8lCcZDhdMdP08V", 
          "width": 800
        }, 
        "ds": {
          "extension": "jpg", 
          "height": 320, 
          "mimetype": "image/jpeg", 
          "secret": "2UcWTrNMCsvBW2Rp9p8lCcZDhdMdP08V", 
          "width": 320
        }, 
        "k": {
          "extension": "jpg", 
          "height": 1452, 
          "mimetype": "image/jpeg", 
          "secret": "2UcWTrNMCsvBW2Rp9p8lCcZDhdMdP08V", 
          "width": 2048
        }, 
        "n": {
          "extension": "jpg", 
          "height": 226, 
          "mimetype": "image/jpeg", 
          "secret": "2UcWTrNMCsvBW2Rp9p8lCcZDhdMdP08V", 
          "width": 320
        }, 
        "o": {
          "extension": "jpg", 
          "height": 3014, 
          "mimetype": "image/jpeg", 
          "secret": "BqvFDfXqfoF6FhVT4N47CmMKfmbqd5th", 
          "width": 4251
        }, 
        "s": {
          "extension": "jpg", 
          "height": 320, 
          "mimetype": "image/jpeg", 
          "secret": "2UcWTrNMCsvBW2Rp9p8lCcZDhdMdP08V", 
          "width": 320
        }, 
        "z": {
          "extension": "jpg", 
          "height": 453, 
          "mimetype": "image/jpeg", 
          "secret": "2UcWTrNMCsvBW2Rp9p8lCcZDhdMdP08V", 
          "width": 640
        }
      }
    }, 
    "sfomuseum:placetype": "image", 
    "wof:depicts": [1159157883, 102527513, 1159554803, 1226606173, 1159554817], 
    "wof:name": "Installation view of \"B is for Bears\"", 
    "wof:placetype": "media" 
  }, 
  "geometry": {"coordinates":[-122.385472,37.613926],"type":"Point"}
}
