{
  "type": "Feature", 
  "properties": {
    "iso:country": "US", 
    "media:created": 1392061877, 
    "media:fingerprint": "de699f9fb56e83c61fdbbe846e59629e221b5212", 
    "media:medium": "image", 
    "media:mimetype": "image/jpeg", 
    "media:properties": {
      "colours": [
        {
          "hex": "#8c806f", 
          "name": "#8c806f", 
          "reference": "vibrant"
        }, 
        {
          "hex": "#cfc4b3", 
          "name": "#cfc4b3", 
          "reference": "vibrant"
        }, 
        {
          "hex": "#645638", 
          "name": "#645638", 
          "reference": "vibrant"
        }
      ], 
      "depicts": [1159160469], 
      "sizes": {
        "b": {
          "extension": "jpg", 
          "height": 682, 
          "mimetype": "image/jpeg", 
          "secret": "vDyuF3pd0QqWeINjXrpr7QyoXqoE1G8O", 
          "width": 1024
        }, 
        "c": {
          "extension": "jpg", 
          "height": 533, 
          "mimetype": "image/jpeg", 
          "secret": "vDyuF3pd0QqWeINjXrpr7QyoXqoE1G8O", 
          "width": 800
        }, 
        "dc": {
          "extension": "jpg", 
          "height": 533, 
          "mimetype": "image/jpeg", 
          "secret": "vDyuF3pd0QqWeINjXrpr7QyoXqoE1G8O", 
          "width": 800
        }, 
        "ds": {
          "extension": "jpg", 
          "height": 320, 
          "mimetype": "image/jpeg", 
          "secret": "vDyuF3pd0QqWeINjXrpr7QyoXqoE1G8O", 
          "width": 320
        }, 
        "k": {
          "extension": "jpg", 
          "height": 1365, 
          "mimetype": "image/jpeg", 
          "secret": "vDyuF3pd0QqWeINjXrpr7QyoXqoE1G8O", 
          "width": 2048
        }, 
        "n": {
          "extension": "jpg", 
          "height": 213, 
          "mimetype": "image/jpeg", 
          "secret": "vDyuF3pd0QqWeINjXrpr7QyoXqoE1G8O", 
          "width": 320
        }, 
        "o": {
          "extension": "jpg", 
          "height": 2400, 
          "mimetype": "image/jpeg", 
          "secret": "K1cR5HLbsqDzN9idOVzIrUPzszOd4wP9", 
          "width": 3600
        }, 
        "s": {
          "extension": "jpg", 
          "height": 320, 
          "mimetype": "image/jpeg", 
          "secret": "vDyuF3pd0QqWeINjXrpr7QyoXqoE1G8O", 
          "width": 320
        }, 
        "z": {
          "extension": "jpg", 
          "height": 426, 
          "mimetype": "image/jpeg", 
          "secret": "vDyuF3pd0QqWeINjXrpr7QyoXqoE1G8O", 
          "width": 640
        }
      }
    }, 
    "sfomuseum:placetype": "image", 
    "wof:depicts": [
      1360516259, 
      1159396333, 
      1159160469, 
      1159396109, 
      102527513, 
      1159396261
    ], 
    "wof:name": "Installation view of \"San Francisco, From the David Rumsey Map Collection\"", 
    "wof:placetype": "media" 
  }, 
  "geometry": {"coordinates":[-122.382712,37.617422],"type":"Point"}
}
