{
  "type": "Feature", 
  "properties": {
    "iso:country": "US", 
    "media:created": -1, 
    "media:fingerprint": "74b46972d5e26556dafd28ab86c50b776ddfc86b", 
    "media:medium": "image", 
    "media:mimetype": "image/tiff", 
    "media:properties": {
      "colours": [
        {
          "hex": "#c9883a", 
          "name": "#c9883a", 
          "reference": "vibrant"
        }, 
        {
          "hex": "#d3be8b", 
          "name": "#d3be8b", 
          "reference": "vibrant"
        }, 
        {
          "hex": "#6d3724", 
          "name": "#6d3724", 
          "reference": "vibrant"
        }, 
        {
          "hex": "#908669", 
          "name": "#908669", 
          "reference": "vibrant"
        }, 
        {
          "hex": "#cec5b0", 
          "name": "#cec5b0", 
          "reference": "vibrant"
        }
      ], 
      "depicts": [1226603375], 
      "sizes": {
        "b": {
          "extension": "jpg", 
          "height": 768, 
          "mimetype": "image/jpeg", 
          "secret": "QCbkfO67LlOfDq4PV4HFTNpw035uxEkA", 
          "width": 544
        }, 
        "c": {
          "extension": "jpg", 
          "height": 600, 
          "mimetype": "image/jpeg", 
          "secret": "QCbkfO67LlOfDq4PV4HFTNpw035uxEkA", 
          "width": 425
        }, 
        "dc": {
          "extension": "jpg", 
          "height": 600, 
          "mimetype": "image/jpeg", 
          "secret": "QCbkfO67LlOfDq4PV4HFTNpw035uxEkA", 
          "width": 425
        }, 
        "ds": {
          "extension": "jpg", 
          "height": 320, 
          "mimetype": "image/jpeg", 
          "secret": "QCbkfO67LlOfDq4PV4HFTNpw035uxEkA", 
          "width": 320
        }, 
        "k": {
          "extension": "jpg", 
          "height": 1536, 
          "mimetype": "image/jpeg", 
          "secret": "QCbkfO67LlOfDq4PV4HFTNpw035uxEkA", 
          "width": 1089
        }, 
        "n": {
          "extension": "jpg", 
          "height": 240, 
          "mimetype": "image/jpeg", 
          "secret": "QCbkfO67LlOfDq4PV4HFTNpw035uxEkA", 
          "width": 170
        }, 
        "o": {
          "extension": "jpg", 
          "height": 4251, 
          "mimetype": "image/jpeg", 
          "secret": "3Wr7sKjE4VZ7JnILlGkvHaNilovTlrFn", 
          "width": 3014
        }, 
        "s": {
          "extension": "jpg", 
          "height": 320, 
          "mimetype": "image/jpeg", 
          "secret": "QCbkfO67LlOfDq4PV4HFTNpw035uxEkA", 
          "width": 320
        }, 
        "z": {
          "extension": "jpg", 
          "height": 480, 
          "mimetype": "image/jpeg", 
          "secret": "QCbkfO67LlOfDq4PV4HFTNpw035uxEkA", 
          "width": 340
        }
      }
    }, 
    "sfomuseum:placetype": "image", 
    "wof:depicts": [1226603375, 1159554829, 1360516265, 1159554803, 102527513], 
    "wof:name": "Installation view of \"Building for Air Travel\"", 
    "wof:placetype": "media" 
  }, 
  "geometry": {"coordinates":[-122.384814,37.617787],"type":"Point"}
}
