{
  "type": "Feature", 
  "properties": {
    "iso:country": "US", 
    "media:created": 1455290621, 
    "media:fingerprint": "c63af24fa8bbffb0313b5dad7b1e9380c78f5684", 
    "media:medium": "image", 
    "media:mimetype": "image/jpeg", 
    "media:properties": {
      "colours": [
        {
          "hex": "#bb945e", 
          "name": "#bb945e", 
          "reference": "vibrant"
        }, 
        {
          "hex": "#843616", 
          "name": "#843616", 
          "reference": "vibrant"
        }, 
        {
          "hex": "#817f7e", 
          "name": "#817f7e", 
          "reference": "vibrant"
        }, 
        {
          "hex": "#d0bfaf", 
          "name": "#d0bfaf", 
          "reference": "vibrant"
        }, 
        {
          "hex": "#674b31", 
          "name": "#674b31", 
          "reference": "vibrant"
        }
      ], 
      "depicts": [1159160583], 
      "sizes": {
        "b": {
          "extension": "jpg", 
          "height": 768, 
          "mimetype": "image/jpeg", 
          "secret": "cazF3Z0TvC801aD6lwL5Cl2QiFOtj9q2", 
          "width": 614
        }, 
        "c": {
          "extension": "jpg", 
          "height": 600, 
          "mimetype": "image/jpeg", 
          "secret": "cazF3Z0TvC801aD6lwL5Cl2QiFOtj9q2", 
          "width": 480
        }, 
        "dc": {
          "extension": "jpg", 
          "height": 600, 
          "mimetype": "image/jpeg", 
          "secret": "cazF3Z0TvC801aD6lwL5Cl2QiFOtj9q2", 
          "width": 480
        }, 
        "ds": {
          "extension": "jpg", 
          "height": 320, 
          "mimetype": "image/jpeg", 
          "secret": "cazF3Z0TvC801aD6lwL5Cl2QiFOtj9q2", 
          "width": 320
        }, 
        "k": {
          "extension": "jpg", 
          "height": 1536, 
          "mimetype": "image/jpeg", 
          "secret": "cazF3Z0TvC801aD6lwL5Cl2QiFOtj9q2", 
          "width": 1228
        }, 
        "n": {
          "extension": "jpg", 
          "height": 240, 
          "mimetype": "image/jpeg", 
          "secret": "cazF3Z0TvC801aD6lwL5Cl2QiFOtj9q2", 
          "width": 192
        }, 
        "o": {
          "extension": "jpg", 
          "height": 3791, 
          "mimetype": "image/jpeg", 
          "secret": "lNGRMv2YyrDceNbolSAmExqAqQvDKrMt", 
          "width": 3033
        }, 
        "s": {
          "extension": "jpg", 
          "height": 320, 
          "mimetype": "image/jpeg", 
          "secret": "cazF3Z0TvC801aD6lwL5Cl2QiFOtj9q2", 
          "width": 320
        }, 
        "z": {
          "extension": "jpg", 
          "height": 480, 
          "mimetype": "image/jpeg", 
          "secret": "cazF3Z0TvC801aD6lwL5Cl2QiFOtj9q2", 
          "width": 384
        }
      }
    }, 
    "sfomuseum:placetype": "image", 
    "wof:depicts": [1159396321, 1159396153, 1159160583, 102527513, 1360516271], 
    "wof:name": "Installation view of \"Essential Style: Antique and Vintage Handbags\"", 
    "wof:placetype": "media" 
  }, 
  "geometry": {"coordinates":[-122.38902,37.614533],"type":"Point"}
}
