{
  "type": "Feature", 
  "properties": {
    "iso:country": "US", 
    "media:created": 1377883987, 
    "media:fingerprint": "fc8df909b2deb916d05a16f9cfea28bf257a5b2f", 
    "media:medium": "image", 
    "media:mimetype": "image/jpeg", 
    "media:properties": {
      "colours": [
        {
          "hex": "#898373", 
          "name": "#898373", 
          "reference": "vibrant"
        }, 
        {
          "hex": "#c6bfb0", 
          "name": "#c6bfb0", 
          "reference": "vibrant"
        }, 
        {
          "hex": "#4e4538", 
          "name": "#4e4538", 
          "reference": "vibrant"
        }
      ], 
      "depicts": [1159160349], 
      "sizes": {
        "b": {
          "extension": "jpg", 
          "height": 682, 
          "mimetype": "image/jpeg", 
          "secret": "HS2tKCtegClgSNaYbTNnv5oYTGef8lz2", 
          "width": 1024
        }, 
        "c": {
          "extension": "jpg", 
          "height": 533, 
          "mimetype": "image/jpeg", 
          "secret": "HS2tKCtegClgSNaYbTNnv5oYTGef8lz2", 
          "width": 800
        }, 
        "dc": {
          "extension": "jpg", 
          "height": 533, 
          "mimetype": "image/jpeg", 
          "secret": "HS2tKCtegClgSNaYbTNnv5oYTGef8lz2", 
          "width": 800
        }, 
        "ds": {
          "extension": "jpg", 
          "height": 320, 
          "mimetype": "image/jpeg", 
          "secret": "HS2tKCtegClgSNaYbTNnv5oYTGef8lz2", 
          "width": 320
        }, 
        "k": {
          "extension": "jpg", 
          "height": 1365, 
          "mimetype": "image/jpeg", 
          "secret": "HS2tKCtegClgSNaYbTNnv5oYTGef8lz2", 
          "width": 2048
        }, 
        "n": {
          "extension": "jpg", 
          "height": 213, 
          "mimetype": "image/jpeg", 
          "secret": "HS2tKCtegClgSNaYbTNnv5oYTGef8lz2", 
          "width": 320
        }, 
        "o": {
          "extension": "jpg", 
          "height": 2400, 
          "mimetype": "image/jpeg", 
          "secret": "ski2SYPqiUSasXv04X3MFLEIF0Rnv217", 
          "width": 3600
        }, 
        "s": {
          "extension": "jpg", 
          "height": 320, 
          "mimetype": "image/jpeg", 
          "secret": "HS2tKCtegClgSNaYbTNnv5oYTGef8lz2", 
          "width": 320
        }, 
        "z": {
          "extension": "jpg", 
          "height": 426, 
          "mimetype": "image/jpeg", 
          "secret": "HS2tKCtegClgSNaYbTNnv5oYTGef8lz2", 
          "width": 640
        }
      }
    }, 
    "sfomuseum:placetype": "image", 
    "wof:depicts": [
      1159396333, 
      1159396159, 
      1360516193, 
      1159160349, 
      102527513, 
      1360516183
    ], 
    "wof:name": "Installation view of \"America’s Cup, Sailing for International Sport’s Greatest Trophy 1851-1937\"", 
    "wof:placetype": "media" 
  }, 
  "geometry": {"coordinates":[-122.388942,37.615424],"type":"Point"}
}
