{
  "type": "Feature",
  "properties": {
    "iso:country": "US",
    "media:created": 1301088493,
    "media:fingerprint": "b46d16ae2f9d58334e5b69c1e1c3b15e2ba33722",
    "media:imagehash_avg": "a:787e67773a323e7a",
    "media:imagehash_diff": "d:d094cfcec266f4e2",
    "media:medium": "image",
    "media:mimetype": "image/jpeg",
    "media:properties": {
      "colours": [
        {
          "hex": "#bd5a0d",
          "name": "#bd5a0d",
          "reference": "vibrant"
        },
        {
          "hex": "#2166a1",
          "name": "#2166a1",
          "reference": "vibrant"
        },
        {
          "hex": "#87837e",
          "name": "#87837e",
          "reference": "vibrant"
        },
        {
          "hex": "#bfbfbc",
          "name": "#bfbfbc",
          "reference": "vibrant"
        },
        {
          "hex": "#523830",
          "name": "#523830",
          "reference": "vibrant"
        }
      ],
      "depicts": [
        772975731
      ],
      "sizes": {
        "b": {
          "extension": "jpg",
          "height": 682,
          "mimetype": "image/jpeg",
          "secret": "8OLePsS4vwoHDmxqvO5XV6xsW5yVoOWL",
          "width": 1024
        },
        "c": {
          "extension": "jpg",
          "height": 533,
          "mimetype": "image/jpeg",
          "secret": "8OLePsS4vwoHDmxqvO5XV6xsW5yVoOWL",
          "width": 800
        },
        "dc": {
          "extension": "jpg",
          "height": 533,
          "mimetype": "image/jpeg",
          "secret": "8OLePsS4vwoHDmxqvO5XV6xsW5yVoOWL",
          "width": 800
        },
        "ds": {
          "extension": "jpg",
          "height": 320,
          "mimetype": "image/jpeg",
          "secret": "8OLePsS4vwoHDmxqvO5XV6xsW5yVoOWL",
          "width": 320
        },
        "k": {
          "extension": "jpg",
          "height": 1365,
          "mimetype": "image/jpeg",
          "secret": "8OLePsS4vwoHDmxqvO5XV6xsW5yVoOWL",
          "width": 2048
        },
        "n": {
          "extension": "jpg",
          "height": 213,
          "mimetype": "image/jpeg",
          "secret": "8OLePsS4vwoHDmxqvO5XV6xsW5yVoOWL",
          "width": 320
        },
        "o": {
          "extension": "jpg",
          "height": 2400,
          "mimetype": "image/jpeg",
          "secret": "0R2xKnIuGh42NxQSeozt2SwUAYngSe8B",
          "width": 3600
        },
        "s": {
          "extension": "jpg",
          "height": 320,
          "mimetype": "image/jpeg",
          "secret": "8OLePsS4vwoHDmxqvO5XV6xsW5yVoOWL",
          "width": 320
        },
        "z": {
          "extension": "jpg",
          "height": 426,
          "mimetype": "image/jpeg",
          "secret": "8OLePsS4vwoHDmxqvO5XV6xsW5yVoOWL",
          "width": 640
        }
      }
    },
    "sfomuseum:placetype": "image",
    "wof:depicts": [
      772975731,
      102527513
    ],
    "wof:name": "Welcome North, Welcome South, Welcome East, Welcome West",
    "wof:placetype": "media"
  },
  "geometry": {"coordinates":[-122.383645,37.61724],"type":"Point"}
}
