{
  "type": "Feature",
  "properties": {
    "iso:country": "US",
    "media:created": 1545308562,
    "media:fingerprint": "d94507029341d0c88c9bd4c4f0623846e62de900",
    "media:imagehash_avg": "a:ffef7c18003c3c00",
    "media:imagehash_diff": "d:948ed0f0f2f8f8f0",
    "media:medium": "image",
    "media:mimetype": "image/jpeg",
    "media:properties": {
      "colours": [
        {
          "hex": "#d69942",
          "name": "#d69942",
          "reference": "vibrant"
        }, 
        {
          "hex": "#da9e70",
          "name": "#da9e70",
          "reference": "vibrant"
        }, 
        {
          "hex": "#ac2630",
          "name": "#ac2630",
          "reference": "vibrant"
        }, 
        {
          "hex": "#a39266",
          "name": "#a39266",
          "reference": "vibrant"
        }, 
        {
          "hex": "#b6bec5",
          "name": "#b6bec5",
          "reference": "vibrant"
        }
      ],
      "depicts": [
        1360702457
      ],
      "sizes": {
        "b": {
          "extension": "jpg",
          "height": 682,
          "mimetype": "image/jpeg",
          "secret": "Tu1dQ1teAqyQA5fgkUrcsWe3fa9MXv1m",
          "width": 1024
        },
        "c": {
          "extension": "jpg",
          "height": 533,
          "mimetype": "image/jpeg",
          "secret": "Tu1dQ1teAqyQA5fgkUrcsWe3fa9MXv1m",
          "width": 800
        },
        "dc": {
          "extension": "jpg",
          "height": 533,
          "mimetype": "image/jpeg",
          "secret": "Tu1dQ1teAqyQA5fgkUrcsWe3fa9MXv1m",
          "width": 800
        },
        "ds": {
          "extension": "jpg",
          "height": 320,
          "mimetype": "image/jpeg",
          "secret": "Tu1dQ1teAqyQA5fgkUrcsWe3fa9MXv1m",
          "width": 320
        },
        "k": {
          "extension": "jpg",
          "height": 1365,
          "mimetype": "image/jpeg",
          "secret": "Tu1dQ1teAqyQA5fgkUrcsWe3fa9MXv1m",
          "width": 2048
        },
        "n": {
          "extension": "jpg",
          "height": 213,
          "mimetype": "image/jpeg",
          "secret": "Tu1dQ1teAqyQA5fgkUrcsWe3fa9MXv1m",
          "width": 320
        },
        "o": {
          "extension": "jpg",
          "height": 2400,
          "mimetype": "image/jpeg",
          "secret": "8mhyCgok2cF57tJ3FbR5e2eK6XwoE4EH",
          "width": 3600
        },
        "s": {
          "extension": "jpg",
          "height": 320,
          "mimetype": "image/jpeg",
          "secret": "Tu1dQ1teAqyQA5fgkUrcsWe3fa9MXv1m",
          "width": 320
        },
        "z": {
          "extension": "jpg",
          "height": 426,
          "mimetype": "image/jpeg",
          "secret": "Tu1dQ1teAqyQA5fgkUrcsWe3fa9MXv1m",
          "width": 640
        }
      }
    },
    "sfomuseum:placetype": "image",
    "wof:depicts": [
      102527513, 
      1159396301, 
      1159157053, 
      1360702457, 
      1159157271, 
      1159157307
    ],
    "wof:name": "Installation view of \"The Modern Consumer – 1950s Products and Styles\"",
    "wof:placetype": "media"
  },
  "geometry": {"coordinates":[-122.387197,37.619087],"type":"Point"}
}
