{
  "type": "Feature", 
  "properties": {
    "iso:country": "US", 
    "media:created": 1360968142, 
    "media:fingerprint": "6f3c6ca569118feb64f979fd21b028635d8d6696", 
    "media:medium": "image", 
    "media:mimetype": "image/jpeg", 
    "media:properties": {
      "colours": [
        {
          "hex": "#d94d35", 
          "name": "#d94d35", 
          "reference": "vibrant"
        }, 
        {
          "hex": "#c8b888", 
          "name": "#c8b888", 
          "reference": "vibrant"
        }, 
        {
          "hex": "#ab8861", 
          "name": "#ab8861", 
          "reference": "vibrant"
        }, 
        {
          "hex": "#c6c0a6", 
          "name": "#c6c0a6", 
          "reference": "vibrant"
        }, 
        {
          "hex": "#3c4344", 
          "name": "#3c4344", 
          "reference": "vibrant"
        }
      ], 
      "depicts": [1159160359], 
      "sizes": {
        "b": {
          "extension": "jpg", 
          "height": 768, 
          "mimetype": "image/jpeg", 
          "secret": "u0OfLHZjq2qlg1efSkRcpLXLjE718TE7", 
          "width": 512
        }, 
        "c": {
          "extension": "jpg", 
          "height": 600, 
          "mimetype": "image/jpeg", 
          "secret": "u0OfLHZjq2qlg1efSkRcpLXLjE718TE7", 
          "width": 400
        }, 
        "dc": {
          "extension": "jpg", 
          "height": 600, 
          "mimetype": "image/jpeg", 
          "secret": "u0OfLHZjq2qlg1efSkRcpLXLjE718TE7", 
          "width": 400
        }, 
        "ds": {
          "extension": "jpg", 
          "height": 320, 
          "mimetype": "image/jpeg", 
          "secret": "u0OfLHZjq2qlg1efSkRcpLXLjE718TE7", 
          "width": 320
        }, 
        "k": {
          "extension": "jpg", 
          "height": 1536, 
          "mimetype": "image/jpeg", 
          "secret": "u0OfLHZjq2qlg1efSkRcpLXLjE718TE7", 
          "width": 1024
        }, 
        "n": {
          "extension": "jpg", 
          "height": 240, 
          "mimetype": "image/jpeg", 
          "secret": "u0OfLHZjq2qlg1efSkRcpLXLjE718TE7", 
          "width": 160
        }, 
        "o": {
          "extension": "jpg", 
          "height": 3600, 
          "mimetype": "image/jpeg", 
          "secret": "4bsIwYwpjUZO6PBOVBfYCjSCDmBvpkc2", 
          "width": 2400
        }, 
        "s": {
          "extension": "jpg", 
          "height": 320, 
          "mimetype": "image/jpeg", 
          "secret": "u0OfLHZjq2qlg1efSkRcpLXLjE718TE7", 
          "width": 320
        }, 
        "z": {
          "extension": "jpg", 
          "height": 480, 
          "mimetype": "image/jpeg", 
          "secret": "u0OfLHZjq2qlg1efSkRcpLXLjE718TE7", 
          "width": 320
        }
      }
    }, 
    "sfomuseum:placetype": "image", 
    "wof:depicts": [1159396159, 1360516283, 1159160359, 1159396333, 102527513], 
    "wof:name": "Installation view of \"Souvenirs: Tokens of Travel\"", 
    "wof:placetype": "media" 
  }, 
  "geometry": {"coordinates":[-122.389725,37.616594],"type":"Point"}
}
