{
  "type": "Feature",
  "properties": {
    "iso:country": "US",
    "media:created": -1,
    "media:fingerprint": "ce26990e2c812b3848a2b85e85ff4550382d118a",
    "media:imagehash_avg": "a:624242df3c3c3c18",
    "media:imagehash_diff": "d:ce96b2b2b07970f0",
    "media:medium": "image",
    "media:mimetype": "image/tiff",
    "media:properties": {
      "colours": [
        {
          "hex": "#b68666",
          "name": "#b68666",
          "reference": "vibrant"
        }, 
        {
          "hex": "#ddaf89",
          "name": "#ddaf89",
          "reference": "vibrant"
        }, 
        {
          "hex": "#88281c",
          "name": "#88281c",
          "reference": "vibrant"
        }, 
        {
          "hex": "#97755f",
          "name": "#97755f",
          "reference": "vibrant"
        }, 
        {
          "hex": "#d7bea6",
          "name": "#d7bea6",
          "reference": "vibrant"
        }
      ],
      "depicts": [
        1226612107
      ],
      "sizes": {
        "b": {
          "extension": "jpg",
          "height": 724,
          "mimetype": "image/jpeg",
          "secret": "ujgmwu2HB4jFGwnp17YIZ6VyboMx6FZb",
          "width": 1024
        },
        "c": {
          "extension": "jpg",
          "height": 565,
          "mimetype": "image/jpeg",
          "secret": "ujgmwu2HB4jFGwnp17YIZ6VyboMx6FZb",
          "width": 800
        },
        "dc": {
          "extension": "jpg",
          "height": 565,
          "mimetype": "image/jpeg",
          "secret": "ujgmwu2HB4jFGwnp17YIZ6VyboMx6FZb",
          "width": 800
        },
        "ds": {
          "extension": "jpg",
          "height": 320,
          "mimetype": "image/jpeg",
          "secret": "ujgmwu2HB4jFGwnp17YIZ6VyboMx6FZb",
          "width": 320
        },
        "k": {
          "extension": "jpg",
          "height": 1448,
          "mimetype": "image/jpeg",
          "secret": "ujgmwu2HB4jFGwnp17YIZ6VyboMx6FZb",
          "width": 2048
        },
        "n": {
          "extension": "jpg",
          "height": 226,
          "mimetype": "image/jpeg",
          "secret": "ujgmwu2HB4jFGwnp17YIZ6VyboMx6FZb",
          "width": 320
        },
        "o": {
          "extension": "jpg",
          "height": 3014,
          "mimetype": "image/jpeg",
          "secret": "WyVu3dxuOEmLyTYrkGdI2NcwtCVWiwTt",
          "width": 4262
        },
        "s": {
          "extension": "jpg",
          "height": 320,
          "mimetype": "image/jpeg",
          "secret": "ujgmwu2HB4jFGwnp17YIZ6VyboMx6FZb",
          "width": 320
        },
        "z": {
          "extension": "jpg",
          "height": 452,
          "mimetype": "image/jpeg",
          "secret": "ujgmwu2HB4jFGwnp17YIZ6VyboMx6FZb",
          "width": 640
        }
      }
    },
    "sfomuseum:placetype": "image",
    "wof:depicts": [
      1226612107, 
      102527513, 
      1159554841, 
      1159554801, 
      1159554819, 
      1360516129
    ],
    "wof:name": "Installation view of \"Airport Cafe\"",
    "wof:placetype": "media"
  },
  "geometry": {"coordinates":[-122.387197,37.619087],"type":"Point"}
}
