{
  "type": "Feature", 
  "properties": {
    "iso:country": "US", 
    "media:created": 1342820610, 
    "media:fingerprint": "c0e63c098bbdb0c67401fb397b30097c85eb7cdd", 
    "media:medium": "image", 
    "media:mimetype": "image/jpeg", 
    "media:properties": {
      "colours": [
        {
          "hex": "#a7433f", 
          "name": "#a7433f", 
          "reference": "vibrant"
        }, 
        {
          "hex": "#30638e", 
          "name": "#30638e", 
          "reference": "vibrant"
        }, 
        {
          "hex": "#987c67", 
          "name": "#987c67", 
          "reference": "vibrant"
        }, 
        {
          "hex": "#bdb3ab", 
          "name": "#bdb3ab", 
          "reference": "vibrant"
        }, 
        {
          "hex": "#4a3f3b", 
          "name": "#4a3f3b", 
          "reference": "vibrant"
        }
      ], 
      "depicts": [1159160327], 
      "sizes": {
        "b": {
          "extension": "jpg", 
          "height": 682, 
          "mimetype": "image/jpeg", 
          "secret": "GeWBEVEDcRKdq5mhlzR0MkYLRSjEYtqc", 
          "width": 1024
        }, 
        "c": {
          "extension": "jpg", 
          "height": 533, 
          "mimetype": "image/jpeg", 
          "secret": "GeWBEVEDcRKdq5mhlzR0MkYLRSjEYtqc", 
          "width": 800
        }, 
        "dc": {
          "extension": "jpg", 
          "height": 533, 
          "mimetype": "image/jpeg", 
          "secret": "GeWBEVEDcRKdq5mhlzR0MkYLRSjEYtqc", 
          "width": 800
        }, 
        "ds": {
          "extension": "jpg", 
          "height": 320, 
          "mimetype": "image/jpeg", 
          "secret": "GeWBEVEDcRKdq5mhlzR0MkYLRSjEYtqc", 
          "width": 320
        }, 
        "k": {
          "extension": "jpg", 
          "height": 1365, 
          "mimetype": "image/jpeg", 
          "secret": "GeWBEVEDcRKdq5mhlzR0MkYLRSjEYtqc", 
          "width": 2048
        }, 
        "n": {
          "extension": "jpg", 
          "height": 213, 
          "mimetype": "image/jpeg", 
          "secret": "GeWBEVEDcRKdq5mhlzR0MkYLRSjEYtqc", 
          "width": 320
        }, 
        "o": {
          "extension": "jpg", 
          "height": 2400, 
          "mimetype": "image/jpeg", 
          "secret": "K0DRb5nCiUiL9mx8t7jCXeQg87yaiKIg", 
          "width": 3600
        }, 
        "s": {
          "extension": "jpg", 
          "height": 320, 
          "mimetype": "image/jpeg", 
          "secret": "GeWBEVEDcRKdq5mhlzR0MkYLRSjEYtqc", 
          "width": 320
        }, 
        "z": {
          "extension": "jpg", 
          "height": 426, 
          "mimetype": "image/jpeg", 
          "secret": "GeWBEVEDcRKdq5mhlzR0MkYLRSjEYtqc", 
          "width": 640
        }
      }
    }, 
    "sfomuseum:placetype": "image", 
    "wof:depicts": [
      1159396333, 
      1159396159, 
      1360516193, 
      1159160327, 
      102527513, 
      1360516183
    ], 
    "wof:name": "Installation view of \"From Repack to Rwanda, The Origins, Evolution and Global Reach of the Mountain Bike\"", 
    "wof:placetype": "media" 
  }, 
  "geometry": {"coordinates":[-122.389131,37.616029],"type":"Point"}
}
