{
  "type": "Feature", 
  "properties": {
    "iso:country": "US", 
    "media:created": 1521740873, 
    "media:fingerprint": "628a753fb13124c0247efe8e69393c190e47fac4", 
    "media:medium": "image", 
    "media:mimetype": "image/jpeg", 
    "media:properties": {
      "colours": [
        {
          "hex": "#eb915b", 
          "name": "#eb915b", 
          "reference": "vibrant"
        }, 
        {
          "hex": "#9c7b5a", 
          "name": "#9c7b5a", 
          "reference": "vibrant"
        }, 
        {
          "hex": "#b0b9c0", 
          "name": "#b0b9c0", 
          "reference": "vibrant"
        }, 
        {
          "hex": "#4c433e", 
          "name": "#4c433e", 
          "reference": "vibrant"
        }
      ], 
      "depicts": [1159160853], 
      "sizes": {
        "b": {
          "extension": "jpg", 
          "height": 682, 
          "mimetype": "image/jpeg", 
          "secret": "XtkFc14nWRx9dJmwAg9APzSecl8udmSd", 
          "width": 1024
        }, 
        "c": {
          "extension": "jpg", 
          "height": 533, 
          "mimetype": "image/jpeg", 
          "secret": "XtkFc14nWRx9dJmwAg9APzSecl8udmSd", 
          "width": 800
        }, 
        "dc": {
          "extension": "jpg", 
          "height": 533, 
          "mimetype": "image/jpeg", 
          "secret": "XtkFc14nWRx9dJmwAg9APzSecl8udmSd", 
          "width": 800
        }, 
        "ds": {
          "extension": "jpg", 
          "height": 320, 
          "mimetype": "image/jpeg", 
          "secret": "XtkFc14nWRx9dJmwAg9APzSecl8udmSd", 
          "width": 320
        }, 
        "k": {
          "extension": "jpg", 
          "height": 1365, 
          "mimetype": "image/jpeg", 
          "secret": "XtkFc14nWRx9dJmwAg9APzSecl8udmSd", 
          "width": 2048
        }, 
        "n": {
          "extension": "jpg", 
          "height": 213, 
          "mimetype": "image/jpeg", 
          "secret": "XtkFc14nWRx9dJmwAg9APzSecl8udmSd", 
          "width": 320
        }, 
        "o": {
          "extension": "jpg", 
          "height": 2400, 
          "mimetype": "image/jpeg", 
          "secret": "hjAKwAWpkD9rmVLq6LSoYxpmS4MgfuiY", 
          "width": 3600
        }, 
        "s": {
          "extension": "jpg", 
          "height": 320, 
          "mimetype": "image/jpeg", 
          "secret": "XtkFc14nWRx9dJmwAg9APzSecl8udmSd", 
          "width": 320
        }, 
        "z": {
          "extension": "jpg", 
          "height": 426, 
          "mimetype": "image/jpeg", 
          "secret": "XtkFc14nWRx9dJmwAg9APzSecl8udmSd", 
          "width": 640
        }
      }
    }, 
    "sfomuseum:placetype": "image", 
    "wof:depicts": [
      1159157053, 
      1159157307, 
      1159396301, 
      102527513, 
      1159160853, 
      1159157271
    ], 
    "wof:name": "Installation view of \"On the Radio\"", 
    "wof:placetype": "media" 
  }, 
  "geometry": {"coordinates":[-122.387197,37.619087],"type":"Point"}
}
