{
  "type": "Feature",
  "properties": {
    "iso:country": "US",
    "media:created": 1377884070,
    "media:fingerprint": "57a49771a23069f71e401249fc2685070dd32409",
    "media:imagehash_avg": "a:190801011cfcffff",
    "media:imagehash_diff": "d:7b73f7d33171f1f1",
    "media:medium": "image",
    "media:mimetype": "image/jpeg",
    "media:properties": {
      "colours": [
        {
          "hex": "#563129",
          "name": "#563129",
          "reference": "vibrant"
        }, 
        {
          "hex": "#627590",
          "name": "#627590",
          "reference": "vibrant"
        }, 
        {
          "hex": "#c8baa8",
          "name": "#c8baa8",
          "reference": "vibrant"
        }, 
        {
          "hex": "#664839",
          "name": "#664839",
          "reference": "vibrant"
        }
      ],
      "depicts": [
        1159160349
      ],
      "sizes": {
        "b": {
          "extension": "jpg",
          "height": 682,
          "mimetype": "image/jpeg",
          "secret": "ZSgsQzUxQyLmy4TLW8q4Y1ew8tO3LFmN",
          "width": 1024
        },
        "c": {
          "extension": "jpg",
          "height": 533,
          "mimetype": "image/jpeg",
          "secret": "ZSgsQzUxQyLmy4TLW8q4Y1ew8tO3LFmN",
          "width": 800
        },
        "dc": {
          "extension": "jpg",
          "height": 533,
          "mimetype": "image/jpeg",
          "secret": "ZSgsQzUxQyLmy4TLW8q4Y1ew8tO3LFmN",
          "width": 800
        },
        "ds": {
          "extension": "jpg",
          "height": 320,
          "mimetype": "image/jpeg",
          "secret": "ZSgsQzUxQyLmy4TLW8q4Y1ew8tO3LFmN",
          "width": 320
        },
        "k": {
          "extension": "jpg",
          "height": 1365,
          "mimetype": "image/jpeg",
          "secret": "ZSgsQzUxQyLmy4TLW8q4Y1ew8tO3LFmN",
          "width": 2048
        },
        "n": {
          "extension": "jpg",
          "height": 213,
          "mimetype": "image/jpeg",
          "secret": "ZSgsQzUxQyLmy4TLW8q4Y1ew8tO3LFmN",
          "width": 320
        },
        "o": {
          "extension": "jpg",
          "height": 2400,
          "mimetype": "image/jpeg",
          "secret": "6JPil79L8q5nPDf6zX25A5xtCe4Ew8f6",
          "width": 3600
        },
        "s": {
          "extension": "jpg",
          "height": 320,
          "mimetype": "image/jpeg",
          "secret": "ZSgsQzUxQyLmy4TLW8q4Y1ew8tO3LFmN",
          "width": 320
        },
        "z": {
          "extension": "jpg",
          "height": 426,
          "mimetype": "image/jpeg",
          "secret": "ZSgsQzUxQyLmy4TLW8q4Y1ew8tO3LFmN",
          "width": 640
        }
      }
    },
    "sfomuseum:placetype": "image",
    "wof:depicts": [
      1159396159, 
      1360516193, 
      102527513, 
      1159396333, 
      1360516183, 
      1159160349
    ],
    "wof:name": "Installation view of \"America’s Cup, Sailing for International Sport’s Greatest Trophy 1851-1937\"",
    "wof:placetype": "media"
  },
  "geometry": {"coordinates":[-122.388942,37.615424],"type":"Point"}
}
