{
  "type": "Feature", 
  "properties": {
    "iso:country": "US", 
    "media:created": 1385422781, 
    "media:fingerprint": "1bcaf0819d5d512b54d541a1d683275f06d19e4d", 
    "media:medium": "image", 
    "media:mimetype": "image/jpeg", 
    "media:properties": {
      "colours": [
        {
          "hex": "#d06255", 
          "name": "#d06255", 
          "reference": "vibrant"
        }, 
        {
          "hex": "#cb8d7a", 
          "name": "#cb8d7a", 
          "reference": "vibrant"
        }, 
        {
          "hex": "#768789", 
          "name": "#768789", 
          "reference": "vibrant"
        }, 
        {
          "hex": "#c3bdb0", 
          "name": "#c3bdb0", 
          "reference": "vibrant"
        }, 
        {
          "hex": "#633e33", 
          "name": "#633e33", 
          "reference": "vibrant"
        }
      ], 
      "depicts": [1159160467], 
      "sizes": {
        "b": {
          "extension": "jpg", 
          "height": 602, 
          "mimetype": "image/jpeg", 
          "secret": "bnOa4CS0mN1lNFT5ulYzKsVzB0NuBIlT", 
          "width": 1024
        }, 
        "c": {
          "extension": "jpg", 
          "height": 470, 
          "mimetype": "image/jpeg", 
          "secret": "bnOa4CS0mN1lNFT5ulYzKsVzB0NuBIlT", 
          "width": 800
        }, 
        "dc": {
          "extension": "jpg", 
          "height": 470, 
          "mimetype": "image/jpeg", 
          "secret": "bnOa4CS0mN1lNFT5ulYzKsVzB0NuBIlT", 
          "width": 800
        }, 
        "ds": {
          "extension": "jpg", 
          "height": 320, 
          "mimetype": "image/jpeg", 
          "secret": "bnOa4CS0mN1lNFT5ulYzKsVzB0NuBIlT", 
          "width": 320
        }, 
        "k": {
          "extension": "jpg", 
          "height": 1204, 
          "mimetype": "image/jpeg", 
          "secret": "bnOa4CS0mN1lNFT5ulYzKsVzB0NuBIlT", 
          "width": 2048
        }, 
        "n": {
          "extension": "jpg", 
          "height": 188, 
          "mimetype": "image/jpeg", 
          "secret": "bnOa4CS0mN1lNFT5ulYzKsVzB0NuBIlT", 
          "width": 320
        }, 
        "o": {
          "extension": "jpg", 
          "height": 2118, 
          "mimetype": "image/jpeg", 
          "secret": "kCLpMbwntA1kpbYmP0TvMleO5FMOEfjD", 
          "width": 3600
        }, 
        "s": {
          "extension": "jpg", 
          "height": 320, 
          "mimetype": "image/jpeg", 
          "secret": "bnOa4CS0mN1lNFT5ulYzKsVzB0NuBIlT", 
          "width": 320
        }, 
        "z": {
          "extension": "jpg", 
          "height": 376, 
          "mimetype": "image/jpeg", 
          "secret": "bnOa4CS0mN1lNFT5ulYzKsVzB0NuBIlT", 
          "width": 640
        }
      }
    }, 
    "sfomuseum:placetype": "image", 
    "wof:depicts": [
      1159396153, 
      1159396321, 
      1360541657, 
      1159160467, 
      1360521563, 
      102527513
    ], 
    "wof:name": "Installation view of \"Airline Identity: Marks, Brands and Logos\"", 
    "wof:placetype": "media" 
  }, 
  "geometry": {"coordinates":[-122.387989,37.614385],"type":"Point"}
}
