{
  "type": "Feature",
  "properties": {
    "date:cessation_lower": "2010-08-16",
    "date:cessation_upper": "2010-08-16",
    "date:inception_lower": "2010-02-19",
    "date:inception_upper": "2010-02-19",
    "iso:country": "US",
    "media:created": 1270142139,
    "media:fingerprint": "7df4c8296272e55be88dee21b7a8abd7017e0301",
    "media:imagehash_avg": "a:ffc0c040404000ff",
    "media:imagehash_diff": "d:a69696b0b0b0acf0",
    "media:medium": "image",
    "media:mimetype": "image/jpeg",
    "media:properties": {
      "colours": [
        {
          "hex": "#c43935",
          "name": "#c43935",
          "reference": "vibrant"
        },
        {
          "hex": "#942423",
          "name": "#942423",
          "reference": "vibrant"
        },
        {
          "hex": "#5e8ab0",
          "name": "#5e8ab0",
          "reference": "vibrant"
        },
        {
          "hex": "#c4b7ac",
          "name": "#c4b7ac",
          "reference": "vibrant"
        },
        {
          "hex": "#303b44",
          "name": "#303b44",
          "reference": "vibrant"
        }
      ],
      "depicts": [
        1159160109
      ],
      "sizes": {
        "b": {
          "extension": "jpg",
          "height": 768,
          "mimetype": "image/jpeg",
          "secret": "XRwIR9tv4bokNniyW0y9H58XQyneaO1d",
          "width": 514
        },
        "c": {
          "extension": "jpg",
          "height": 600,
          "mimetype": "image/jpeg",
          "secret": "XRwIR9tv4bokNniyW0y9H58XQyneaO1d",
          "width": 401
        },
        "dc": {
          "extension": "jpg",
          "height": 600,
          "mimetype": "image/jpeg",
          "secret": "XRwIR9tv4bokNniyW0y9H58XQyneaO1d",
          "width": 401
        },
        "ds": {
          "extension": "jpg",
          "height": 320,
          "mimetype": "image/jpeg",
          "secret": "XRwIR9tv4bokNniyW0y9H58XQyneaO1d",
          "width": 320
        },
        "k": {
          "extension": "jpg",
          "height": 1536,
          "mimetype": "image/jpeg",
          "secret": "XRwIR9tv4bokNniyW0y9H58XQyneaO1d",
          "width": 1028
        },
        "n": {
          "extension": "jpg",
          "height": 240,
          "mimetype": "image/jpeg",
          "secret": "XRwIR9tv4bokNniyW0y9H58XQyneaO1d",
          "width": 160
        },
        "o": {
          "extension": "jpg",
          "height": 3872,
          "mimetype": "image/jpeg",
          "secret": "pZfaifv7RKzchqc4lOAsT6UdMQ3uTswu",
          "width": 2592
        },
        "s": {
          "extension": "jpg",
          "height": 320,
          "mimetype": "image/jpeg",
          "secret": "XRwIR9tv4bokNniyW0y9H58XQyneaO1d",
          "width": 320
        },
        "z": {
          "extension": "jpg",
          "height": 480,
          "mimetype": "image/jpeg",
          "secret": "XRwIR9tv4bokNniyW0y9H58XQyneaO1d",
          "width": 321
        }
      }
    },
    "sfomuseum:placetype": "image",
    "wof:depicts": [
      1159160109,
      1360521569,
      102527513,
      1360541661,
      1159396337,
      1159396147
    ],
    "wof:name": "Installation view of \"Japan Airlines: Over Fifty-Five Years of Service\"",
    "wof:placetype": "media"
  },
  "geometry": {"coordinates":[-122.387989,37.614385],"type":"Point"}
}
