{
  "type": "Feature", 
  "properties": {
    "iso:country": "US", 
    "media:created": -1, 
    "media:fingerprint": "6f26716c8920f17afed8adcee73ca1bdf62c9088", 
    "media:medium": "image", 
    "media:mimetype": "image/tiff", 
    "media:properties": {
      "colours": [
        {
          "hex": "#a5bed5", 
          "name": "#a5bed5", 
          "reference": "vibrant"
        }, 
        {
          "hex": "#6b7d8a", 
          "name": "#6b7d8a", 
          "reference": "vibrant"
        }, 
        {
          "hex": "#91a9bf", 
          "name": "#91a9bf", 
          "reference": "vibrant"
        }, 
        {
          "hex": "#35394c", 
          "name": "#35394c", 
          "reference": "vibrant"
        }
      ], 
      "depicts": [1376812951], 
      "sizes": {
        "b": {
          "extension": "jpg", 
          "height": 726, 
          "mimetype": "image/jpeg", 
          "secret": "5UhxJWIbhsU1es7NF5y9DQBFMWa89XM8", 
          "width": 1024
        }, 
        "c": {
          "extension": "jpg", 
          "height": 567, 
          "mimetype": "image/jpeg", 
          "secret": "5UhxJWIbhsU1es7NF5y9DQBFMWa89XM8", 
          "width": 800
        }, 
        "dc": {
          "extension": "jpg", 
          "height": 567, 
          "mimetype": "image/jpeg", 
          "secret": "5UhxJWIbhsU1es7NF5y9DQBFMWa89XM8", 
          "width": 800
        }, 
        "ds": {
          "extension": "jpg", 
          "height": 320, 
          "mimetype": "image/jpeg", 
          "secret": "5UhxJWIbhsU1es7NF5y9DQBFMWa89XM8", 
          "width": 320
        }, 
        "k": {
          "extension": "jpg", 
          "height": 1452, 
          "mimetype": "image/jpeg", 
          "secret": "5UhxJWIbhsU1es7NF5y9DQBFMWa89XM8", 
          "width": 2048
        }, 
        "n": {
          "extension": "jpg", 
          "height": 226, 
          "mimetype": "image/jpeg", 
          "secret": "5UhxJWIbhsU1es7NF5y9DQBFMWa89XM8", 
          "width": 320
        }, 
        "o": {
          "extension": "jpg", 
          "height": 3014, 
          "mimetype": "image/jpeg", 
          "secret": "Ey8fGvU1m9F8PY4HuGhiJS2Lb5w5v4ts", 
          "width": 4251
        }, 
        "s": {
          "extension": "jpg", 
          "height": 320, 
          "mimetype": "image/jpeg", 
          "secret": "5UhxJWIbhsU1es7NF5y9DQBFMWa89XM8", 
          "width": 320
        }, 
        "z": {
          "extension": "jpg", 
          "height": 453, 
          "mimetype": "image/jpeg", 
          "secret": "5UhxJWIbhsU1es7NF5y9DQBFMWa89XM8", 
          "width": 640
        }
      }
    }, 
    "sfomuseum:placetype": "image", 
    "wof:depicts": [
      1159554855, 
      1376812951, 
      1159554821, 
      102527513, 
      1360516127, 
      1159554803
    ], 
    "wof:name": "Installation view of \"Before the 21st Century: An Ode to Boats, Cars, Motorcycles, Planes, and Trains\"", 
    "wof:placetype": "media" 
  }, 
  "geometry": {"coordinates":[-122.387197,37.619087],"type":"Point"}
}
