{
  "type": "Feature", 
  "properties": {
    "iso:country": "US", 
    "media:created": 1352161625, 
    "media:fingerprint": "fc32019542658d4c6d892793427a5f7ff81bdfb2", 
    "media:medium": "image", 
    "media:mimetype": "image/jpeg", 
    "media:properties": {
      "colours": [
        {
          "hex": "#b56731", 
          "name": "#b56731", 
          "reference": "vibrant"
        }, 
        {
          "hex": "#2d6650", 
          "name": "#2d6650", 
          "reference": "vibrant"
        }, 
        {
          "hex": "#a7875a", 
          "name": "#a7875a", 
          "reference": "vibrant"
        }, 
        {
          "hex": "#c0bcb0", 
          "name": "#c0bcb0", 
          "reference": "vibrant"
        }, 
        {
          "hex": "#54463c", 
          "name": "#54463c", 
          "reference": "vibrant"
        }
      ], 
      "depicts": [1159160347], 
      "sizes": {
        "b": {
          "extension": "jpg", 
          "height": 768, 
          "mimetype": "image/jpeg", 
          "secret": "LpeARsyv5DvJLnY9R7jbvlRSRLW9lWuE", 
          "width": 512
        }, 
        "c": {
          "extension": "jpg", 
          "height": 600, 
          "mimetype": "image/jpeg", 
          "secret": "LpeARsyv5DvJLnY9R7jbvlRSRLW9lWuE", 
          "width": 400
        }, 
        "dc": {
          "extension": "jpg", 
          "height": 600, 
          "mimetype": "image/jpeg", 
          "secret": "LpeARsyv5DvJLnY9R7jbvlRSRLW9lWuE", 
          "width": 400
        }, 
        "ds": {
          "extension": "jpg", 
          "height": 320, 
          "mimetype": "image/jpeg", 
          "secret": "LpeARsyv5DvJLnY9R7jbvlRSRLW9lWuE", 
          "width": 320
        }, 
        "k": {
          "extension": "jpg", 
          "height": 1536, 
          "mimetype": "image/jpeg", 
          "secret": "LpeARsyv5DvJLnY9R7jbvlRSRLW9lWuE", 
          "width": 1024
        }, 
        "n": {
          "extension": "jpg", 
          "height": 240, 
          "mimetype": "image/jpeg", 
          "secret": "LpeARsyv5DvJLnY9R7jbvlRSRLW9lWuE", 
          "width": 160
        }, 
        "o": {
          "extension": "jpg", 
          "height": 3600, 
          "mimetype": "image/jpeg", 
          "secret": "gWlu9NCr8PHnEYXqYUnAmERHrz2GWa8i", 
          "width": 2400
        }, 
        "s": {
          "extension": "jpg", 
          "height": 320, 
          "mimetype": "image/jpeg", 
          "secret": "LpeARsyv5DvJLnY9R7jbvlRSRLW9lWuE", 
          "width": 320
        }, 
        "z": {
          "extension": "jpg", 
          "height": 480, 
          "mimetype": "image/jpeg", 
          "secret": "LpeARsyv5DvJLnY9R7jbvlRSRLW9lWuE", 
          "width": 320
        }
      }
    }, 
    "sfomuseum:placetype": "image", 
    "wof:depicts": [
      102527513, 
      1159160347, 
      1159396333, 
      1159396261, 
      1360516259, 
      1159396109
    ], 
    "wof:name": "Installation view of \"Let’s Play! 100 Years of Board Games\"", 
    "wof:placetype": "media" 
  }, 
  "geometry": {"coordinates":[-122.382712,37.617422],"type":"Point"}
}
