{
  "type": "Feature",
  "properties": {
    "date:cessation_lower": "1997-10-31",
    "date:cessation_upper": "1997-10-31",
    "date:inception_lower": "1997-03-21",
    "date:inception_upper": "1997-03-21",
    "iso:country": "US",
    "media:created": -1,
    "media:fingerprint": "b81df72a8b0d91f2511a71a83b20b8f2078176b6",
    "media:imagehash_avg": "a:00ff7e2666666706",
    "media:imagehash_diff": "d:c0e0c2ce8c8c8c8c",
    "media:medium": "image",
    "media:mimetype": "image/tiff",
    "media:properties": {
      "colours": [
        {
          "hex": "#b29555",
          "name": "#b29555",
          "reference": "vibrant"
        },
        {
          "hex": "#ddd6ab",
          "name": "#ddd6ab",
          "reference": "vibrant"
        },
        {
          "hex": "#a38754",
          "name": "#a38754",
          "reference": "vibrant"
        },
        {
          "hex": "#d1c69e",
          "name": "#d1c69e",
          "reference": "vibrant"
        },
        {
          "hex": "#5a3e2c",
          "name": "#5a3e2c",
          "reference": "vibrant"
        }
      ],
      "depicts": [
        1226603375
      ],
      "sizes": {
        "b": {
          "extension": "jpg",
          "height": 726,
          "mimetype": "image/jpeg",
          "secret": "oILPmZ1x63YDRwVkL8uhEul4VacXVZ1Y",
          "width": 1024
        },
        "c": {
          "extension": "jpg",
          "height": 567,
          "mimetype": "image/jpeg",
          "secret": "oILPmZ1x63YDRwVkL8uhEul4VacXVZ1Y",
          "width": 800
        },
        "dc": {
          "extension": "jpg",
          "height": 567,
          "mimetype": "image/jpeg",
          "secret": "oILPmZ1x63YDRwVkL8uhEul4VacXVZ1Y",
          "width": 800
        },
        "ds": {
          "extension": "jpg",
          "height": 320,
          "mimetype": "image/jpeg",
          "secret": "oILPmZ1x63YDRwVkL8uhEul4VacXVZ1Y",
          "width": 320
        },
        "k": {
          "extension": "jpg",
          "height": 1452,
          "mimetype": "image/jpeg",
          "secret": "oILPmZ1x63YDRwVkL8uhEul4VacXVZ1Y",
          "width": 2048
        },
        "n": {
          "extension": "jpg",
          "height": 226,
          "mimetype": "image/jpeg",
          "secret": "oILPmZ1x63YDRwVkL8uhEul4VacXVZ1Y",
          "width": 320
        },
        "o": {
          "extension": "jpg",
          "height": 3014,
          "mimetype": "image/jpeg",
          "secret": "Kq4QMTGU1acl8tm0qV0QdQkW3RwiqHRJ",
          "width": 4251
        },
        "s": {
          "extension": "jpg",
          "height": 320,
          "mimetype": "image/jpeg",
          "secret": "oILPmZ1x63YDRwVkL8uhEul4VacXVZ1Y",
          "width": 320
        },
        "z": {
          "extension": "jpg",
          "height": 453,
          "mimetype": "image/jpeg",
          "secret": "oILPmZ1x63YDRwVkL8uhEul4VacXVZ1Y",
          "width": 640
        }
      }
    },
    "sfomuseum:placetype": "image",
    "wof:depicts": [
      1159554803,
      1360516265,
      1226603375,
      102527513,
      1159554829
    ],
    "wof:name": "Installation view of \"Building for Air Travel\"",
    "wof:placetype": "media"
  },
  "geometry": {"coordinates":[-122.384814,37.617787],"type":"Point"}
}
