{
  "type": "Feature", 
  "properties": {
    "iso:country": "US", 
    "media:created": -1, 
    "media:fingerprint": "67d396bab8e7c5b158ee4c0dd8b8f3524a28fb4d", 
    "media:medium": "image", 
    "media:mimetype": "image/tiff", 
    "media:properties": {
      "colours": [
        {
          "hex": "#757588", 
          "name": "#757588", 
          "reference": "vibrant"
        }, 
        {
          "hex": "#b4c1d5", 
          "name": "#b4c1d5", 
          "reference": "vibrant"
        }, 
        {
          "hex": "#443c4b", 
          "name": "#443c4b", 
          "reference": "vibrant"
        }
      ], 
      "depicts": [1226612107], 
      "sizes": {
        "b": {
          "extension": "jpg", 
          "height": 724, 
          "mimetype": "image/jpeg", 
          "secret": "dwPJ21Bjx4ExDv3DBwyjsb6oIOnPbcSj", 
          "width": 1024
        }, 
        "c": {
          "extension": "jpg", 
          "height": 565, 
          "mimetype": "image/jpeg", 
          "secret": "dwPJ21Bjx4ExDv3DBwyjsb6oIOnPbcSj", 
          "width": 800
        }, 
        "dc": {
          "extension": "jpg", 
          "height": 565, 
          "mimetype": "image/jpeg", 
          "secret": "dwPJ21Bjx4ExDv3DBwyjsb6oIOnPbcSj", 
          "width": 800
        }, 
        "ds": {
          "extension": "jpg", 
          "height": 320, 
          "mimetype": "image/jpeg", 
          "secret": "dwPJ21Bjx4ExDv3DBwyjsb6oIOnPbcSj", 
          "width": 320
        }, 
        "k": {
          "extension": "jpg", 
          "height": 1448, 
          "mimetype": "image/jpeg", 
          "secret": "dwPJ21Bjx4ExDv3DBwyjsb6oIOnPbcSj", 
          "width": 2048
        }, 
        "n": {
          "extension": "jpg", 
          "height": 226, 
          "mimetype": "image/jpeg", 
          "secret": "dwPJ21Bjx4ExDv3DBwyjsb6oIOnPbcSj", 
          "width": 320
        }, 
        "o": {
          "extension": "jpg", 
          "height": 3014, 
          "mimetype": "image/jpeg", 
          "secret": "pWTXLnXkqfd9dnQKCUaNvSTiN3JSOM42", 
          "width": 4262
        }, 
        "s": {
          "extension": "jpg", 
          "height": 320, 
          "mimetype": "image/jpeg", 
          "secret": "dwPJ21Bjx4ExDv3DBwyjsb6oIOnPbcSj", 
          "width": 320
        }, 
        "z": {
          "extension": "jpg", 
          "height": 452, 
          "mimetype": "image/jpeg", 
          "secret": "dwPJ21Bjx4ExDv3DBwyjsb6oIOnPbcSj", 
          "width": 640
        }
      }
    }, 
    "sfomuseum:placetype": "image", 
    "wof:depicts": [
      1159554801, 
      1159554841, 
      102527513, 
      1226612107, 
      1159554819, 
      1360516129
    ], 
    "wof:name": "Installation view of \"Airport Cafe\"", 
    "wof:placetype": "media" 
  }, 
  "geometry": {"coordinates":[-122.387197,37.619087],"type":"Point"}
}
