{
  "type": "Feature", 
  "properties": {
    "iso:country": "US", 
    "media:created": 1342820720, 
    "media:fingerprint": "ef2f89f29fe8314a8c48b5172ca6031fc5a2fa36", 
    "media:medium": "image", 
    "media:mimetype": "image/jpeg", 
    "media:properties": {
      "colours": [
        {
          "hex": "#a65449", 
          "name": "#a65449", 
          "reference": "vibrant"
        }, 
        {
          "hex": "#335d76", 
          "name": "#335d76", 
          "reference": "vibrant"
        }, 
        {
          "hex": "#5d8da8", 
          "name": "#5d8da8", 
          "reference": "vibrant"
        }, 
        {
          "hex": "#b9b9b8", 
          "name": "#b9b9b8", 
          "reference": "vibrant"
        }, 
        {
          "hex": "#493d3a", 
          "name": "#493d3a", 
          "reference": "vibrant"
        }
      ], 
      "depicts": [1159160327], 
      "sizes": {
        "b": {
          "extension": "jpg", 
          "height": 682, 
          "mimetype": "image/jpeg", 
          "secret": "kohjoYk0nQEqxINbd70YpDVLDfjkWsRr", 
          "width": 1024
        }, 
        "c": {
          "extension": "jpg", 
          "height": 533, 
          "mimetype": "image/jpeg", 
          "secret": "kohjoYk0nQEqxINbd70YpDVLDfjkWsRr", 
          "width": 800
        }, 
        "dc": {
          "extension": "jpg", 
          "height": 533, 
          "mimetype": "image/jpeg", 
          "secret": "kohjoYk0nQEqxINbd70YpDVLDfjkWsRr", 
          "width": 800
        }, 
        "ds": {
          "extension": "jpg", 
          "height": 320, 
          "mimetype": "image/jpeg", 
          "secret": "kohjoYk0nQEqxINbd70YpDVLDfjkWsRr", 
          "width": 320
        }, 
        "k": {
          "extension": "jpg", 
          "height": 1365, 
          "mimetype": "image/jpeg", 
          "secret": "kohjoYk0nQEqxINbd70YpDVLDfjkWsRr", 
          "width": 2048
        }, 
        "n": {
          "extension": "jpg", 
          "height": 213, 
          "mimetype": "image/jpeg", 
          "secret": "kohjoYk0nQEqxINbd70YpDVLDfjkWsRr", 
          "width": 320
        }, 
        "o": {
          "extension": "jpg", 
          "height": 2400, 
          "mimetype": "image/jpeg", 
          "secret": "jXOgVx8UTOP2tm9wCtKiQiL0r4cC9nKG", 
          "width": 3600
        }, 
        "s": {
          "extension": "jpg", 
          "height": 320, 
          "mimetype": "image/jpeg", 
          "secret": "kohjoYk0nQEqxINbd70YpDVLDfjkWsRr", 
          "width": 320
        }, 
        "z": {
          "extension": "jpg", 
          "height": 426, 
          "mimetype": "image/jpeg", 
          "secret": "kohjoYk0nQEqxINbd70YpDVLDfjkWsRr", 
          "width": 640
        }
      }
    }, 
    "sfomuseum:placetype": "image", 
    "wof:depicts": [
      1360516183, 
      1159160327, 
      102527513, 
      1159396333, 
      1360516193, 
      1159396159
    ], 
    "wof:name": "Installation view of \"From Repack to Rwanda, The Origins, Evolution and Global Reach of the Mountain Bike\"", 
    "wof:placetype": "media" 
  }, 
  "geometry": {"coordinates":[-122.389131,37.616029],"type":"Point"}
}
