{
  "type": "Feature",
  "properties": {
    "date:cessation_lower": "1997-10-31",
    "date:cessation_upper": "1997-10-31",
    "date:inception_lower": "1997-03-21",
    "date:inception_upper": "1997-03-21",
    "iso:country": "US",
    "media:created": -1,
    "media:fingerprint": "753fb0b4cbf3beeb7f1d44960a84683380661547",
    "media:imagehash_avg": "a:007f7e1f3f7c3e00",
    "media:imagehash_diff": "d:dcfc9cfcfef0f0fc",
    "media:medium": "image",
    "media:mimetype": "image/tiff",
    "media:properties": {
      "colours": [
        {
          "hex": "#707c8e",
          "name": "#707c8e",
          "reference": "vibrant"
        },
        {
          "hex": "#b6c3d2",
          "name": "#b6c3d2",
          "reference": "vibrant"
        },
        {
          "hex": "#403a43",
          "name": "#403a43",
          "reference": "vibrant"
        }
      ],
      "depicts": [
        1226603375
      ],
      "sizes": {
        "b": {
          "extension": "jpg",
          "height": 726,
          "mimetype": "image/jpeg",
          "secret": "7teFudNXI04MAN2HSv0lYLJbqfWEKEia",
          "width": 1024
        },
        "c": {
          "extension": "jpg",
          "height": 567,
          "mimetype": "image/jpeg",
          "secret": "7teFudNXI04MAN2HSv0lYLJbqfWEKEia",
          "width": 800
        },
        "dc": {
          "extension": "jpg",
          "height": 567,
          "mimetype": "image/jpeg",
          "secret": "7teFudNXI04MAN2HSv0lYLJbqfWEKEia",
          "width": 800
        },
        "ds": {
          "extension": "jpg",
          "height": 320,
          "mimetype": "image/jpeg",
          "secret": "7teFudNXI04MAN2HSv0lYLJbqfWEKEia",
          "width": 320
        },
        "k": {
          "extension": "jpg",
          "height": 1452,
          "mimetype": "image/jpeg",
          "secret": "7teFudNXI04MAN2HSv0lYLJbqfWEKEia",
          "width": 2048
        },
        "n": {
          "extension": "jpg",
          "height": 226,
          "mimetype": "image/jpeg",
          "secret": "7teFudNXI04MAN2HSv0lYLJbqfWEKEia",
          "width": 320
        },
        "o": {
          "extension": "jpg",
          "height": 3014,
          "mimetype": "image/jpeg",
          "secret": "yBEc8r1t8eShdxQV2a6sbSX7Ec5YBEdR",
          "width": 4251
        },
        "s": {
          "extension": "jpg",
          "height": 320,
          "mimetype": "image/jpeg",
          "secret": "7teFudNXI04MAN2HSv0lYLJbqfWEKEia",
          "width": 320
        },
        "z": {
          "extension": "jpg",
          "height": 453,
          "mimetype": "image/jpeg",
          "secret": "7teFudNXI04MAN2HSv0lYLJbqfWEKEia",
          "width": 640
        }
      }
    },
    "sfomuseum:placetype": "image",
    "wof:depicts": [
      102527513,
      1159554803,
      1159554829,
      1226603375,
      1360516265
    ],
    "wof:name": "Installation view of \"Building for Air Travel\"",
    "wof:placetype": "media"
  },
  "geometry": {"coordinates":[-122.384814,37.617787],"type":"Point"}
}
