{
  "type": "Feature",
  "properties": {
    "date:cessation_lower": "2016-07-25",
    "date:cessation_upper": "2016-07-25",
    "date:inception_lower": "2016-01-22",
    "date:inception_upper": "2016-01-22",
    "iso:country": "US",
    "media:created": 1455290621,
    "media:fingerprint": "e7b0c83decd6f7d1a98493ab687791e31ce6d785",
    "media:imagehash_avg": "a:e1ffc3c380dbc100",
    "media:imagehash_diff": "d:090f07070aaa2b40",
    "media:medium": "image",
    "media:mimetype": "image/jpeg",
    "media:placetype": "installation",
    "media:properties": {
      "colours": [
        {
          "hex": "#d3b9a3",
          "name": "#d3b9a3",
          "reference": "vibrant"
        },
        {
          "hex": "#797c83",
          "name": "#797c83",
          "reference": "vibrant"
        },
        {
          "hex": "#c7b395",
          "name": "#c7b395",
          "reference": "vibrant"
        },
        {
          "hex": "#3c352a",
          "name": "#3c352a",
          "reference": "vibrant"
        }
      ],
      "depicts": [
        1159160583
      ],
      "sizes": {
        "b": {
          "extension": "jpg",
          "height": 768,
          "mimetype": "image/jpeg",
          "secret": "iPyn3WzjxnuF5dLrOZA71bDfeMqy6Z1Z",
          "width": 614
        },
        "c": {
          "extension": "jpg",
          "height": 600,
          "mimetype": "image/jpeg",
          "secret": "iPyn3WzjxnuF5dLrOZA71bDfeMqy6Z1Z",
          "width": 480
        },
        "dc": {
          "extension": "jpg",
          "height": 600,
          "mimetype": "image/jpeg",
          "secret": "iPyn3WzjxnuF5dLrOZA71bDfeMqy6Z1Z",
          "width": 480
        },
        "ds": {
          "extension": "jpg",
          "height": 320,
          "mimetype": "image/jpeg",
          "secret": "iPyn3WzjxnuF5dLrOZA71bDfeMqy6Z1Z",
          "width": 320
        },
        "k": {
          "extension": "jpg",
          "height": 1536,
          "mimetype": "image/jpeg",
          "secret": "iPyn3WzjxnuF5dLrOZA71bDfeMqy6Z1Z",
          "width": 1228
        },
        "n": {
          "extension": "jpg",
          "height": 240,
          "mimetype": "image/jpeg",
          "secret": "iPyn3WzjxnuF5dLrOZA71bDfeMqy6Z1Z",
          "width": 192
        },
        "o": {
          "extension": "jpg",
          "height": 3600,
          "mimetype": "image/jpeg",
          "secret": "8GanrdujIZ0IXk8wd9jocN6B34g7RMg9",
          "width": 2880
        },
        "s": {
          "extension": "jpg",
          "height": 320,
          "mimetype": "image/jpeg",
          "secret": "iPyn3WzjxnuF5dLrOZA71bDfeMqy6Z1Z",
          "width": 320
        },
        "z": {
          "extension": "jpg",
          "height": 480,
          "mimetype": "image/jpeg",
          "secret": "iPyn3WzjxnuF5dLrOZA71bDfeMqy6Z1Z",
          "width": 384
        }
      }
    },
    "sfomuseum:placetype": "image",
    "wof:depicts": [
      1159396153,
      102527513,
      1360516271,
      1159396321,
      1159160583
    ],
    "wof:name": "Installation view of \"Essential Style: Antique and Vintage Handbags\"",
    "wof:placetype": "custom",
    "wof:placetype_alt": [
      "image"
    ]
  },
  "geometry": {"type":"Point","coordinates":[-122.38902,37.614533]}
}
