{
  "type": "Feature",
  "properties": {
    "iso:country": "US",
    "media:created": -1,
    "media:fingerprint": "69b2369723f2943685e0ada1d3474469a0033e4d",
    "media:imagehash_avg": "a:00183c3c3c180000",
    "media:imagehash_diff": "d:f0f0f0f0f8f0fcf4",
    "media:medium": "image",
    "media:mimetype": "image/tiff",
    "media:properties": {
      "colours": [
        {
          "hex": "#c2825f",
          "name": "#c2825f",
          "reference": "vibrant"
        }, 
        {
          "hex": "#e6e191",
          "name": "#e6e191",
          "reference": "vibrant"
        }, 
        {
          "hex": "#324977",
          "name": "#324977",
          "reference": "vibrant"
        }, 
        {
          "hex": "#9b785e",
          "name": "#9b785e",
          "reference": "vibrant"
        }, 
        {
          "hex": "#d3c9a0",
          "name": "#d3c9a0",
          "reference": "vibrant"
        }
      ],
      "depicts": [
        1226612107
      ],
      "sizes": {
        "b": {
          "extension": "jpg",
          "height": 726,
          "mimetype": "image/jpeg",
          "secret": "WbIGZPdG65uBCF5mPDFDj0Gg7Pfk6hSX",
          "width": 1024
        },
        "c": {
          "extension": "jpg",
          "height": 567,
          "mimetype": "image/jpeg",
          "secret": "WbIGZPdG65uBCF5mPDFDj0Gg7Pfk6hSX",
          "width": 800
        },
        "dc": {
          "extension": "jpg",
          "height": 567,
          "mimetype": "image/jpeg",
          "secret": "WbIGZPdG65uBCF5mPDFDj0Gg7Pfk6hSX",
          "width": 800
        },
        "ds": {
          "extension": "jpg",
          "height": 320,
          "mimetype": "image/jpeg",
          "secret": "WbIGZPdG65uBCF5mPDFDj0Gg7Pfk6hSX",
          "width": 320
        },
        "k": {
          "extension": "jpg",
          "height": 1452,
          "mimetype": "image/jpeg",
          "secret": "WbIGZPdG65uBCF5mPDFDj0Gg7Pfk6hSX",
          "width": 2048
        },
        "n": {
          "extension": "jpg",
          "height": 226,
          "mimetype": "image/jpeg",
          "secret": "WbIGZPdG65uBCF5mPDFDj0Gg7Pfk6hSX",
          "width": 320
        },
        "o": {
          "extension": "jpg",
          "height": 3014,
          "mimetype": "image/jpeg",
          "secret": "RqzOdCA51k2DKL4d059oFt93RSrp1CAj",
          "width": 4251
        },
        "s": {
          "extension": "jpg",
          "height": 320,
          "mimetype": "image/jpeg",
          "secret": "WbIGZPdG65uBCF5mPDFDj0Gg7Pfk6hSX",
          "width": 320
        },
        "z": {
          "extension": "jpg",
          "height": 453,
          "mimetype": "image/jpeg",
          "secret": "WbIGZPdG65uBCF5mPDFDj0Gg7Pfk6hSX",
          "width": 640
        }
      }
    },
    "sfomuseum:placetype": "image",
    "wof:depicts": [
      1360516129, 
      102527513, 
      1226612107, 
      1159554801, 
      1159554841, 
      1159554819
    ],
    "wof:name": "Installation view of \"Airport Cafe\"",
    "wof:placetype": "media"
  },
  "geometry": {"coordinates":[-122.387197,37.619087],"type":"Point"}
}
