{
  "type": "Feature", 
  "properties": {
    "iso:country": "US", 
    "media:created": -1, 
    "media:fingerprint": "d7c7406c5edda3c18f7c595780cdd4386a735c02", 
    "media:medium": "image", 
    "media:mimetype": "image/tiff", 
    "media:properties": {
      "colours": [
        {
          "hex": "#bacbe1", 
          "name": "#bacbe1", 
          "reference": "vibrant"
        }, 
        {
          "hex": "#757883", 
          "name": "#757883", 
          "reference": "vibrant"
        }, 
        {
          "hex": "#b0bed1", 
          "name": "#b0bed1", 
          "reference": "vibrant"
        }, 
        {
          "hex": "#423b43", 
          "name": "#423b43", 
          "reference": "vibrant"
        }
      ], 
      "depicts": [1226612011], 
      "sizes": {
        "b": {
          "extension": "jpg", 
          "height": 726, 
          "mimetype": "image/jpeg", 
          "secret": "mYAvwVXL6IKgUPHXYGMINwo8evwXdxCE", 
          "width": 1024
        }, 
        "c": {
          "extension": "jpg", 
          "height": 567, 
          "mimetype": "image/jpeg", 
          "secret": "mYAvwVXL6IKgUPHXYGMINwo8evwXdxCE", 
          "width": 800
        }, 
        "dc": {
          "extension": "jpg", 
          "height": 567, 
          "mimetype": "image/jpeg", 
          "secret": "mYAvwVXL6IKgUPHXYGMINwo8evwXdxCE", 
          "width": 800
        }, 
        "ds": {
          "extension": "jpg", 
          "height": 320, 
          "mimetype": "image/jpeg", 
          "secret": "mYAvwVXL6IKgUPHXYGMINwo8evwXdxCE", 
          "width": 320
        }, 
        "k": {
          "extension": "jpg", 
          "height": 1452, 
          "mimetype": "image/jpeg", 
          "secret": "mYAvwVXL6IKgUPHXYGMINwo8evwXdxCE", 
          "width": 2048
        }, 
        "n": {
          "extension": "jpg", 
          "height": 226, 
          "mimetype": "image/jpeg", 
          "secret": "mYAvwVXL6IKgUPHXYGMINwo8evwXdxCE", 
          "width": 320
        }, 
        "o": {
          "extension": "jpg", 
          "height": 3014, 
          "mimetype": "image/jpeg", 
          "secret": "NyFMtMnVwIJ3F61ULXLxpWbWUcmRpDaw", 
          "width": 4251
        }, 
        "s": {
          "extension": "jpg", 
          "height": 320, 
          "mimetype": "image/jpeg", 
          "secret": "mYAvwVXL6IKgUPHXYGMINwo8evwXdxCE", 
          "width": 320
        }, 
        "z": {
          "extension": "jpg", 
          "height": 453, 
          "mimetype": "image/jpeg", 
          "secret": "mYAvwVXL6IKgUPHXYGMINwo8evwXdxCE", 
          "width": 640
        }
      }
    }, 
    "sfomuseum:placetype": "image", 
    "wof:depicts": [
      1360516133, 
      1159396233, 
      102527513, 
      1226612011, 
      1159396129, 
      1159396327
    ], 
    "wof:name": "Installation view of \"Artist's Furniture: New Dimensions and Statements in Design\"", 
    "wof:placetype": "media" 
  }, 
  "geometry": {"coordinates":[-122.387197,37.619087],"type":"Point"}
}
