{
  "type": "Feature", 
  "properties": {
    "iso:country": "US", 
    "media:created": 1383968458, 
    "media:fingerprint": "a34ed6145162735758c55cb855cf30a6cc68752d", 
    "media:medium": "image", 
    "media:mimetype": "image/jpeg", 
    "media:properties": {
      "colours": [
        {
          "hex": "#e2c638", 
          "name": "#e2c638", 
          "reference": "vibrant"
        }, 
        {
          "hex": "#e8debb", 
          "name": "#e8debb", 
          "reference": "vibrant"
        }, 
        {
          "hex": "#80332e", 
          "name": "#80332e", 
          "reference": "vibrant"
        }, 
        {
          "hex": "#b0a25d", 
          "name": "#b0a25d", 
          "reference": "vibrant"
        }, 
        {
          "hex": "#cac3a4", 
          "name": "#cac3a4", 
          "reference": "vibrant"
        }
      ], 
      "depicts": [1159160369], 
      "sizes": {
        "b": {
          "extension": "jpg", 
          "height": 682, 
          "mimetype": "image/jpeg", 
          "secret": "zrvjUIPjNdQjZlqDZMOjJgt4aCohvXQk", 
          "width": 1023
        }, 
        "c": {
          "extension": "jpg", 
          "height": 533, 
          "mimetype": "image/jpeg", 
          "secret": "zrvjUIPjNdQjZlqDZMOjJgt4aCohvXQk", 
          "width": 800
        }, 
        "dc": {
          "extension": "jpg", 
          "height": 533, 
          "mimetype": "image/jpeg", 
          "secret": "zrvjUIPjNdQjZlqDZMOjJgt4aCohvXQk", 
          "width": 800
        }, 
        "ds": {
          "extension": "jpg", 
          "height": 320, 
          "mimetype": "image/jpeg", 
          "secret": "zrvjUIPjNdQjZlqDZMOjJgt4aCohvXQk", 
          "width": 320
        }, 
        "k": {
          "extension": "jpg", 
          "height": 1365, 
          "mimetype": "image/jpeg", 
          "secret": "zrvjUIPjNdQjZlqDZMOjJgt4aCohvXQk", 
          "width": 2047
        }, 
        "n": {
          "extension": "jpg", 
          "height": 213, 
          "mimetype": "image/jpeg", 
          "secret": "zrvjUIPjNdQjZlqDZMOjJgt4aCohvXQk", 
          "width": 320
        }, 
        "o": {
          "extension": "jpg", 
          "height": 2400, 
          "mimetype": "image/jpeg", 
          "secret": "Wp7IGVSI4vAiFOg3nxOGluBa3ASwJjmP", 
          "width": 3599
        }, 
        "s": {
          "extension": "jpg", 
          "height": 320, 
          "mimetype": "image/jpeg", 
          "secret": "zrvjUIPjNdQjZlqDZMOjJgt4aCohvXQk", 
          "width": 320
        }, 
        "z": {
          "extension": "jpg", 
          "height": 426, 
          "mimetype": "image/jpeg", 
          "secret": "zrvjUIPjNdQjZlqDZMOjJgt4aCohvXQk", 
          "width": 640
        }
      }
    }, 
    "sfomuseum:placetype": "image", 
    "wof:depicts": [
      1159396141, 
      1159396333, 
      102527513, 
      1360516121, 
      1159160369, 
      1159396295
    ], 
    "wof:name": "Installation view of \"Japanese Toys! From Kokeshi to Kaiju\"", 
    "wof:placetype": "media" 
  }, 
  "geometry": {"coordinates":[-122.387197,37.619087],"type":"Point"}
}
