{
  "type": "Feature",
  "properties": {
    "date:cessation_lower": "2013-07-15",
    "date:cessation_upper": "2013-07-15",
    "date:inception_lower": "2013-01-11",
    "date:inception_upper": "2013-01-11",
    "iso:country": "US",
    "media:created": 1360970035,
    "media:fingerprint": "cc3b6c61421d1a2baa89a6c185c75f2134e0fe0a",
    "media:imagehash_avg": "a:7f3fffe381810000",
    "media:imagehash_diff": "d:e8f8bbcb13333373",
    "media:medium": "image",
    "media:mimetype": "image/jpeg",
    "media:properties": {
      "colours": [
        {
          "hex": "#e05054",
          "name": "#e05054",
          "reference": "vibrant"
        },
        {
          "hex": "#c07873",
          "name": "#c07873",
          "reference": "vibrant"
        },
        {
          "hex": "#a4836b",
          "name": "#a4836b",
          "reference": "vibrant"
        },
        {
          "hex": "#bfc4b3",
          "name": "#bfc4b3",
          "reference": "vibrant"
        },
        {
          "hex": "#42443f",
          "name": "#42443f",
          "reference": "vibrant"
        }
      ],
      "depicts": [
        1159160359
      ],
      "sizes": {
        "b": {
          "extension": "jpg",
          "height": 682,
          "mimetype": "image/jpeg",
          "secret": "0TBH2bOufuVdrHfRUT8E7SkCTOCtrU3l",
          "width": 1024
        },
        "c": {
          "extension": "jpg",
          "height": 533,
          "mimetype": "image/jpeg",
          "secret": "0TBH2bOufuVdrHfRUT8E7SkCTOCtrU3l",
          "width": 800
        },
        "dc": {
          "extension": "jpg",
          "height": 533,
          "mimetype": "image/jpeg",
          "secret": "0TBH2bOufuVdrHfRUT8E7SkCTOCtrU3l",
          "width": 800
        },
        "ds": {
          "extension": "jpg",
          "height": 320,
          "mimetype": "image/jpeg",
          "secret": "0TBH2bOufuVdrHfRUT8E7SkCTOCtrU3l",
          "width": 320
        },
        "k": {
          "extension": "jpg",
          "height": 1365,
          "mimetype": "image/jpeg",
          "secret": "0TBH2bOufuVdrHfRUT8E7SkCTOCtrU3l",
          "width": 2048
        },
        "n": {
          "extension": "jpg",
          "height": 213,
          "mimetype": "image/jpeg",
          "secret": "0TBH2bOufuVdrHfRUT8E7SkCTOCtrU3l",
          "width": 320
        },
        "o": {
          "extension": "jpg",
          "height": 2400,
          "mimetype": "image/jpeg",
          "secret": "W6LAs9F5Y0z9q5Hw9Ftu9zCUoxYEne85",
          "width": 3600
        },
        "s": {
          "extension": "jpg",
          "height": 320,
          "mimetype": "image/jpeg",
          "secret": "0TBH2bOufuVdrHfRUT8E7SkCTOCtrU3l",
          "width": 320
        },
        "z": {
          "extension": "jpg",
          "height": 426,
          "mimetype": "image/jpeg",
          "secret": "0TBH2bOufuVdrHfRUT8E7SkCTOCtrU3l",
          "width": 640
        }
      }
    },
    "sfomuseum:placetype": "image",
    "wof:depicts": [
      1360516283,
      1159160359,
      1159396159,
      1159396333,
      102527513
    ],
    "wof:name": "Installation view of \"Souvenirs: Tokens of Travel\"",
    "wof:placetype": "media"
  },
  "geometry": {"coordinates":[-122.389725,37.616594],"type":"Point"}
}
