{
  "type": "Feature", 
  "properties": {
    "iso:country": "US", 
    "media:created": -1, 
    "media:fingerprint": "59bda9d9b6fe7285af0d269b4264098cdf8c6ce3", 
    "media:medium": "image", 
    "media:mimetype": "image/tiff", 
    "media:properties": {
      "colours": [
        {
          "hex": "#915132", 
          "name": "#915132", 
          "reference": "vibrant"
        }, 
        {
          "hex": "#6c442e", 
          "name": "#6c442e", 
          "reference": "vibrant"
        }, 
        {
          "hex": "#898c5f", 
          "name": "#898c5f", 
          "reference": "vibrant"
        }, 
        {
          "hex": "#c1b0a6", 
          "name": "#c1b0a6", 
          "reference": "vibrant"
        }, 
        {
          "hex": "#4c434a", 
          "name": "#4c434a", 
          "reference": "vibrant"
        }
      ], 
      "depicts": [1226612107], 
      "sizes": {
        "b": {
          "extension": "jpg", 
          "height": 724, 
          "mimetype": "image/jpeg", 
          "secret": "oK12wSrC7rCPrF5d4hfv2sNXWLPHJHAP", 
          "width": 1024
        }, 
        "c": {
          "extension": "jpg", 
          "height": 565, 
          "mimetype": "image/jpeg", 
          "secret": "oK12wSrC7rCPrF5d4hfv2sNXWLPHJHAP", 
          "width": 800
        }, 
        "dc": {
          "extension": "jpg", 
          "height": 565, 
          "mimetype": "image/jpeg", 
          "secret": "oK12wSrC7rCPrF5d4hfv2sNXWLPHJHAP", 
          "width": 800
        }, 
        "ds": {
          "extension": "jpg", 
          "height": 320, 
          "mimetype": "image/jpeg", 
          "secret": "oK12wSrC7rCPrF5d4hfv2sNXWLPHJHAP", 
          "width": 320
        }, 
        "k": {
          "extension": "jpg", 
          "height": 1448, 
          "mimetype": "image/jpeg", 
          "secret": "oK12wSrC7rCPrF5d4hfv2sNXWLPHJHAP", 
          "width": 2048
        }, 
        "n": {
          "extension": "jpg", 
          "height": 226, 
          "mimetype": "image/jpeg", 
          "secret": "oK12wSrC7rCPrF5d4hfv2sNXWLPHJHAP", 
          "width": 320
        }, 
        "o": {
          "extension": "jpg", 
          "height": 3014, 
          "mimetype": "image/jpeg", 
          "secret": "Q6mdmIAt53zWR6zYnNOInm5VqaKJSnTd", 
          "width": 4262
        }, 
        "s": {
          "extension": "jpg", 
          "height": 320, 
          "mimetype": "image/jpeg", 
          "secret": "oK12wSrC7rCPrF5d4hfv2sNXWLPHJHAP", 
          "width": 320
        }, 
        "z": {
          "extension": "jpg", 
          "height": 452, 
          "mimetype": "image/jpeg", 
          "secret": "oK12wSrC7rCPrF5d4hfv2sNXWLPHJHAP", 
          "width": 640
        }
      }
    }, 
    "sfomuseum:placetype": "image", 
    "wof:depicts": [
      1159554801, 
      1159554819, 
      1159554841, 
      1360516129, 
      1226612107, 
      102527513
    ], 
    "wof:name": "Installation view of \"Airport Cafe\"", 
    "wof:placetype": "media" 
  }, 
  "geometry": {"coordinates":[-122.387197,37.619087],"type":"Point"}
}
