{
  "type": "Feature", 
  "properties": {
    "iso:country": "US", 
    "media:created": -1, 
    "media:fingerprint": "8a067efec095183000fe294cd249fbb60d1a07dc", 
    "media:medium": "image", 
    "media:mimetype": "image/tiff", 
    "media:properties": {
      "colours": [
        {
          "hex": "#88b0ca", 
          "name": "#88b0ca", 
          "reference": "vibrant"
        }, 
        {
          "hex": "#afc5d9", 
          "name": "#afc5d9", 
          "reference": "vibrant"
        }, 
        {
          "hex": "#737886", 
          "name": "#737886", 
          "reference": "vibrant"
        }, 
        {
          "hex": "#bbcbd4", 
          "name": "#bbcbd4", 
          "reference": "vibrant"
        }, 
        {
          "hex": "#383137", 
          "name": "#383137", 
          "reference": "vibrant"
        }
      ], 
      "depicts": [1226607175], 
      "sizes": {
        "b": {
          "extension": "jpg", 
          "height": 726, 
          "mimetype": "image/jpeg", 
          "secret": "JgJoSlPtoJcAp6J6GI9CapHMLisMRIpR", 
          "width": 1024
        }, 
        "c": {
          "extension": "jpg", 
          "height": 567, 
          "mimetype": "image/jpeg", 
          "secret": "JgJoSlPtoJcAp6J6GI9CapHMLisMRIpR", 
          "width": 800
        }, 
        "dc": {
          "extension": "jpg", 
          "height": 567, 
          "mimetype": "image/jpeg", 
          "secret": "JgJoSlPtoJcAp6J6GI9CapHMLisMRIpR", 
          "width": 800
        }, 
        "ds": {
          "extension": "jpg", 
          "height": 320, 
          "mimetype": "image/jpeg", 
          "secret": "JgJoSlPtoJcAp6J6GI9CapHMLisMRIpR", 
          "width": 320
        }, 
        "k": {
          "extension": "jpg", 
          "height": 1452, 
          "mimetype": "image/jpeg", 
          "secret": "JgJoSlPtoJcAp6J6GI9CapHMLisMRIpR", 
          "width": 2048
        }, 
        "n": {
          "extension": "jpg", 
          "height": 226, 
          "mimetype": "image/jpeg", 
          "secret": "JgJoSlPtoJcAp6J6GI9CapHMLisMRIpR", 
          "width": 320
        }, 
        "o": {
          "extension": "jpg", 
          "height": 3014, 
          "mimetype": "image/jpeg", 
          "secret": "mktzoVJWX8khFlytyQ4z9YJ0RXTiA7Eb", 
          "width": 4251
        }, 
        "s": {
          "extension": "jpg", 
          "height": 320, 
          "mimetype": "image/jpeg", 
          "secret": "JgJoSlPtoJcAp6J6GI9CapHMLisMRIpR", 
          "width": 320
        }, 
        "z": {
          "extension": "jpg", 
          "height": 453, 
          "mimetype": "image/jpeg", 
          "secret": "JgJoSlPtoJcAp6J6GI9CapHMLisMRIpR", 
          "width": 640
        }
      }
    }, 
    "sfomuseum:placetype": "image", 
    "wof:depicts": [1159554803, 1159554829, 102527513, 1226607175, 1360516265], 
    "wof:name": "Installation view of \"Bark: Photographs by Ann Giordano\"", 
    "wof:placetype": "media" 
  }, 
  "geometry": {"coordinates":[-122.384814,37.617787],"type":"Point"}
}
