{
  "type": "Feature", 
  "properties": {
    "iso:country": "US", 
    "media:created": 1068004933, 
    "media:fingerprint": "ef10a3a8c9b1e6c87c21a20e3e1e16d384e375c9", 
    "media:medium": "image", 
    "media:mimetype": "image/jpeg", 
    "media:properties": {
      "colours": [
        {
          "hex": "#c1433c", 
          "name": "#c1433c", 
          "reference": "vibrant"
        }, 
        {
          "hex": "#987265", 
          "name": "#987265", 
          "reference": "vibrant"
        }, 
        {
          "hex": "#a5b8ce", 
          "name": "#a5b8ce", 
          "reference": "vibrant"
        }, 
        {
          "hex": "#41474b", 
          "name": "#41474b", 
          "reference": "vibrant"
        }
      ], 
      "depicts": [1159159593], 
      "sizes": {
        "b": {
          "extension": "jpg", 
          "height": 1024, 
          "mimetype": "image/jpeg", 
          "secret": "F1fCF1t93T7XzTXVxtP34gOESiW2EAgD", 
          "width": 768
        }, 
        "c": {
          "extension": "jpg", 
          "height": 800, 
          "mimetype": "image/jpeg", 
          "secret": "vNXblEgbUQlPBoRoaCPdHogEWrFmCoGw", 
          "width": 600
        }, 
        "dc": {
          "extension": "jpg", 
          "height": 800, 
          "mimetype": "image/jpeg", 
          "secret": "ZquiueJApSFzdPRK0dwJBgEkhNpijp4s", 
          "width": 600
        }, 
        "ds": {
          "extension": "jpg", 
          "height": 320, 
          "mimetype": "image/jpeg", 
          "secret": "6jg6xvINpETsXdBL1WarwPuxbQKFux1a", 
          "width": 320
        }, 
        "k": {
          "extension": "jpg", 
          "height": 2048, 
          "mimetype": "image/jpeg", 
          "secret": "Z60dnu8J1b4u7DdXPFIhEtg5iIe4KPY7", 
          "width": 1536
        }, 
        "n": {
          "extension": "jpg", 
          "height": 320, 
          "mimetype": "image/jpeg", 
          "secret": "8veVDZu2pNgyPfATLQcZRxQq8yQWIx48", 
          "width": 240
        }, 
        "o": {
          "extension": "jpg", 
          "height": 1600, 
          "mimetype": "image/jpeg", 
          "secret": "bXOht63kH9ONmcxzlCA5SjOsti41eKPY", 
          "width": 1200
        }, 
        "s": {
          "extension": "jpg", 
          "height": 320, 
          "mimetype": "image/jpeg", 
          "secret": "urGYQS52QpJNcerXPQIxtHOzRCO3zoYT", 
          "width": 320
        }, 
        "z": {
          "extension": "jpg", 
          "height": 640, 
          "mimetype": "image/jpeg", 
          "secret": "bZCf8J6ElWysALdILSBMgE0KWfHrB4JF", 
          "width": 480
        }
      }
    }, 
    "sfomuseum:placetype": "image", 
    "wof:depicts": [102527513, 1360516477, 1159159593, 1159396115, 1159396319], 
    "wof:name": "Installation view of \"The Flight Bag: Icon of Air Travel\"", 
    "wof:placetype": "media" 
  }, 
  "geometry": {"coordinates":[-122.385472,37.613926],"type":"Point"}
}
