{
  "type": "Feature", 
  "properties": {
    "iso:country": "US", 
    "media:created": 1068004933, 
    "media:fingerprint": "ef10a3a8c9b1e6c87c21a20e3e1e16d384e375c9", 
    "media:medium": "image", 
    "media:mimetype": "image/jpeg", 
    "media:properties": {
      "colours": [
        {
          "hex": "#c1433c", 
          "name": "#c1433c", 
          "reference": "vibrant"
        }, 
        {
          "hex": "#987265", 
          "name": "#987265", 
          "reference": "vibrant"
        }, 
        {
          "hex": "#a5b8ce", 
          "name": "#a5b8ce", 
          "reference": "vibrant"
        }, 
        {
          "hex": "#41474b", 
          "name": "#41474b", 
          "reference": "vibrant"
        }
      ], 
      "depicts": [1159159593], 
      "sizes": {
        "b": {
          "extension": "jpg", 
          "height": 768, 
          "mimetype": "image/jpeg", 
          "secret": "5G349XAmADY2leiD5JE92Xg0e1cB87SH", 
          "width": 1024
        }, 
        "c": {
          "extension": "jpg", 
          "height": 600, 
          "mimetype": "image/jpeg", 
          "secret": "XR8BMPV8ivWYJophvZWx5ZvkAqibGzgy", 
          "width": 800
        }, 
        "dc": {
          "extension": "jpg", 
          "height": 600, 
          "mimetype": "image/jpeg", 
          "secret": "kAPsjNA1MKl8A2oaRSdWsKBb4tMlAwel", 
          "width": 800
        }, 
        "ds": {
          "extension": "jpg", 
          "height": 320, 
          "mimetype": "image/jpeg", 
          "secret": "zWfYuDX1Ggx2zBEmJNTfKsW6MXtqwNak", 
          "width": 320
        }, 
        "k": {
          "extension": "jpg", 
          "height": 1536, 
          "mimetype": "image/jpeg", 
          "secret": "03BVT9impLtTS1hJZhI5Wq4rQgZym1uT", 
          "width": 2048
        }, 
        "n": {
          "extension": "jpg", 
          "height": 240, 
          "mimetype": "image/jpeg", 
          "secret": "3Yb7e0oL1cYPxDpm5QL7haHouS2aiXDO", 
          "width": 320
        }, 
        "o": {
          "extension": "jpg", 
          "height": 1200, 
          "mimetype": "image/jpeg", 
          "secret": "rUzUMptG0EW1SftRKMQn9me8njwCNSN2", 
          "width": 1600
        }, 
        "s": {
          "extension": "jpg", 
          "height": 320, 
          "mimetype": "image/jpeg", 
          "secret": "2zRlvFUjQcQyFfIAdLgThGRUd02lCwjg", 
          "width": 320
        }, 
        "z": {
          "extension": "jpg", 
          "height": 480, 
          "mimetype": "image/jpeg", 
          "secret": "RHT4TYaB8NWDWyE2GbnTgIkVvAREvSqB", 
          "width": 640
        }
      }
    }, 
    "sfomuseum:placetype": "image", 
    "wof:depicts": [102527513, 1360516477, 1159159593, 1159396115, 1159396319], 
    "wof:name": "Installation view of \"The Flight Bag: Icon of Air Travel\"", 
    "wof:placetype": "media" 
  }, 
  "geometry": {"coordinates":[-122.385472,37.613926],"type":"Point"}
}
