{
  "type": "Feature",
  "properties": {
    "date:cessation_lower": "2014-05-12",
    "date:cessation_upper": "2014-05-12",
    "date:inception_lower": "2013-11-01",
    "date:inception_upper": "2013-11-01",
    "iso:country": "US",
    "media:created": 1383966477,
    "media:fingerprint": "e377c08214744af73a0063de5dcfe100b521ce5e",
    "media:imagehash_avg": "a:3ebfbdbdbca080b0",
    "media:imagehash_diff": "d:7272736161616363",
    "media:medium": "image",
    "media:mimetype": "image/jpeg",
    "media:properties": {
      "colours": [
        {
          "hex": "#1a5890",
          "name": "#1a5890",
          "reference": "vibrant"
        },
        {
          "hex": "#632926",
          "name": "#632926",
          "reference": "vibrant"
        },
        {
          "hex": "#54579f",
          "name": "#54579f",
          "reference": "vibrant"
        },
        {
          "hex": "#cec7b6",
          "name": "#cec7b6",
          "reference": "vibrant"
        },
        {
          "hex": "#39312b",
          "name": "#39312b",
          "reference": "vibrant"
        }
      ],
      "depicts": [
        1159160369
      ],
      "sizes": {
        "b": {
          "extension": "jpg",
          "height": 682,
          "mimetype": "image/jpeg",
          "secret": "YDIwfb0FDyUXA6TPe59F7jC1U0Fs5uQd",
          "width": 1024
        },
        "c": {
          "extension": "jpg",
          "height": 533,
          "mimetype": "image/jpeg",
          "secret": "YDIwfb0FDyUXA6TPe59F7jC1U0Fs5uQd",
          "width": 800
        },
        "dc": {
          "extension": "jpg",
          "height": 533,
          "mimetype": "image/jpeg",
          "secret": "YDIwfb0FDyUXA6TPe59F7jC1U0Fs5uQd",
          "width": 800
        },
        "ds": {
          "extension": "jpg",
          "height": 320,
          "mimetype": "image/jpeg",
          "secret": "YDIwfb0FDyUXA6TPe59F7jC1U0Fs5uQd",
          "width": 320
        },
        "k": {
          "extension": "jpg",
          "height": 1365,
          "mimetype": "image/jpeg",
          "secret": "YDIwfb0FDyUXA6TPe59F7jC1U0Fs5uQd",
          "width": 2048
        },
        "n": {
          "extension": "jpg",
          "height": 213,
          "mimetype": "image/jpeg",
          "secret": "YDIwfb0FDyUXA6TPe59F7jC1U0Fs5uQd",
          "width": 320
        },
        "o": {
          "extension": "jpg",
          "height": 2400,
          "mimetype": "image/jpeg",
          "secret": "iYUDyY3b57XBIAmXfDrNXvNOu9eHgr61",
          "width": 3600
        },
        "s": {
          "extension": "jpg",
          "height": 320,
          "mimetype": "image/jpeg",
          "secret": "YDIwfb0FDyUXA6TPe59F7jC1U0Fs5uQd",
          "width": 320
        },
        "z": {
          "extension": "jpg",
          "height": 426,
          "mimetype": "image/jpeg",
          "secret": "YDIwfb0FDyUXA6TPe59F7jC1U0Fs5uQd",
          "width": 640
        }
      }
    },
    "sfomuseum:placetype": "image",
    "wof:depicts": [
      1360516121,
      1159160369,
      1159396141,
      1159396333,
      102527513,
      1159396295
    ],
    "wof:name": "Installation view of \"Japanese Toys! From Kokeshi to Kaiju\"",
    "wof:placetype": "media"
  },
  "geometry": {"coordinates":[-122.387197,37.619087],"type":"Point"}
}
