{
  "type": "Feature", 
  "properties": {
    "iso:country": "US", 
    "media:created": 1533750118, 
    "media:fingerprint": "af49698617999ba30bba38e514b1f0803473de09", 
    "media:medium": "image", 
    "media:mimetype": "image/jpeg", 
    "media:properties": {
      "colours": [
        {
          "hex": "#c18e5e", 
          "name": "#c18e5e", 
          "reference": "vibrant"
        }, 
        {
          "hex": "#d1ae82", 
          "name": "#d1ae82", 
          "reference": "vibrant"
        }, 
        {
          "hex": "#887e72", 
          "name": "#887e72", 
          "reference": "vibrant"
        }, 
        {
          "hex": "#a9bfc5", 
          "name": "#a9bfc5", 
          "reference": "vibrant"
        }, 
        {
          "hex": "#53473d", 
          "name": "#53473d", 
          "reference": "vibrant"
        }
      ], 
      "depicts": [1226620513], 
      "sizes": {
        "b": {
          "extension": "jpg", 
          "height": 768, 
          "mimetype": "image/jpeg", 
          "secret": "aPv6gD4wcySMYG1AmbvJMQNGe0dVxc7v", 
          "width": 614
        }, 
        "c": {
          "extension": "jpg", 
          "height": 600, 
          "mimetype": "image/jpeg", 
          "secret": "aPv6gD4wcySMYG1AmbvJMQNGe0dVxc7v", 
          "width": 480
        }, 
        "dc": {
          "extension": "jpg", 
          "height": 600, 
          "mimetype": "image/jpeg", 
          "secret": "aPv6gD4wcySMYG1AmbvJMQNGe0dVxc7v", 
          "width": 480
        }, 
        "ds": {
          "extension": "jpg", 
          "height": 320, 
          "mimetype": "image/jpeg", 
          "secret": "aPv6gD4wcySMYG1AmbvJMQNGe0dVxc7v", 
          "width": 320
        }, 
        "k": {
          "extension": "jpg", 
          "height": 1536, 
          "mimetype": "image/jpeg", 
          "secret": "aPv6gD4wcySMYG1AmbvJMQNGe0dVxc7v", 
          "width": 1228
        }, 
        "n": {
          "extension": "jpg", 
          "height": 240, 
          "mimetype": "image/jpeg", 
          "secret": "aPv6gD4wcySMYG1AmbvJMQNGe0dVxc7v", 
          "width": 192
        }, 
        "o": {
          "extension": "jpg", 
          "height": 3600, 
          "mimetype": "image/jpeg", 
          "secret": "rvnHRdANcqeCdPrmRaRjqPtYvRfJw5dg", 
          "width": 2880
        }, 
        "s": {
          "extension": "jpg", 
          "height": 320, 
          "mimetype": "image/jpeg", 
          "secret": "aPv6gD4wcySMYG1AmbvJMQNGe0dVxc7v", 
          "width": 320
        }, 
        "z": {
          "extension": "jpg", 
          "height": 480, 
          "mimetype": "image/jpeg", 
          "secret": "aPv6gD4wcySMYG1AmbvJMQNGe0dVxc7v", 
          "width": 384
        }
      }
    }, 
    "sfomuseum:placetype": "image", 
    "wof:depicts": [
      1159157039, 
      1226620513, 
      1159157333, 
      1159157271, 
      1159157335, 
      102527513
    ], 
    "wof:name": "Installation view of \"Caticons\"", 
    "wof:placetype": "media" 
  }, 
  "geometry": {"coordinates":[-122.389725,37.616594],"type":"Point"}
}
