{
  "type": "Feature", 
  "properties": {
    "iso:country": "US", 
    "media:created": -1, 
    "media:fingerprint": "d66db4c2d6c7cbcf307eac0b1305bef292df5ad8", 
    "media:medium": "image", 
    "media:mimetype": "image/tiff", 
    "media:properties": {
      "colours": [
        {
          "hex": "#cfb795", 
          "name": "#cfb795", 
          "reference": "vibrant"
        }, 
        {
          "hex": "#9d7967", 
          "name": "#9d7967", 
          "reference": "vibrant"
        }, 
        {
          "hex": "#a6aec2", 
          "name": "#a6aec2", 
          "reference": "vibrant"
        }, 
        {
          "hex": "#494449", 
          "name": "#494449", 
          "reference": "vibrant"
        }
      ], 
      "depicts": [1226612107], 
      "sizes": {
        "b": {
          "extension": "jpg", 
          "height": 726, 
          "mimetype": "image/jpeg", 
          "secret": "oNVibihrB2oq21dJzc4OZjiSY0DZnR4D", 
          "width": 1024
        }, 
        "c": {
          "extension": "jpg", 
          "height": 567, 
          "mimetype": "image/jpeg", 
          "secret": "oNVibihrB2oq21dJzc4OZjiSY0DZnR4D", 
          "width": 800
        }, 
        "dc": {
          "extension": "jpg", 
          "height": 567, 
          "mimetype": "image/jpeg", 
          "secret": "oNVibihrB2oq21dJzc4OZjiSY0DZnR4D", 
          "width": 800
        }, 
        "ds": {
          "extension": "jpg", 
          "height": 320, 
          "mimetype": "image/jpeg", 
          "secret": "oNVibihrB2oq21dJzc4OZjiSY0DZnR4D", 
          "width": 320
        }, 
        "k": {
          "extension": "jpg", 
          "height": 1452, 
          "mimetype": "image/jpeg", 
          "secret": "oNVibihrB2oq21dJzc4OZjiSY0DZnR4D", 
          "width": 2048
        }, 
        "n": {
          "extension": "jpg", 
          "height": 226, 
          "mimetype": "image/jpeg", 
          "secret": "oNVibihrB2oq21dJzc4OZjiSY0DZnR4D", 
          "width": 320
        }, 
        "o": {
          "extension": "jpg", 
          "height": 3014, 
          "mimetype": "image/jpeg", 
          "secret": "Qxu1FfoTRjgakbiVowu9FHdRUYHuTd2V", 
          "width": 4251
        }, 
        "s": {
          "extension": "jpg", 
          "height": 320, 
          "mimetype": "image/jpeg", 
          "secret": "oNVibihrB2oq21dJzc4OZjiSY0DZnR4D", 
          "width": 320
        }, 
        "z": {
          "extension": "jpg", 
          "height": 453, 
          "mimetype": "image/jpeg", 
          "secret": "oNVibihrB2oq21dJzc4OZjiSY0DZnR4D", 
          "width": 640
        }
      }
    }, 
    "sfomuseum:placetype": "image", 
    "wof:depicts": [
      1159554819, 
      1159554841, 
      1226612107, 
      1360516129, 
      1159554801, 
      102527513
    ], 
    "wof:name": "Installation view of \"Airport Cafe\"", 
    "wof:placetype": "media" 
  }, 
  "geometry": {"coordinates":[-122.387197,37.619087],"type":"Point"}
}
