{
  "type": "Feature",
  "properties": {
    "iso:country": "US",
    "media:created": -1,
    "media:fingerprint": "6e1225ba11ceb54ac6a1f00a4fda54bbb3ff77ba",
    "media:imagehash_avg": "a:58d860747efe3c00",
    "media:imagehash_diff": "d:b090c0ccccecf0b8",
    "media:medium": "image",
    "media:mimetype": "image/tiff",
    "media:properties": {
      "colours": [
        {
          "hex": "#d7c790",
          "name": "#d7c790",
          "reference": "vibrant"
        }, 
        {
          "hex": "#72748b",
          "name": "#72748b",
          "reference": "vibrant"
        }, 
        {
          "hex": "#d4cdb1",
          "name": "#d4cdb1",
          "reference": "vibrant"
        }, 
        {
          "hex": "#43425b",
          "name": "#43425b",
          "reference": "vibrant"
        }
      ],
      "depicts": [
        1226612107
      ],
      "sizes": {
        "b": {
          "extension": "jpg",
          "height": 726,
          "mimetype": "image/jpeg",
          "secret": "YI5o9FbZiyGmRJYRlKZNYfvBbWh6C1ui",
          "width": 1024
        },
        "c": {
          "extension": "jpg",
          "height": 567,
          "mimetype": "image/jpeg",
          "secret": "YI5o9FbZiyGmRJYRlKZNYfvBbWh6C1ui",
          "width": 800
        },
        "dc": {
          "extension": "jpg",
          "height": 567,
          "mimetype": "image/jpeg",
          "secret": "YI5o9FbZiyGmRJYRlKZNYfvBbWh6C1ui",
          "width": 800
        },
        "ds": {
          "extension": "jpg",
          "height": 320,
          "mimetype": "image/jpeg",
          "secret": "YI5o9FbZiyGmRJYRlKZNYfvBbWh6C1ui",
          "width": 320
        },
        "k": {
          "extension": "jpg",
          "height": 1452,
          "mimetype": "image/jpeg",
          "secret": "YI5o9FbZiyGmRJYRlKZNYfvBbWh6C1ui",
          "width": 2048
        },
        "n": {
          "extension": "jpg",
          "height": 226,
          "mimetype": "image/jpeg",
          "secret": "YI5o9FbZiyGmRJYRlKZNYfvBbWh6C1ui",
          "width": 320
        },
        "o": {
          "extension": "jpg",
          "height": 3014,
          "mimetype": "image/jpeg",
          "secret": "0Z64C5Ye7LVqbkpk3JLN0IuHO4kDi8it",
          "width": 4251
        },
        "s": {
          "extension": "jpg",
          "height": 320,
          "mimetype": "image/jpeg",
          "secret": "YI5o9FbZiyGmRJYRlKZNYfvBbWh6C1ui",
          "width": 320
        },
        "z": {
          "extension": "jpg",
          "height": 453,
          "mimetype": "image/jpeg",
          "secret": "YI5o9FbZiyGmRJYRlKZNYfvBbWh6C1ui",
          "width": 640
        }
      }
    },
    "sfomuseum:placetype": "image",
    "wof:depicts": [
      102527513, 
      1159554841, 
      1159554819, 
      1360516129, 
      1226612107, 
      1159554801
    ],
    "wof:name": "Installation view of \"Airport Cafe\"",
    "wof:placetype": "media"
  },
  "geometry": {"coordinates":[-122.387197,37.619087],"type":"Point"}
}
