{
  "type": "Feature", 
  "properties": {
    "iso:country": "US", 
    "media:created": 1352161541, 
    "media:fingerprint": "f3ae8cb32ef5d3c975be8c46c9999c4fcd366d94", 
    "media:medium": "image", 
    "media:mimetype": "image/jpeg", 
    "media:properties": {
      "colours": [
        {
          "hex": "#d83a0d", 
          "name": "#d83a0d", 
          "reference": "vibrant"
        }, 
        {
          "hex": "#cebe92", 
          "name": "#cebe92", 
          "reference": "vibrant"
        }, 
        {
          "hex": "#cf3106", 
          "name": "#cf3106", 
          "reference": "vibrant"
        }, 
        {
          "hex": "#9b915f", 
          "name": "#9b915f", 
          "reference": "vibrant"
        }, 
        {
          "hex": "#a1bc9b", 
          "name": "#a1bc9b", 
          "reference": "vibrant"
        }
      ], 
      "depicts": [1159160347], 
      "sizes": {
        "b": {
          "extension": "jpg", 
          "height": 768, 
          "mimetype": "image/jpeg", 
          "secret": "fdetXzFlGlrtUzHdaJ4rlkWBzFvsaCSk", 
          "width": 512
        }, 
        "c": {
          "extension": "jpg", 
          "height": 600, 
          "mimetype": "image/jpeg", 
          "secret": "fdetXzFlGlrtUzHdaJ4rlkWBzFvsaCSk", 
          "width": 400
        }, 
        "dc": {
          "extension": "jpg", 
          "height": 600, 
          "mimetype": "image/jpeg", 
          "secret": "fdetXzFlGlrtUzHdaJ4rlkWBzFvsaCSk", 
          "width": 400
        }, 
        "ds": {
          "extension": "jpg", 
          "height": 320, 
          "mimetype": "image/jpeg", 
          "secret": "fdetXzFlGlrtUzHdaJ4rlkWBzFvsaCSk", 
          "width": 320
        }, 
        "k": {
          "extension": "jpg", 
          "height": 1536, 
          "mimetype": "image/jpeg", 
          "secret": "fdetXzFlGlrtUzHdaJ4rlkWBzFvsaCSk", 
          "width": 1024
        }, 
        "n": {
          "extension": "jpg", 
          "height": 240, 
          "mimetype": "image/jpeg", 
          "secret": "fdetXzFlGlrtUzHdaJ4rlkWBzFvsaCSk", 
          "width": 160
        }, 
        "o": {
          "extension": "jpg", 
          "height": 3600, 
          "mimetype": "image/jpeg", 
          "secret": "NDVs02hpajmNRZOZzCiEI4dztU1MeVFN", 
          "width": 2400
        }, 
        "s": {
          "extension": "jpg", 
          "height": 320, 
          "mimetype": "image/jpeg", 
          "secret": "fdetXzFlGlrtUzHdaJ4rlkWBzFvsaCSk", 
          "width": 320
        }, 
        "z": {
          "extension": "jpg", 
          "height": 480, 
          "mimetype": "image/jpeg", 
          "secret": "fdetXzFlGlrtUzHdaJ4rlkWBzFvsaCSk", 
          "width": 320
        }
      }
    }, 
    "sfomuseum:placetype": "image", 
    "wof:depicts": [
      1159396333, 
      1360516259, 
      1159160347, 
      1159396109, 
      1159396261, 
      102527513
    ], 
    "wof:name": "Installation view of \"Let’s Play! 100 Years of Board Games\"", 
    "wof:placetype": "media" 
  }, 
  "geometry": {"coordinates":[-122.382712,37.617422],"type":"Point"}
}
