{
  "type": "Feature",
  "properties": {
    "date:cessation_lower": "2013-10-28",
    "date:cessation_upper": "2013-10-28",
    "date:inception_lower": "2013-03-15",
    "date:inception_upper": "2013-03-15",
    "iso:country": "US",
    "media:created": 1366258319,
    "media:fingerprint": "416fd68cf4774c21ee0d7447cba2112f6939fa1e",
    "media:imagehash_avg": "a:ff3f00003c3c3c00",
    "media:imagehash_diff": "d:f0f0f0e8f0f0e0e9",
    "media:medium": "image",
    "media:mimetype": "image/jpeg",
    "media:properties": {
      "colours": [
        {
          "hex": "#dccc2f",
          "name": "#dccc2f",
          "reference": "vibrant"
        },
        {
          "hex": "#caa567",
          "name": "#caa567",
          "reference": "vibrant"
        },
        {
          "hex": "#75291d",
          "name": "#75291d",
          "reference": "vibrant"
        },
        {
          "hex": "#a78660",
          "name": "#a78660",
          "reference": "vibrant"
        },
        {
          "hex": "#cabfb2",
          "name": "#cabfb2",
          "reference": "vibrant"
        }
      ],
      "depicts": [
        1159160335
      ],
      "sizes": {
        "b": {
          "extension": "jpg",
          "height": 682,
          "mimetype": "image/jpeg",
          "secret": "20CfURZD87gkNJPIThTMeOeKfNmfouPK",
          "width": 1024
        },
        "c": {
          "extension": "jpg",
          "height": 533,
          "mimetype": "image/jpeg",
          "secret": "20CfURZD87gkNJPIThTMeOeKfNmfouPK",
          "width": 800
        },
        "dc": {
          "extension": "jpg",
          "height": 533,
          "mimetype": "image/jpeg",
          "secret": "20CfURZD87gkNJPIThTMeOeKfNmfouPK",
          "width": 800
        },
        "ds": {
          "extension": "jpg",
          "height": 320,
          "mimetype": "image/jpeg",
          "secret": "20CfURZD87gkNJPIThTMeOeKfNmfouPK",
          "width": 320
        },
        "k": {
          "extension": "jpg",
          "height": 1365,
          "mimetype": "image/jpeg",
          "secret": "20CfURZD87gkNJPIThTMeOeKfNmfouPK",
          "width": 2048
        },
        "n": {
          "extension": "jpg",
          "height": 213,
          "mimetype": "image/jpeg",
          "secret": "20CfURZD87gkNJPIThTMeOeKfNmfouPK",
          "width": 320
        },
        "o": {
          "extension": "jpg",
          "height": 2400,
          "mimetype": "image/jpeg",
          "secret": "qtFpvaz3O0WDXoWhzy8GNYFEMtOeFrvC",
          "width": 3600
        },
        "s": {
          "extension": "jpg",
          "height": 320,
          "mimetype": "image/jpeg",
          "secret": "20CfURZD87gkNJPIThTMeOeKfNmfouPK",
          "width": 320
        },
        "z": {
          "extension": "jpg",
          "height": 426,
          "mimetype": "image/jpeg",
          "secret": "20CfURZD87gkNJPIThTMeOeKfNmfouPK",
          "width": 640
        }
      }
    },
    "sfomuseum:placetype": "image",
    "wof:depicts": [
      1360516121,
      1159396333,
      1159396141,
      1159160335,
      102527513,
      1159396295
    ],
    "wof:name": "Installation view of \"The Art of Recology: The Artist in Residence Program 1990-2013\"",
    "wof:placetype": "media"
  },
  "geometry": {"coordinates":[-122.387197,37.619087],"type":"Point"}
}
