{
  "type": "Feature", 
  "properties": {
    "iso:country": "US", 
    "media:created": -1, 
    "media:fingerprint": "0a1975d8f946663bee5520cae174f47dd2369ce8", 
    "media:medium": "image", 
    "media:mimetype": "image/tiff", 
    "media:properties": {
      "colours": [
        {
          "hex": "#d2b48f", 
          "name": "#d2b48f", 
          "reference": "vibrant"
        }, 
        {
          "hex": "#d5c89e", 
          "name": "#d5c89e", 
          "reference": "vibrant"
        }, 
        {
          "hex": "#90766a", 
          "name": "#90766a", 
          "reference": "vibrant"
        }, 
        {
          "hex": "#c4c3aa", 
          "name": "#c4c3aa", 
          "reference": "vibrant"
        }, 
        {
          "hex": "#55434c", 
          "name": "#55434c", 
          "reference": "vibrant"
        }
      ], 
      "depicts": [1226612107], 
      "sizes": {
        "b": {
          "extension": "jpg", 
          "height": 724, 
          "mimetype": "image/jpeg", 
          "secret": "838hA8uNZ24RAP9sc5jTnZRcAQ9YVsgu", 
          "width": 1024
        }, 
        "c": {
          "extension": "jpg", 
          "height": 565, 
          "mimetype": "image/jpeg", 
          "secret": "838hA8uNZ24RAP9sc5jTnZRcAQ9YVsgu", 
          "width": 800
        }, 
        "dc": {
          "extension": "jpg", 
          "height": 565, 
          "mimetype": "image/jpeg", 
          "secret": "838hA8uNZ24RAP9sc5jTnZRcAQ9YVsgu", 
          "width": 800
        }, 
        "ds": {
          "extension": "jpg", 
          "height": 320, 
          "mimetype": "image/jpeg", 
          "secret": "838hA8uNZ24RAP9sc5jTnZRcAQ9YVsgu", 
          "width": 320
        }, 
        "k": {
          "extension": "jpg", 
          "height": 1448, 
          "mimetype": "image/jpeg", 
          "secret": "838hA8uNZ24RAP9sc5jTnZRcAQ9YVsgu", 
          "width": 2048
        }, 
        "n": {
          "extension": "jpg", 
          "height": 226, 
          "mimetype": "image/jpeg", 
          "secret": "838hA8uNZ24RAP9sc5jTnZRcAQ9YVsgu", 
          "width": 320
        }, 
        "o": {
          "extension": "jpg", 
          "height": 3014, 
          "mimetype": "image/jpeg", 
          "secret": "XqxNjNnmQAvl7YHCW2BdJAntOBzRb0D6", 
          "width": 4262
        }, 
        "s": {
          "extension": "jpg", 
          "height": 320, 
          "mimetype": "image/jpeg", 
          "secret": "838hA8uNZ24RAP9sc5jTnZRcAQ9YVsgu", 
          "width": 320
        }, 
        "z": {
          "extension": "jpg", 
          "height": 452, 
          "mimetype": "image/jpeg", 
          "secret": "838hA8uNZ24RAP9sc5jTnZRcAQ9YVsgu", 
          "width": 640
        }
      }
    }, 
    "sfomuseum:placetype": "image", 
    "wof:depicts": [
      1159554801, 
      1159554819, 
      102527513, 
      1159554841, 
      1226612107, 
      1360516129
    ], 
    "wof:name": "Installation view of \"Airport Cafe\"", 
    "wof:placetype": "media" 
  }, 
  "geometry": {"coordinates":[-122.387197,37.619087],"type":"Point"}
}
