{
  "type": "Feature", 
  "properties": {
    "iso:country": "US", 
    "media:created": 1392063170, 
    "media:fingerprint": "cf115c3328e2a708045a8b17481dfd25681f5030", 
    "media:medium": "image", 
    "media:mimetype": "image/jpeg", 
    "media:properties": {
      "colours": [
        {
          "hex": "#968472", 
          "name": "#968472", 
          "reference": "vibrant"
        }, 
        {
          "hex": "#c7bcb0", 
          "name": "#c7bcb0", 
          "reference": "vibrant"
        }, 
        {
          "hex": "#5a4e45", 
          "name": "#5a4e45", 
          "reference": "vibrant"
        }
      ], 
      "depicts": [1159160469], 
      "sizes": {
        "b": {
          "extension": "jpg", 
          "height": 682, 
          "mimetype": "image/jpeg", 
          "secret": "eLaS2vdbPxwWMK1SdOpaKjqKdH5gxlg4", 
          "width": 1024
        }, 
        "c": {
          "extension": "jpg", 
          "height": 533, 
          "mimetype": "image/jpeg", 
          "secret": "eLaS2vdbPxwWMK1SdOpaKjqKdH5gxlg4", 
          "width": 800
        }, 
        "dc": {
          "extension": "jpg", 
          "height": 533, 
          "mimetype": "image/jpeg", 
          "secret": "eLaS2vdbPxwWMK1SdOpaKjqKdH5gxlg4", 
          "width": 800
        }, 
        "ds": {
          "extension": "jpg", 
          "height": 320, 
          "mimetype": "image/jpeg", 
          "secret": "eLaS2vdbPxwWMK1SdOpaKjqKdH5gxlg4", 
          "width": 320
        }, 
        "k": {
          "extension": "jpg", 
          "height": 1365, 
          "mimetype": "image/jpeg", 
          "secret": "eLaS2vdbPxwWMK1SdOpaKjqKdH5gxlg4", 
          "width": 2048
        }, 
        "n": {
          "extension": "jpg", 
          "height": 213, 
          "mimetype": "image/jpeg", 
          "secret": "eLaS2vdbPxwWMK1SdOpaKjqKdH5gxlg4", 
          "width": 320
        }, 
        "o": {
          "extension": "jpg", 
          "height": 2400, 
          "mimetype": "image/jpeg", 
          "secret": "lY10LbeCsdXpchfrNyhNtMJzvLvXagZL", 
          "width": 3600
        }, 
        "s": {
          "extension": "jpg", 
          "height": 320, 
          "mimetype": "image/jpeg", 
          "secret": "eLaS2vdbPxwWMK1SdOpaKjqKdH5gxlg4", 
          "width": 320
        }, 
        "z": {
          "extension": "jpg", 
          "height": 426, 
          "mimetype": "image/jpeg", 
          "secret": "eLaS2vdbPxwWMK1SdOpaKjqKdH5gxlg4", 
          "width": 640
        }
      }
    }, 
    "sfomuseum:placetype": "image", 
    "wof:depicts": [
      1360516259, 
      1159396109, 
      102527513, 
      1159396261, 
      1159396333, 
      1159160469
    ], 
    "wof:name": "Installation view of \"San Francisco, From the David Rumsey Map Collection\"", 
    "wof:placetype": "media" 
  }, 
  "geometry": {"coordinates":[-122.382712,37.617422],"type":"Point"}
}
