{
  "type": "Feature",
  "properties": {
    "date:cessation_lower": "1996-09-15",
    "date:cessation_upper": "1996-09-15",
    "date:inception_lower": "1996-03-15",
    "date:inception_upper": "1996-03-15",
    "iso:country": "US",
    "media:created": -1,
    "media:fingerprint": "f39e25d9b07536e3c9abed5cd5b44827390382f0",
    "media:imagehash_avg": "a:387f7f7f1f0e0000",
    "media:imagehash_diff": "d:e2e3d3bbbc9cf4c2",
    "media:medium": "image",
    "media:mimetype": "image/tiff",
    "media:placetype": "installation",
    "media:properties": {
      "colours": [
        {
          "hex": "#6b362e",
          "name": "#6b362e",
          "reference": "vibrant"
        },
        {
          "hex": "#98906c",
          "name": "#98906c",
          "reference": "vibrant"
        },
        {
          "hex": "#c0beb4",
          "name": "#c0beb4",
          "reference": "vibrant"
        },
        {
          "hex": "#433b44",
          "name": "#433b44",
          "reference": "vibrant"
        }
      ],
      "depicts": [
        1226611157
      ],
      "sizes": {
        "b": {
          "extension": "jpg",
          "height": 726,
          "mimetype": "image/jpeg",
          "secret": "aWtA3xIlWT67n8baKgopgE5SntjM3vpT",
          "width": 1024
        },
        "c": {
          "extension": "jpg",
          "height": 567,
          "mimetype": "image/jpeg",
          "secret": "aWtA3xIlWT67n8baKgopgE5SntjM3vpT",
          "width": 800
        },
        "dc": {
          "extension": "jpg",
          "height": 567,
          "mimetype": "image/jpeg",
          "secret": "aWtA3xIlWT67n8baKgopgE5SntjM3vpT",
          "width": 800
        },
        "ds": {
          "extension": "jpg",
          "height": 320,
          "mimetype": "image/jpeg",
          "secret": "aWtA3xIlWT67n8baKgopgE5SntjM3vpT",
          "width": 320
        },
        "k": {
          "extension": "jpg",
          "height": 1452,
          "mimetype": "image/jpeg",
          "secret": "aWtA3xIlWT67n8baKgopgE5SntjM3vpT",
          "width": 2048
        },
        "n": {
          "extension": "jpg",
          "height": 226,
          "mimetype": "image/jpeg",
          "secret": "aWtA3xIlWT67n8baKgopgE5SntjM3vpT",
          "width": 320
        },
        "o": {
          "extension": "jpg",
          "height": 3014,
          "mimetype": "image/jpeg",
          "secret": "ndRJBoOp8fsF1NcIsyqniLgbx8SeYMJ6",
          "width": 4251
        },
        "s": {
          "extension": "jpg",
          "height": 320,
          "mimetype": "image/jpeg",
          "secret": "aWtA3xIlWT67n8baKgopgE5SntjM3vpT",
          "width": 320
        },
        "z": {
          "extension": "jpg",
          "height": 453,
          "mimetype": "image/jpeg",
          "secret": "aWtA3xIlWT67n8baKgopgE5SntjM3vpT",
          "width": 640
        }
      }
    },
    "sfomuseum:placetype": "image",
    "wof:depicts": [
      1360516127,
      102527513,
      1226611157,
      1159554803,
      1159554855,
      1159554821
    ],
    "wof:name": "Installation view of \"Boomerang\"",
    "wof:placetype": "media"
  },
  "geometry": {"coordinates":[-122.387197,37.619087],"type":"Point"}
}
