{
  "type": "Feature",
  "properties": {
    "date:cessation_lower": "2017-12-11",
    "date:cessation_upper": "2017-12-11",
    "date:inception_lower": "2017-04-21",
    "date:inception_upper": "2017-04-21",
    "iso:country": "US",
    "media:created": 1493398605,
    "media:fingerprint": "c4d67bb985584dcb6454dbdd4db8369a26aecb40",
    "media:imagehash_avg": "a:81ffc3c1030be100",
    "media:imagehash_diff": "d:550f8a0373539379",
    "media:medium": "image",
    "media:mimetype": "image/jpeg",
    "media:properties": {
      "colours": [
        {
          "hex": "#b97b46",
          "name": "#b97b46",
          "reference": "vibrant"
        },
        {
          "hex": "#e4c19a",
          "name": "#e4c19a",
          "reference": "vibrant"
        },
        {
          "hex": "#462913",
          "name": "#462913",
          "reference": "vibrant"
        },
        {
          "hex": "#a67d6e",
          "name": "#a67d6e",
          "reference": "vibrant"
        },
        {
          "hex": "#c2b09c",
          "name": "#c2b09c",
          "reference": "vibrant"
        }
      ],
      "depicts": [
        1159160703
      ],
      "sizes": {
        "b": {
          "extension": "jpg",
          "height": 768,
          "mimetype": "image/jpeg",
          "secret": "kGmQ36VU2PVY4kB8AL5etLEbBf9RB4In",
          "width": 614
        },
        "c": {
          "extension": "jpg",
          "height": 600,
          "mimetype": "image/jpeg",
          "secret": "kGmQ36VU2PVY4kB8AL5etLEbBf9RB4In",
          "width": 480
        },
        "dc": {
          "extension": "jpg",
          "height": 600,
          "mimetype": "image/jpeg",
          "secret": "kGmQ36VU2PVY4kB8AL5etLEbBf9RB4In",
          "width": 480
        },
        "ds": {
          "extension": "jpg",
          "height": 320,
          "mimetype": "image/jpeg",
          "secret": "kGmQ36VU2PVY4kB8AL5etLEbBf9RB4In",
          "width": 320
        },
        "k": {
          "extension": "jpg",
          "height": 1536,
          "mimetype": "image/jpeg",
          "secret": "kGmQ36VU2PVY4kB8AL5etLEbBf9RB4In",
          "width": 1228
        },
        "n": {
          "extension": "jpg",
          "height": 240,
          "mimetype": "image/jpeg",
          "secret": "kGmQ36VU2PVY4kB8AL5etLEbBf9RB4In",
          "width": 192
        },
        "o": {
          "extension": "jpg",
          "height": 3600,
          "mimetype": "image/jpeg",
          "secret": "3urbowtTjpjN1H7GyVMXrp3VH0yzC6SY",
          "width": 2880
        },
        "s": {
          "extension": "jpg",
          "height": 320,
          "mimetype": "image/jpeg",
          "secret": "kGmQ36VU2PVY4kB8AL5etLEbBf9RB4In",
          "width": 320
        },
        "z": {
          "extension": "jpg",
          "height": 480,
          "mimetype": "image/jpeg",
          "secret": "kGmQ36VU2PVY4kB8AL5etLEbBf9RB4In",
          "width": 384
        }
      }
    },
    "sfomuseum:placetype": "image",
    "wof:depicts": [
      1159157335,
      1159157037,
      102527513,
      1159160703,
      1159268871,
      1159157333,
      1159157271
    ],
    "wof:name": "Installation view of \"At Home with Arts and Crafts\"",
    "wof:placetype": "media"
  },
  "geometry": {"coordinates":[-122.389537,37.616642],"type":"Point"}
}
