{
  "type": "Feature",
  "properties": {
    "date:cessation_lower": "1991-06-30",
    "date:cessation_upper": "1991-06-30",
    "date:inception_lower": "1991-05-01",
    "date:inception_upper": "1991-05-01",
    "iso:country": "US",
    "media:created": -1,
    "media:fingerprint": "03f060494a689fc956d74ac2669fc91b443a68f1",
    "media:imagehash_avg": "a:e6f766e2fe7e4000",
    "media:imagehash_diff": "d:cccccc8e96b2a292",
    "media:medium": "image",
    "media:mimetype": "image/tiff",
    "media:placetype": "installation",
    "media:properties": {
      "colours": [
        {
          "hex": "#d0bb9b",
          "name": "#d0bb9b",
          "reference": "vibrant"
        },
        {
          "hex": "#85868e",
          "name": "#85868e",
          "reference": "vibrant"
        },
        {
          "hex": "#d6ccb4",
          "name": "#d6ccb4",
          "reference": "vibrant"
        },
        {
          "hex": "#423847",
          "name": "#423847",
          "reference": "vibrant"
        }
      ],
      "depicts": [
        1226607773
      ],
      "sizes": {
        "b": {
          "extension": "jpg",
          "height": 768,
          "mimetype": "image/jpeg",
          "secret": "Uy8yByEpkiAiCZ1y5Gj7bJo029yHmf0e",
          "width": 544
        },
        "c": {
          "extension": "jpg",
          "height": 600,
          "mimetype": "image/jpeg",
          "secret": "Uy8yByEpkiAiCZ1y5Gj7bJo029yHmf0e",
          "width": 425
        },
        "dc": {
          "extension": "jpg",
          "height": 600,
          "mimetype": "image/jpeg",
          "secret": "Uy8yByEpkiAiCZ1y5Gj7bJo029yHmf0e",
          "width": 425
        },
        "ds": {
          "extension": "jpg",
          "height": 320,
          "mimetype": "image/jpeg",
          "secret": "Uy8yByEpkiAiCZ1y5Gj7bJo029yHmf0e",
          "width": 320
        },
        "k": {
          "extension": "jpg",
          "height": 1536,
          "mimetype": "image/jpeg",
          "secret": "Uy8yByEpkiAiCZ1y5Gj7bJo029yHmf0e",
          "width": 1089
        },
        "n": {
          "extension": "jpg",
          "height": 240,
          "mimetype": "image/jpeg",
          "secret": "Uy8yByEpkiAiCZ1y5Gj7bJo029yHmf0e",
          "width": 170
        },
        "o": {
          "extension": "jpg",
          "height": 4251,
          "mimetype": "image/jpeg",
          "secret": "sjhNgxJdQTjlfHSORCywzVsdQ6cGF4g7",
          "width": 3014
        },
        "s": {
          "extension": "jpg",
          "height": 320,
          "mimetype": "image/jpeg",
          "secret": "Uy8yByEpkiAiCZ1y5Gj7bJo029yHmf0e",
          "width": 320
        },
        "z": {
          "extension": "jpg",
          "height": 480,
          "mimetype": "image/jpeg",
          "secret": "Uy8yByEpkiAiCZ1y5Gj7bJo029yHmf0e",
          "width": 340
        }
      }
    },
    "sfomuseum:placetype": "image",
    "wof:depicts": [
      1159554803,
      1360516471,
      1226607773,
      102527513,
      1159554829
    ],
    "wof:name": "Installation view of \"Bowling: A Unique American Art Form\"",
    "wof:placetype": "custom",
    "wof:placetype_alt": [
      "image"
    ]
  },
  "geometry": {"type":"Point","coordinates":[-122.38274,37.617227]}
}
