{
  "type": "Feature", 
  "properties": {
    "iso:country": "US", 
    "media:created": 1538415172, 
    "media:fingerprint": "b5c06e6f691248af120c2374ebd9cb8af7e14035", 
    "media:medium": "image", 
    "media:mimetype": "image/jpeg", 
    "media:properties": {
      "colours": [
        {
          "hex": "#c2864b", 
          "name": "#c2864b", 
          "reference": "vibrant"
        }, 
        {
          "hex": "#355a74", 
          "name": "#355a74", 
          "reference": "vibrant"
        }, 
        {
          "hex": "#937476", 
          "name": "#937476", 
          "reference": "vibrant"
        }, 
        {
          "hex": "#c7ad95", 
          "name": "#c7ad95", 
          "reference": "vibrant"
        }, 
        {
          "hex": "#3d464a", 
          "name": "#3d464a", 
          "reference": "vibrant"
        }
      ], 
      "depicts": [1360664647], 
      "sizes": {
        "b": {
          "extension": "jpg", 
          "height": 682, 
          "mimetype": "image/jpeg", 
          "secret": "kS4KzWePu2BOPyTLYiUrgUwXjGM0M6L3", 
          "width": 1024
        }, 
        "c": {
          "extension": "jpg", 
          "height": 533, 
          "mimetype": "image/jpeg", 
          "secret": "kS4KzWePu2BOPyTLYiUrgUwXjGM0M6L3", 
          "width": 800
        }, 
        "dc": {
          "extension": "jpg", 
          "height": 533, 
          "mimetype": "image/jpeg", 
          "secret": "kS4KzWePu2BOPyTLYiUrgUwXjGM0M6L3", 
          "width": 800
        }, 
        "ds": {
          "extension": "jpg", 
          "height": 320, 
          "mimetype": "image/jpeg", 
          "secret": "kS4KzWePu2BOPyTLYiUrgUwXjGM0M6L3", 
          "width": 320
        }, 
        "k": {
          "extension": "jpg", 
          "height": 1365, 
          "mimetype": "image/jpeg", 
          "secret": "kS4KzWePu2BOPyTLYiUrgUwXjGM0M6L3", 
          "width": 2048
        }, 
        "n": {
          "extension": "jpg", 
          "height": 213, 
          "mimetype": "image/jpeg", 
          "secret": "kS4KzWePu2BOPyTLYiUrgUwXjGM0M6L3", 
          "width": 320
        }, 
        "o": {
          "extension": "jpg", 
          "height": 2400, 
          "mimetype": "image/jpeg", 
          "secret": "umPbVhq9p3pwxHN9VCAhwZXVJfRv53M1", 
          "width": 3600
        }, 
        "s": {
          "extension": "jpg", 
          "height": 320, 
          "mimetype": "image/jpeg", 
          "secret": "kS4KzWePu2BOPyTLYiUrgUwXjGM0M6L3", 
          "width": 320
        }, 
        "z": {
          "extension": "jpg", 
          "height": 426, 
          "mimetype": "image/jpeg", 
          "secret": "kS4KzWePu2BOPyTLYiUrgUwXjGM0M6L3", 
          "width": 640
        }
      }
    }, 
    "sfomuseum:placetype": "image", 
    "wof:depicts": [
      1159157271, 
      102527513, 
      1159396181, 
      1159157067, 
      1360664647, 
      1159396121
    ], 
    "wof:name": "Installation view of \"Down-Home Music: The Story of Arhoolie Records\"", 
    "wof:placetype": "media" 
  }, 
  "geometry": {"coordinates":[-122.382712,37.617422],"type":"Point"}
}
