{
  "type": "Feature", 
  "properties": {
    "iso:country": "US", 
    "media:created": 1023482087, 
    "media:fingerprint": "5641271323973e4aedab5ebc053b3f1d8449b793", 
    "media:medium": "image", 
    "media:mimetype": "image/jpeg", 
    "media:properties": {
      "colours": [
        {
          "hex": "#dd3723", 
          "name": "#dd3723", 
          "reference": "vibrant"
        }, 
        {
          "hex": "#4dbfea", 
          "name": "#4dbfea", 
          "reference": "vibrant"
        }, 
        {
          "hex": "#bb2619", 
          "name": "#bb2619", 
          "reference": "vibrant"
        }, 
        {
          "hex": "#988867", 
          "name": "#988867", 
          "reference": "vibrant"
        }, 
        {
          "hex": "#d6ceb8", 
          "name": "#d6ceb8", 
          "reference": "vibrant"
        }
      ], 
      "depicts": [1159159507], 
      "sizes": {
        "b": {
          "extension": "jpg", 
          "height": 768, 
          "mimetype": "image/jpeg", 
          "secret": "6SZLu1DiLq4voRL4KJMTBsqXSwvzShBY", 
          "width": 1024
        }, 
        "c": {
          "extension": "jpg", 
          "height": 600, 
          "mimetype": "image/jpeg", 
          "secret": "6SZLu1DiLq4voRL4KJMTBsqXSwvzShBY", 
          "width": 800
        }, 
        "dc": {
          "extension": "jpg", 
          "height": 600, 
          "mimetype": "image/jpeg", 
          "secret": "6SZLu1DiLq4voRL4KJMTBsqXSwvzShBY", 
          "width": 800
        }, 
        "ds": {
          "extension": "jpg", 
          "height": 320, 
          "mimetype": "image/jpeg", 
          "secret": "6SZLu1DiLq4voRL4KJMTBsqXSwvzShBY", 
          "width": 320
        }, 
        "k": {
          "extension": "jpg", 
          "height": 1536, 
          "mimetype": "image/jpeg", 
          "secret": "6SZLu1DiLq4voRL4KJMTBsqXSwvzShBY", 
          "width": 2048
        }, 
        "n": {
          "extension": "jpg", 
          "height": 240, 
          "mimetype": "image/jpeg", 
          "secret": "6SZLu1DiLq4voRL4KJMTBsqXSwvzShBY", 
          "width": 320
        }, 
        "o": {
          "extension": "jpg", 
          "height": 1920, 
          "mimetype": "image/jpeg", 
          "secret": "7UpYGI1GrdMWc7hI6aiVMyVFtbScxkTw", 
          "width": 2560
        }, 
        "s": {
          "extension": "jpg", 
          "height": 320, 
          "mimetype": "image/jpeg", 
          "secret": "6SZLu1DiLq4voRL4KJMTBsqXSwvzShBY", 
          "width": 320
        }, 
        "z": {
          "extension": "jpg", 
          "height": 480, 
          "mimetype": "image/jpeg", 
          "secret": "6SZLu1DiLq4voRL4KJMTBsqXSwvzShBY", 
          "width": 640
        }
      }
    }, 
    "sfomuseum:placetype": "image", 
    "wof:depicts": [
      1159396107, 
      1360541557, 
      1159396319, 
      1360521571, 
      1159159507, 
      102527513
    ], 
    "wof:name": "Installation view of \"The Golden Age of Airships\"", 
    "wof:placetype": "media" 
  }, 
  "geometry": {"coordinates":[-122.38622,37.616463],"type":"Point"}
}
