{
  "type": "Feature", 
  "properties": {
    "iso:country": "US", 
    "media:created": 1383966120, 
    "media:fingerprint": "9030c71fd39c1a1a7657fcd4f77fd460eeafb19f", 
    "media:medium": "image", 
    "media:mimetype": "image/jpeg", 
    "media:properties": {
      "colours": [
        {
          "hex": "#c78c3e", 
          "name": "#c78c3e", 
          "reference": "vibrant"
        }, 
        {
          "hex": "#7c3a35", 
          "name": "#7c3a35", 
          "reference": "vibrant"
        }, 
        {
          "hex": "#6f8b90", 
          "name": "#6f8b90", 
          "reference": "vibrant"
        }, 
        {
          "hex": "#c2b9b1", 
          "name": "#c2b9b1", 
          "reference": "vibrant"
        }, 
        {
          "hex": "#3f3c37", 
          "name": "#3f3c37", 
          "reference": "vibrant"
        }
      ], 
      "depicts": [1159160369], 
      "sizes": {
        "b": {
          "extension": "jpg", 
          "height": 682, 
          "mimetype": "image/jpeg", 
          "secret": "EVowcywo3O5HTzbZe7BaYt8ujVzgpMTd", 
          "width": 1024
        }, 
        "c": {
          "extension": "jpg", 
          "height": 533, 
          "mimetype": "image/jpeg", 
          "secret": "EVowcywo3O5HTzbZe7BaYt8ujVzgpMTd", 
          "width": 800
        }, 
        "dc": {
          "extension": "jpg", 
          "height": 533, 
          "mimetype": "image/jpeg", 
          "secret": "EVowcywo3O5HTzbZe7BaYt8ujVzgpMTd", 
          "width": 800
        }, 
        "ds": {
          "extension": "jpg", 
          "height": 320, 
          "mimetype": "image/jpeg", 
          "secret": "EVowcywo3O5HTzbZe7BaYt8ujVzgpMTd", 
          "width": 320
        }, 
        "k": {
          "extension": "jpg", 
          "height": 1365, 
          "mimetype": "image/jpeg", 
          "secret": "EVowcywo3O5HTzbZe7BaYt8ujVzgpMTd", 
          "width": 2048
        }, 
        "n": {
          "extension": "jpg", 
          "height": 213, 
          "mimetype": "image/jpeg", 
          "secret": "EVowcywo3O5HTzbZe7BaYt8ujVzgpMTd", 
          "width": 320
        }, 
        "o": {
          "extension": "jpg", 
          "height": 2400, 
          "mimetype": "image/jpeg", 
          "secret": "EcINyWRAeJ1cDZCEtU5T75X4E2b0Ln9X", 
          "width": 3600
        }, 
        "s": {
          "extension": "jpg", 
          "height": 320, 
          "mimetype": "image/jpeg", 
          "secret": "EVowcywo3O5HTzbZe7BaYt8ujVzgpMTd", 
          "width": 320
        }, 
        "z": {
          "extension": "jpg", 
          "height": 426, 
          "mimetype": "image/jpeg", 
          "secret": "EVowcywo3O5HTzbZe7BaYt8ujVzgpMTd", 
          "width": 640
        }
      }
    }, 
    "sfomuseum:placetype": "image", 
    "wof:depicts": [
      102527513, 
      1159396333, 
      1360516121, 
      1159396295, 
      1159160369, 
      1159396141
    ], 
    "wof:name": "Installation view of \"Japanese Toys! From Kokeshi to Kaiju\"", 
    "wof:placetype": "media" 
  }, 
  "geometry": {"coordinates":[-122.387197,37.619087],"type":"Point"}
}
