{
  "type": "Feature",
  "properties": {
    "date:cessation_lower": "2014-05-12",
    "date:cessation_upper": "2014-05-12",
    "date:inception_lower": "2013-11-01",
    "date:inception_upper": "2013-11-01",
    "iso:country": "US",
    "media:created": 1383964208,
    "media:fingerprint": "dfb5f0dc058750ff53c6bf9dfb7ea3e06fd6ca22",
    "media:imagehash_avg": "a:79f8ecece0e6e0f0",
    "media:imagehash_diff": "d:e3d159580a0c01c0",
    "media:medium": "image",
    "media:mimetype": "image/jpeg",
    "media:placetype": "installation",
    "media:properties": {
      "colours": [
        {
          "hex": "#c8aa5b",
          "name": "#c8aa5b",
          "reference": "vibrant"
        },
        {
          "hex": "#8e3130",
          "name": "#8e3130",
          "reference": "vibrant"
        },
        {
          "hex": "#a68f53",
          "name": "#a68f53",
          "reference": "vibrant"
        },
        {
          "hex": "#c6bf9c",
          "name": "#c6bf9c",
          "reference": "vibrant"
        },
        {
          "hex": "#47453e",
          "name": "#47453e",
          "reference": "vibrant"
        }
      ],
      "depicts": [
        1159160369
      ],
      "sizes": {
        "b": {
          "extension": "jpg",
          "height": 682,
          "mimetype": "image/jpeg",
          "secret": "ZL8VuTL19ANtcRyweuE1JQ0MOQoTX3Xr",
          "width": 1024
        },
        "c": {
          "extension": "jpg",
          "height": 533,
          "mimetype": "image/jpeg",
          "secret": "ZL8VuTL19ANtcRyweuE1JQ0MOQoTX3Xr",
          "width": 800
        },
        "dc": {
          "extension": "jpg",
          "height": 533,
          "mimetype": "image/jpeg",
          "secret": "ZL8VuTL19ANtcRyweuE1JQ0MOQoTX3Xr",
          "width": 800
        },
        "ds": {
          "extension": "jpg",
          "height": 320,
          "mimetype": "image/jpeg",
          "secret": "ZL8VuTL19ANtcRyweuE1JQ0MOQoTX3Xr",
          "width": 320
        },
        "k": {
          "extension": "jpg",
          "height": 1365,
          "mimetype": "image/jpeg",
          "secret": "ZL8VuTL19ANtcRyweuE1JQ0MOQoTX3Xr",
          "width": 2048
        },
        "n": {
          "extension": "jpg",
          "height": 213,
          "mimetype": "image/jpeg",
          "secret": "ZL8VuTL19ANtcRyweuE1JQ0MOQoTX3Xr",
          "width": 320
        },
        "o": {
          "extension": "jpg",
          "height": 2400,
          "mimetype": "image/jpeg",
          "secret": "A7XqGm8TucRm6WdafT53ItexrsZpeO2k",
          "width": 3600
        },
        "s": {
          "extension": "jpg",
          "height": 320,
          "mimetype": "image/jpeg",
          "secret": "ZL8VuTL19ANtcRyweuE1JQ0MOQoTX3Xr",
          "width": 320
        },
        "z": {
          "extension": "jpg",
          "height": 426,
          "mimetype": "image/jpeg",
          "secret": "ZL8VuTL19ANtcRyweuE1JQ0MOQoTX3Xr",
          "width": 640
        }
      }
    },
    "sfomuseum:placetype": "image",
    "wof:depicts": [
      1159396295,
      1159396141,
      1159396333,
      1159160369,
      1360516121,
      102527513
    ],
    "wof:name": "Installation view of \"Japanese Toys! From Kokeshi to Kaiju\"",
    "wof:placetype": "custom",
    "wof:placetype_alt": [
      "image"
    ]
  },
  "geometry": {"type":"Point","coordinates":[-122.387197,37.619087]}
}
