{
  "type": "Feature", 
  "properties": {
    "iso:country": "US", 
    "media:created": 1540229755, 
    "media:fingerprint": "e9a4def77bae1ce7933e5761ff978f2267a659cd", 
    "media:medium": "image", 
    "media:mimetype": "image/jpeg", 
    "media:properties": {
      "colours": [
        {
          "hex": "#5686a3", 
          "name": "#5686a3", 
          "reference": "vibrant"
        }, 
        {
          "hex": "#b0bdc3", 
          "name": "#b0bdc3", 
          "reference": "vibrant"
        }, 
        {
          "hex": "#413946", 
          "name": "#413946", 
          "reference": "vibrant"
        }
      ], 
      "depicts": [1360667837], 
      "sizes": {
        "b": {
          "extension": "jpg", 
          "height": 768, 
          "mimetype": "image/jpeg", 
          "secret": "4CvlF8PSyfoIaIMwXyKOGN6dIQsnryis", 
          "width": 614
        }, 
        "c": {
          "extension": "jpg", 
          "height": 600, 
          "mimetype": "image/jpeg", 
          "secret": "4CvlF8PSyfoIaIMwXyKOGN6dIQsnryis", 
          "width": 480
        }, 
        "dc": {
          "extension": "jpg", 
          "height": 600, 
          "mimetype": "image/jpeg", 
          "secret": "4CvlF8PSyfoIaIMwXyKOGN6dIQsnryis", 
          "width": 480
        }, 
        "ds": {
          "extension": "jpg", 
          "height": 320, 
          "mimetype": "image/jpeg", 
          "secret": "4CvlF8PSyfoIaIMwXyKOGN6dIQsnryis", 
          "width": 320
        }, 
        "k": {
          "extension": "jpg", 
          "height": 1536, 
          "mimetype": "image/jpeg", 
          "secret": "4CvlF8PSyfoIaIMwXyKOGN6dIQsnryis", 
          "width": 1228
        }, 
        "n": {
          "extension": "jpg", 
          "height": 240, 
          "mimetype": "image/jpeg", 
          "secret": "4CvlF8PSyfoIaIMwXyKOGN6dIQsnryis", 
          "width": 192
        }, 
        "o": {
          "extension": "jpg", 
          "height": 3600, 
          "mimetype": "image/jpeg", 
          "secret": "Ei1jQAoyBUcCzSEb4M7bWZBwQh4DP30q", 
          "width": 2880
        }, 
        "s": {
          "extension": "jpg", 
          "height": 320, 
          "mimetype": "image/jpeg", 
          "secret": "4CvlF8PSyfoIaIMwXyKOGN6dIQsnryis", 
          "width": 320
        }, 
        "z": {
          "extension": "jpg", 
          "height": 480, 
          "mimetype": "image/jpeg", 
          "secret": "4CvlF8PSyfoIaIMwXyKOGN6dIQsnryis", 
          "width": 384
        }
      }
    }, 
    "sfomuseum:placetype": "image", 
    "wof:depicts": [
      1159157271, 
      102527513, 
      1159157335, 
      1159157037, 
      1159157333, 
      1360667837
    ], 
    "wof:name": "Installation view of \"A Sterling Renaissance, British Silver Design 1957-2018\"", 
    "wof:placetype": "media" 
  }, 
  "geometry": {"coordinates":[-122.389725,37.616594],"type":"Point"}
}
