{
  "type": "Feature", 
  "properties": {
    "iso:country": "US", 
    "media:created": 1269892585, 
    "media:fingerprint": "41955cadaaeac1228288080817421c8a5fda78e2", 
    "media:medium": "image", 
    "media:mimetype": "image/jpeg", 
    "media:properties": {
      "colours": [
        {
          "hex": "#ce433b", 
          "name": "#ce433b", 
          "reference": "vibrant"
        }, 
        {
          "hex": "#103791", 
          "name": "#103791", 
          "reference": "vibrant"
        }, 
        {
          "hex": "#9d7b56", 
          "name": "#9d7b56", 
          "reference": "vibrant"
        }, 
        {
          "hex": "#c8c8bd", 
          "name": "#c8c8bd", 
          "reference": "vibrant"
        }, 
        {
          "hex": "#2f211b", 
          "name": "#2f211b", 
          "reference": "vibrant"
        }
      ], 
      "depicts": [1159160109], 
      "sizes": {
        "b": {
          "extension": "jpg", 
          "height": 685, 
          "mimetype": "image/jpeg", 
          "secret": "gHuZIW0U4RklGiS3h9l8q3VCUhiZXdj8", 
          "width": 1024
        }, 
        "c": {
          "extension": "jpg", 
          "height": 535, 
          "mimetype": "image/jpeg", 
          "secret": "gHuZIW0U4RklGiS3h9l8q3VCUhiZXdj8", 
          "width": 800
        }, 
        "dc": {
          "extension": "jpg", 
          "height": 535, 
          "mimetype": "image/jpeg", 
          "secret": "gHuZIW0U4RklGiS3h9l8q3VCUhiZXdj8", 
          "width": 800
        }, 
        "ds": {
          "extension": "jpg", 
          "height": 320, 
          "mimetype": "image/jpeg", 
          "secret": "gHuZIW0U4RklGiS3h9l8q3VCUhiZXdj8", 
          "width": 320
        }, 
        "k": {
          "extension": "jpg", 
          "height": 1370, 
          "mimetype": "image/jpeg", 
          "secret": "gHuZIW0U4RklGiS3h9l8q3VCUhiZXdj8", 
          "width": 2048
        }, 
        "n": {
          "extension": "jpg", 
          "height": 214, 
          "mimetype": "image/jpeg", 
          "secret": "gHuZIW0U4RklGiS3h9l8q3VCUhiZXdj8", 
          "width": 320
        }, 
        "o": {
          "extension": "jpg", 
          "height": 2592, 
          "mimetype": "image/jpeg", 
          "secret": "1iO9oLvsO8UgPJwjm2tzQ8KQPIsquHbW", 
          "width": 3872
        }, 
        "s": {
          "extension": "jpg", 
          "height": 320, 
          "mimetype": "image/jpeg", 
          "secret": "gHuZIW0U4RklGiS3h9l8q3VCUhiZXdj8", 
          "width": 320
        }, 
        "z": {
          "extension": "jpg", 
          "height": 428, 
          "mimetype": "image/jpeg", 
          "secret": "gHuZIW0U4RklGiS3h9l8q3VCUhiZXdj8", 
          "width": 640
        }
      }
    }, 
    "sfomuseum:placetype": "image", 
    "wof:depicts": [
      1360541661, 
      1159396147, 
      102527513, 
      1360521569, 
      1159160109, 
      1159396337
    ], 
    "wof:name": "Installation view of \"Japan Airlines: Over Fifty-Five Years of Service\"", 
    "wof:placetype": "media" 
  }, 
  "geometry": {"coordinates":[-122.387989,37.614385],"type":"Point"}
}
