{
  "type": "Feature",
  "properties": {
    "date:cessation_lower": "2013-07-15",
    "date:cessation_upper": "2013-07-15",
    "date:inception_lower": "2013-01-11",
    "date:inception_upper": "2013-01-11",
    "iso:country": "US",
    "media:created": 1360969016,
    "media:fingerprint": "e8e644178156be5cccc346ebfe4e702f3e40a0aa",
    "media:imagehash_avg": "a:7871717f7f07c7ff",
    "media:imagehash_diff": "d:e0e3e3e1d89c1c08",
    "media:medium": "image",
    "media:mimetype": "image/jpeg",
    "media:placetype": "installation",
    "media:properties": {
      "colours": [
        {
          "hex": "#d3b52f",
          "name": "#d3b52f",
          "reference": "vibrant"
        },
        {
          "hex": "#dec8a7",
          "name": "#dec8a7",
          "reference": "vibrant"
        },
        {
          "hex": "#80522b",
          "name": "#80522b",
          "reference": "vibrant"
        },
        {
          "hex": "#947c64",
          "name": "#947c64",
          "reference": "vibrant"
        },
        {
          "hex": "#cfbb9a",
          "name": "#cfbb9a",
          "reference": "vibrant"
        }
      ],
      "depicts": [
        1159160359
      ],
      "sizes": {
        "b": {
          "extension": "jpg",
          "height": 682,
          "mimetype": "image/jpeg",
          "secret": "GpfYIQ5ZicLXMbX34Gsw3usQWQw3T1oy",
          "width": 1024
        },
        "c": {
          "extension": "jpg",
          "height": 533,
          "mimetype": "image/jpeg",
          "secret": "GpfYIQ5ZicLXMbX34Gsw3usQWQw3T1oy",
          "width": 800
        },
        "dc": {
          "extension": "jpg",
          "height": 533,
          "mimetype": "image/jpeg",
          "secret": "GpfYIQ5ZicLXMbX34Gsw3usQWQw3T1oy",
          "width": 800
        },
        "ds": {
          "extension": "jpg",
          "height": 320,
          "mimetype": "image/jpeg",
          "secret": "GpfYIQ5ZicLXMbX34Gsw3usQWQw3T1oy",
          "width": 320
        },
        "k": {
          "extension": "jpg",
          "height": 1365,
          "mimetype": "image/jpeg",
          "secret": "GpfYIQ5ZicLXMbX34Gsw3usQWQw3T1oy",
          "width": 2048
        },
        "n": {
          "extension": "jpg",
          "height": 213,
          "mimetype": "image/jpeg",
          "secret": "GpfYIQ5ZicLXMbX34Gsw3usQWQw3T1oy",
          "width": 320
        },
        "o": {
          "extension": "jpg",
          "height": 2401,
          "mimetype": "image/jpeg",
          "secret": "QGOH4n37RhC8jMY9GeWMExNZfBSW1wop",
          "width": 3600
        },
        "s": {
          "extension": "jpg",
          "height": 320,
          "mimetype": "image/jpeg",
          "secret": "GpfYIQ5ZicLXMbX34Gsw3usQWQw3T1oy",
          "width": 320
        },
        "z": {
          "extension": "jpg",
          "height": 426,
          "mimetype": "image/jpeg",
          "secret": "GpfYIQ5ZicLXMbX34Gsw3usQWQw3T1oy",
          "width": 640
        }
      }
    },
    "sfomuseum:placetype": "image",
    "wof:depicts": [
      1360516283,
      1159160359,
      1159396159,
      1159396333,
      102527513
    ],
    "wof:name": "Installation view of \"Souvenirs: Tokens of Travel\"",
    "wof:placetype": "custom",
    "wof:placetype_alt": [
      "image"
    ]
  },
  "geometry": {"type":"Point","coordinates":[-122.389725,37.616594]}
}
