{
  "type": "Feature", 
  "properties": {
    "iso:country": "US", 
    "media:created": 1360969016, 
    "media:fingerprint": "e8e644178156be5cccc346ebfe4e702f3e40a0aa", 
    "media:medium": "image", 
    "media:mimetype": "image/jpeg", 
    "media:properties": {
      "colours": [
        {
          "hex": "#d3b52f", 
          "name": "#d3b52f", 
          "reference": "vibrant"
        }, 
        {
          "hex": "#dec8a7", 
          "name": "#dec8a7", 
          "reference": "vibrant"
        }, 
        {
          "hex": "#80522b", 
          "name": "#80522b", 
          "reference": "vibrant"
        }, 
        {
          "hex": "#947c64", 
          "name": "#947c64", 
          "reference": "vibrant"
        }, 
        {
          "hex": "#cfbb9a", 
          "name": "#cfbb9a", 
          "reference": "vibrant"
        }
      ], 
      "depicts": [1159160359], 
      "sizes": {
        "b": {
          "extension": "jpg", 
          "height": 682, 
          "mimetype": "image/jpeg", 
          "secret": "GpfYIQ5ZicLXMbX34Gsw3usQWQw3T1oy", 
          "width": 1024
        }, 
        "c": {
          "extension": "jpg", 
          "height": 533, 
          "mimetype": "image/jpeg", 
          "secret": "GpfYIQ5ZicLXMbX34Gsw3usQWQw3T1oy", 
          "width": 800
        }, 
        "dc": {
          "extension": "jpg", 
          "height": 533, 
          "mimetype": "image/jpeg", 
          "secret": "GpfYIQ5ZicLXMbX34Gsw3usQWQw3T1oy", 
          "width": 800
        }, 
        "ds": {
          "extension": "jpg", 
          "height": 320, 
          "mimetype": "image/jpeg", 
          "secret": "GpfYIQ5ZicLXMbX34Gsw3usQWQw3T1oy", 
          "width": 320
        }, 
        "k": {
          "extension": "jpg", 
          "height": 1365, 
          "mimetype": "image/jpeg", 
          "secret": "GpfYIQ5ZicLXMbX34Gsw3usQWQw3T1oy", 
          "width": 2048
        }, 
        "n": {
          "extension": "jpg", 
          "height": 213, 
          "mimetype": "image/jpeg", 
          "secret": "GpfYIQ5ZicLXMbX34Gsw3usQWQw3T1oy", 
          "width": 320
        }, 
        "o": {
          "extension": "jpg", 
          "height": 2401, 
          "mimetype": "image/jpeg", 
          "secret": "QGOH4n37RhC8jMY9GeWMExNZfBSW1wop", 
          "width": 3600
        }, 
        "s": {
          "extension": "jpg", 
          "height": 320, 
          "mimetype": "image/jpeg", 
          "secret": "GpfYIQ5ZicLXMbX34Gsw3usQWQw3T1oy", 
          "width": 320
        }, 
        "z": {
          "extension": "jpg", 
          "height": 426, 
          "mimetype": "image/jpeg", 
          "secret": "GpfYIQ5ZicLXMbX34Gsw3usQWQw3T1oy", 
          "width": 640
        }
      }
    }, 
    "sfomuseum:placetype": "image", 
    "wof:depicts": [1159160359, 1159396159, 1159396333, 102527513, 1360516283], 
    "wof:name": "Installation view of \"Souvenirs: Tokens of Travel\"", 
    "wof:placetype": "media" 
  }, 
  "geometry": {"coordinates":[-122.389725,37.616594],"type":"Point"}
}
