{
  "type": "Feature",
  "properties": {
    "date:cessation_lower": "2013-05-20",
    "date:cessation_upper": "2013-05-20",
    "date:inception_lower": "2012-10-26",
    "date:inception_upper": "2012-10-26",
    "iso:country": "US",
    "media:created": 1352160991,
    "media:fingerprint": "196a507ca513f41a68b54d057612bd29ddae52d6",
    "media:imagehash_avg": "a:1c0efcdc0e87c7ef",
    "media:imagehash_diff": "d:e8dcdc5c1c3d1f8f",
    "media:medium": "image",
    "media:mimetype": "image/jpeg",
    "media:properties": {
      "colours": [
        {
          "hex": "#5c759d",
          "name": "#5c759d",
          "reference": "vibrant"
        },
        {
          "hex": "#c3b6a1",
          "name": "#c3b6a1",
          "reference": "vibrant"
        },
        {
          "hex": "#483d32",
          "name": "#483d32",
          "reference": "vibrant"
        }
      ],
      "depicts": [
        1159160347
      ],
      "sizes": {
        "b": {
          "extension": "jpg",
          "height": 768,
          "mimetype": "image/jpeg",
          "secret": "Jvf38Glo3BQxTjepoHkn4oZxLUJ6LDml",
          "width": 512
        },
        "c": {
          "extension": "jpg",
          "height": 600,
          "mimetype": "image/jpeg",
          "secret": "Jvf38Glo3BQxTjepoHkn4oZxLUJ6LDml",
          "width": 400
        },
        "dc": {
          "extension": "jpg",
          "height": 600,
          "mimetype": "image/jpeg",
          "secret": "Jvf38Glo3BQxTjepoHkn4oZxLUJ6LDml",
          "width": 400
        },
        "ds": {
          "extension": "jpg",
          "height": 320,
          "mimetype": "image/jpeg",
          "secret": "Jvf38Glo3BQxTjepoHkn4oZxLUJ6LDml",
          "width": 320
        },
        "k": {
          "extension": "jpg",
          "height": 1536,
          "mimetype": "image/jpeg",
          "secret": "Jvf38Glo3BQxTjepoHkn4oZxLUJ6LDml",
          "width": 1024
        },
        "n": {
          "extension": "jpg",
          "height": 240,
          "mimetype": "image/jpeg",
          "secret": "Jvf38Glo3BQxTjepoHkn4oZxLUJ6LDml",
          "width": 160
        },
        "o": {
          "extension": "jpg",
          "height": 3600,
          "mimetype": "image/jpeg",
          "secret": "X6Nk9txgUjdQKFOvJlwoXhbdAj0n2tZJ",
          "width": 2400
        },
        "s": {
          "extension": "jpg",
          "height": 320,
          "mimetype": "image/jpeg",
          "secret": "Jvf38Glo3BQxTjepoHkn4oZxLUJ6LDml",
          "width": 320
        },
        "z": {
          "extension": "jpg",
          "height": 480,
          "mimetype": "image/jpeg",
          "secret": "Jvf38Glo3BQxTjepoHkn4oZxLUJ6LDml",
          "width": 320
        }
      }
    },
    "sfomuseum:placetype": "image",
    "wof:depicts": [
      1159396333,
      1159396109,
      1159160347,
      102527513,
      1159396261,
      1360516259
    ],
    "wof:name": "Installation view of \"Let’s Play! 100 Years of Board Games\"",
    "wof:placetype": "media"
  },
  "geometry": {"coordinates":[-122.382712,37.617422],"type":"Point"}
}
