{
  "type": "Feature", 
  "properties": {
    "iso:country": "US", 
    "media:created": 1270141616, 
    "media:fingerprint": "a054a7fe45d42683ee4979408ce3f40f2c01c45e", 
    "media:medium": "image", 
    "media:mimetype": "image/jpeg", 
    "media:properties": {
      "colours": [
        {
          "hex": "#e0482e", 
          "name": "#e0482e", 
          "reference": "vibrant"
        }, 
        {
          "hex": "#e26042", 
          "name": "#e26042", 
          "reference": "vibrant"
        }, 
        {
          "hex": "#8a2117", 
          "name": "#8a2117", 
          "reference": "vibrant"
        }, 
        {
          "hex": "#9c856e", 
          "name": "#9c856e", 
          "reference": "vibrant"
        }, 
        {
          "hex": "#cebda6", 
          "name": "#cebda6", 
          "reference": "vibrant"
        }
      ], 
      "depicts": [1159160109], 
      "sizes": {
        "b": {
          "extension": "jpg", 
          "height": 768, 
          "mimetype": "image/jpeg", 
          "secret": "a1RP6oVex5nvy2doV5xdNFpP0az1f13i", 
          "width": 514
        }, 
        "c": {
          "extension": "jpg", 
          "height": 600, 
          "mimetype": "image/jpeg", 
          "secret": "a1RP6oVex5nvy2doV5xdNFpP0az1f13i", 
          "width": 401
        }, 
        "dc": {
          "extension": "jpg", 
          "height": 600, 
          "mimetype": "image/jpeg", 
          "secret": "a1RP6oVex5nvy2doV5xdNFpP0az1f13i", 
          "width": 401
        }, 
        "ds": {
          "extension": "jpg", 
          "height": 320, 
          "mimetype": "image/jpeg", 
          "secret": "a1RP6oVex5nvy2doV5xdNFpP0az1f13i", 
          "width": 320
        }, 
        "k": {
          "extension": "jpg", 
          "height": 1536, 
          "mimetype": "image/jpeg", 
          "secret": "a1RP6oVex5nvy2doV5xdNFpP0az1f13i", 
          "width": 1028
        }, 
        "n": {
          "extension": "jpg", 
          "height": 240, 
          "mimetype": "image/jpeg", 
          "secret": "a1RP6oVex5nvy2doV5xdNFpP0az1f13i", 
          "width": 160
        }, 
        "o": {
          "extension": "jpg", 
          "height": 3872, 
          "mimetype": "image/jpeg", 
          "secret": "FNAlp8HNuSzANrwKqvOCbqb0Jw86JhJa", 
          "width": 2592
        }, 
        "s": {
          "extension": "jpg", 
          "height": 320, 
          "mimetype": "image/jpeg", 
          "secret": "a1RP6oVex5nvy2doV5xdNFpP0az1f13i", 
          "width": 320
        }, 
        "z": {
          "extension": "jpg", 
          "height": 480, 
          "mimetype": "image/jpeg", 
          "secret": "a1RP6oVex5nvy2doV5xdNFpP0az1f13i", 
          "width": 321
        }
      }
    }, 
    "sfomuseum:placetype": "image", 
    "wof:depicts": [
      1159396337, 
      1360521569, 
      1159160109, 
      1360541661, 
      102527513, 
      1159396147
    ], 
    "wof:name": "Installation view of \"Japan Airlines: Over Fifty-Five Years of Service\"", 
    "wof:placetype": "media" 
  }, 
  "geometry": {"coordinates":[-122.387989,37.614385],"type":"Point"}
}
