{
  "type": "Feature", 
  "properties": {
    "iso:country": "US", 
    "media:created": -1, 
    "media:fingerprint": "70757aa14b73c5e0a6271ebc085c7e0ed29bdff7", 
    "media:medium": "image", 
    "media:mimetype": "image/tiff", 
    "media:properties": {
      "colours": [
        {
          "hex": "#642d23", 
          "name": "#642d23", 
          "reference": "vibrant"
        }, 
        {
          "hex": "#878177", 
          "name": "#878177", 
          "reference": "vibrant"
        }, 
        {
          "hex": "#c6bcb3", 
          "name": "#c6bcb3", 
          "reference": "vibrant"
        }, 
        {
          "hex": "#624f34", 
          "name": "#624f34", 
          "reference": "vibrant"
        }
      ], 
      "depicts": [1226611157], 
      "sizes": {
        "b": {
          "extension": "jpg", 
          "height": 726, 
          "mimetype": "image/jpeg", 
          "secret": "WzCvD4un6pinL64FU8S35zcBxNoxOUit", 
          "width": 1024
        }, 
        "c": {
          "extension": "jpg", 
          "height": 567, 
          "mimetype": "image/jpeg", 
          "secret": "WzCvD4un6pinL64FU8S35zcBxNoxOUit", 
          "width": 800
        }, 
        "dc": {
          "extension": "jpg", 
          "height": 567, 
          "mimetype": "image/jpeg", 
          "secret": "WzCvD4un6pinL64FU8S35zcBxNoxOUit", 
          "width": 800
        }, 
        "ds": {
          "extension": "jpg", 
          "height": 320, 
          "mimetype": "image/jpeg", 
          "secret": "WzCvD4un6pinL64FU8S35zcBxNoxOUit", 
          "width": 320
        }, 
        "k": {
          "extension": "jpg", 
          "height": 1452, 
          "mimetype": "image/jpeg", 
          "secret": "WzCvD4un6pinL64FU8S35zcBxNoxOUit", 
          "width": 2048
        }, 
        "n": {
          "extension": "jpg", 
          "height": 226, 
          "mimetype": "image/jpeg", 
          "secret": "WzCvD4un6pinL64FU8S35zcBxNoxOUit", 
          "width": 320
        }, 
        "o": {
          "extension": "jpg", 
          "height": 3014, 
          "mimetype": "image/jpeg", 
          "secret": "AVBOVOcwhpL8jMJqgRC01OIAa7i8Caty", 
          "width": 4251
        }, 
        "s": {
          "extension": "jpg", 
          "height": 320, 
          "mimetype": "image/jpeg", 
          "secret": "WzCvD4un6pinL64FU8S35zcBxNoxOUit", 
          "width": 320
        }, 
        "z": {
          "extension": "jpg", 
          "height": 453, 
          "mimetype": "image/jpeg", 
          "secret": "WzCvD4un6pinL64FU8S35zcBxNoxOUit", 
          "width": 640
        }
      }
    }, 
    "sfomuseum:placetype": "image", 
    "wof:depicts": [
      1226611157, 
      1159554803, 
      102527513, 
      1159554821, 
      1159554855, 
      1360516127
    ], 
    "wof:name": "Installation view of \"Boomerang\"", 
    "wof:placetype": "media" 
  }, 
  "geometry": {"coordinates":[-122.387197,37.619087],"type":"Point"}
}
