{
  "type": "Feature",
  "properties": {
    "iso:country": "US",
    "media:created": 1093628031,
    "media:fingerprint": "e832532e4214377ce7594eb88f2222a918a4df2c",
    "media:imagehash_avg": "a:272767a5a521063e",
    "media:imagehash_diff": "d:cf4e4d4d4dcdecec",
    "media:medium": "image",
    "media:mimetype": "image/jpeg",
    "media:properties": {
      "colours": [
        {
          "hex": "#51b2ad",
          "name": "#51b2ad",
          "reference": "vibrant"
        }, 
        {
          "hex": "#7c2123",
          "name": "#7c2123",
          "reference": "vibrant"
        }, 
        {
          "hex": "#51938c",
          "name": "#51938c",
          "reference": "vibrant"
        }, 
        {
          "hex": "#a5c7c4",
          "name": "#a5c7c4",
          "reference": "vibrant"
        }, 
        {
          "hex": "#3e342d",
          "name": "#3e342d",
          "reference": "vibrant"
        }
      ],
      "depicts": [
        1159159593
      ],
      "sizes": {
        "b": {
          "extension": "jpg",
          "height": 768,
          "mimetype": "image/jpeg",
          "secret": "dLzv2IehcfFjdGXWrTPKAsAg31SsW7E8",
          "width": 1024
        },
        "c": {
          "extension": "jpg",
          "height": 600,
          "mimetype": "image/jpeg",
          "secret": "dLzv2IehcfFjdGXWrTPKAsAg31SsW7E8",
          "width": 800
        },
        "dc": {
          "extension": "jpg",
          "height": 600,
          "mimetype": "image/jpeg",
          "secret": "dLzv2IehcfFjdGXWrTPKAsAg31SsW7E8",
          "width": 800
        },
        "ds": {
          "extension": "jpg",
          "height": 320,
          "mimetype": "image/jpeg",
          "secret": "dLzv2IehcfFjdGXWrTPKAsAg31SsW7E8",
          "width": 320
        },
        "k": {
          "extension": "jpg",
          "height": 1536,
          "mimetype": "image/jpeg",
          "secret": "dLzv2IehcfFjdGXWrTPKAsAg31SsW7E8",
          "width": 2048
        },
        "n": {
          "extension": "jpg",
          "height": 240,
          "mimetype": "image/jpeg",
          "secret": "dLzv2IehcfFjdGXWrTPKAsAg31SsW7E8",
          "width": 320
        },
        "o": {
          "extension": "jpg",
          "height": 1920,
          "mimetype": "image/jpeg",
          "secret": "1OutXfWsxjLZmoDL9Bt6FDFdYUAktmsz",
          "width": 2560
        },
        "s": {
          "extension": "jpg",
          "height": 320,
          "mimetype": "image/jpeg",
          "secret": "dLzv2IehcfFjdGXWrTPKAsAg31SsW7E8",
          "width": 320
        },
        "z": {
          "extension": "jpg",
          "height": 480,
          "mimetype": "image/jpeg",
          "secret": "dLzv2IehcfFjdGXWrTPKAsAg31SsW7E8",
          "width": 640
        }
      }
    },
    "sfomuseum:placetype": "image",
    "wof:depicts": [
      1159396115, 
      102527513, 
      1360516477, 
      1159159593, 
      1159396319
    ],
    "wof:name": "Installation view of \"The Flight Bag: Icon of Air Travel\"",
    "wof:placetype": "media"
  },
  "geometry": {"coordinates":[-122.385472,37.613926],"type":"Point"}
}
