{
  "type": "Feature", 
  "properties": {
    "iso:country": "US", 
    "media:created": 1270142291, 
    "media:fingerprint": "47ac5eab547a725e94aadfac401dcedfb43f401c", 
    "media:medium": "image", 
    "media:mimetype": "image/jpeg", 
    "media:properties": {
      "colours": [
        {
          "hex": "#e43d16", 
          "name": "#e43d16", 
          "reference": "vibrant"
        }, 
        {
          "hex": "#dbcba6", 
          "name": "#dbcba6", 
          "reference": "vibrant"
        }, 
        {
          "hex": "#7d4813", 
          "name": "#7d4813", 
          "reference": "vibrant"
        }, 
        {
          "hex": "#ac7b57", 
          "name": "#ac7b57", 
          "reference": "vibrant"
        }, 
        {
          "hex": "#c8b488", 
          "name": "#c8b488", 
          "reference": "vibrant"
        }
      ], 
      "depicts": [1159160109], 
      "sizes": {
        "b": {
          "extension": "jpg", 
          "height": 768, 
          "mimetype": "image/jpeg", 
          "secret": "9KfB93Z2p4BUpMZVJV3sv3uK2ln84HoT", 
          "width": 514
        }, 
        "c": {
          "extension": "jpg", 
          "height": 600, 
          "mimetype": "image/jpeg", 
          "secret": "9KfB93Z2p4BUpMZVJV3sv3uK2ln84HoT", 
          "width": 401
        }, 
        "dc": {
          "extension": "jpg", 
          "height": 600, 
          "mimetype": "image/jpeg", 
          "secret": "9KfB93Z2p4BUpMZVJV3sv3uK2ln84HoT", 
          "width": 401
        }, 
        "ds": {
          "extension": "jpg", 
          "height": 320, 
          "mimetype": "image/jpeg", 
          "secret": "9KfB93Z2p4BUpMZVJV3sv3uK2ln84HoT", 
          "width": 320
        }, 
        "k": {
          "extension": "jpg", 
          "height": 1536, 
          "mimetype": "image/jpeg", 
          "secret": "9KfB93Z2p4BUpMZVJV3sv3uK2ln84HoT", 
          "width": 1028
        }, 
        "n": {
          "extension": "jpg", 
          "height": 240, 
          "mimetype": "image/jpeg", 
          "secret": "9KfB93Z2p4BUpMZVJV3sv3uK2ln84HoT", 
          "width": 160
        }, 
        "o": {
          "extension": "jpg", 
          "height": 3872, 
          "mimetype": "image/jpeg", 
          "secret": "Sam3zTNVj1bXCOVG5iZquG7IlLD1Gosy", 
          "width": 2592
        }, 
        "s": {
          "extension": "jpg", 
          "height": 320, 
          "mimetype": "image/jpeg", 
          "secret": "9KfB93Z2p4BUpMZVJV3sv3uK2ln84HoT", 
          "width": 320
        }, 
        "z": {
          "extension": "jpg", 
          "height": 480, 
          "mimetype": "image/jpeg", 
          "secret": "9KfB93Z2p4BUpMZVJV3sv3uK2ln84HoT", 
          "width": 321
        }
      }
    }, 
    "sfomuseum:placetype": "image", 
    "wof:depicts": [
      1360521569, 
      1159396337, 
      1159160109, 
      102527513, 
      1360541661, 
      1159396147
    ], 
    "wof:name": "Installation view of \"Japan Airlines: Over Fifty-Five Years of Service\"", 
    "wof:placetype": "media" 
  }, 
  "geometry": {"coordinates":[-122.387989,37.614385],"type":"Point"}
}
