{
  "type": "Feature", 
  "properties": {
    "iso:country": "US", 
    "media:created": 1383779772, 
    "media:fingerprint": "e121534a7d1e04f0d5e40af8658d93239e14eca5", 
    "media:medium": "image", 
    "media:mimetype": "image/jpeg", 
    "media:properties": {
      "colours": [
        {
          "hex": "#eada51", 
          "name": "#eada51", 
          "reference": "vibrant"
        }, 
        {
          "hex": "#ac9864", 
          "name": "#ac9864", 
          "reference": "vibrant"
        }, 
        {
          "hex": "#acb2c6", 
          "name": "#acb2c6", 
          "reference": "vibrant"
        }, 
        {
          "hex": "#3c3e4b", 
          "name": "#3c3e4b", 
          "reference": "vibrant"
        }
      ], 
      "depicts": [1159160369], 
      "sizes": {
        "b": {
          "extension": "jpg", 
          "height": 682, 
          "mimetype": "image/jpeg", 
          "secret": "aosY5idqaHAGITFil8WMsvbXRabNy62e", 
          "width": 1024
        }, 
        "c": {
          "extension": "jpg", 
          "height": 533, 
          "mimetype": "image/jpeg", 
          "secret": "aosY5idqaHAGITFil8WMsvbXRabNy62e", 
          "width": 800
        }, 
        "dc": {
          "extension": "jpg", 
          "height": 533, 
          "mimetype": "image/jpeg", 
          "secret": "aosY5idqaHAGITFil8WMsvbXRabNy62e", 
          "width": 800
        }, 
        "ds": {
          "extension": "jpg", 
          "height": 320, 
          "mimetype": "image/jpeg", 
          "secret": "aosY5idqaHAGITFil8WMsvbXRabNy62e", 
          "width": 320
        }, 
        "k": {
          "extension": "jpg", 
          "height": 1365, 
          "mimetype": "image/jpeg", 
          "secret": "aosY5idqaHAGITFil8WMsvbXRabNy62e", 
          "width": 2048
        }, 
        "n": {
          "extension": "jpg", 
          "height": 213, 
          "mimetype": "image/jpeg", 
          "secret": "aosY5idqaHAGITFil8WMsvbXRabNy62e", 
          "width": 320
        }, 
        "o": {
          "extension": "jpg", 
          "height": 2400, 
          "mimetype": "image/jpeg", 
          "secret": "w3mC0QNLwE9v1J3KY5YMsN0zE5B7LCkh", 
          "width": 3600
        }, 
        "s": {
          "extension": "jpg", 
          "height": 320, 
          "mimetype": "image/jpeg", 
          "secret": "aosY5idqaHAGITFil8WMsvbXRabNy62e", 
          "width": 320
        }, 
        "z": {
          "extension": "jpg", 
          "height": 426, 
          "mimetype": "image/jpeg", 
          "secret": "aosY5idqaHAGITFil8WMsvbXRabNy62e", 
          "width": 640
        }
      }
    }, 
    "sfomuseum:placetype": "image", 
    "wof:depicts": [
      1159396295, 
      1159396333, 
      1159160369, 
      1159396141, 
      1360516121, 
      102527513
    ], 
    "wof:name": "Installation view of \"Japanese Toys! From Kokeshi to Kaiju\"", 
    "wof:placetype": "media" 
  }, 
  "geometry": {"coordinates":[-122.387197,37.619087],"type":"Point"}
}
