{
  "type": "Feature",
  "properties": {
    "iso:country": "US",
    "media:created": 1374514430,
    "media:fingerprint": "f9b9534a135317b3d36c90cd3954f25fc63ef316",
    "media:imagehash_avg": "a:0effff0e0101837f",
    "media:imagehash_diff": "d:7c783cb2373f1bd0",
    "media:medium": "image",
    "media:mimetype": "image/jpeg",
    "media:properties": {
      "colours": [
        {
          "hex": "#b07f45",
          "name": "#b07f45",
          "reference": "vibrant"
        }, 
        {
          "hex": "#8a541f",
          "name": "#8a541f",
          "reference": "vibrant"
        }, 
        {
          "hex": "#8e826f",
          "name": "#8e826f",
          "reference": "vibrant"
        }, 
        {
          "hex": "#bcc3c2",
          "name": "#bcc3c2",
          "reference": "vibrant"
        }, 
        {
          "hex": "#474238",
          "name": "#474238",
          "reference": "vibrant"
        }
      ],
      "depicts": [
        1159160455
      ],
      "sizes": {
        "b": {
          "extension": "jpg",
          "height": 768,
          "mimetype": "image/jpeg",
          "secret": "qNZ3fnfpwoL9e2pSsyfcaAC9HE2NBW1O",
          "width": 553
        },
        "c": {
          "extension": "jpg",
          "height": 600,
          "mimetype": "image/jpeg",
          "secret": "qNZ3fnfpwoL9e2pSsyfcaAC9HE2NBW1O",
          "width": 432
        },
        "dc": {
          "extension": "jpg",
          "height": 600,
          "mimetype": "image/jpeg",
          "secret": "qNZ3fnfpwoL9e2pSsyfcaAC9HE2NBW1O",
          "width": 432
        },
        "ds": {
          "extension": "jpg",
          "height": 320,
          "mimetype": "image/jpeg",
          "secret": "qNZ3fnfpwoL9e2pSsyfcaAC9HE2NBW1O",
          "width": 320
        },
        "k": {
          "extension": "jpg",
          "height": 1536,
          "mimetype": "image/jpeg",
          "secret": "qNZ3fnfpwoL9e2pSsyfcaAC9HE2NBW1O",
          "width": 1107
        },
        "n": {
          "extension": "jpg",
          "height": 240,
          "mimetype": "image/jpeg",
          "secret": "qNZ3fnfpwoL9e2pSsyfcaAC9HE2NBW1O",
          "width": 173
        },
        "o": {
          "extension": "jpg",
          "height": 3600,
          "mimetype": "image/jpeg",
          "secret": "rsXHpz1vrglLaOxnLPi9pjdDBdl3E8ec",
          "width": 2596
        },
        "s": {
          "extension": "jpg",
          "height": 320,
          "mimetype": "image/jpeg",
          "secret": "qNZ3fnfpwoL9e2pSsyfcaAC9HE2NBW1O",
          "width": 320
        },
        "z": {
          "extension": "jpg",
          "height": 480,
          "mimetype": "image/jpeg",
          "secret": "qNZ3fnfpwoL9e2pSsyfcaAC9HE2NBW1O",
          "width": 346
        }
      }
    },
    "sfomuseum:placetype": "image",
    "wof:depicts": [
      1159396159, 
      102527513, 
      1159160455, 
      1159396333, 
      1360516273
    ],
    "wof:name": "Installation view of \"Classic Plastics: 1870s-1970s\"",
    "wof:placetype": "media"
  },
  "geometry": {"coordinates":[-122.38902,37.614533],"type":"Point"}
}
