{
  "type": "Feature",
  "properties": {
    "date:cessation_lower": "1985-03-14",
    "date:cessation_upper": "1985-03-14",
    "date:inception_lower": "1984-11-30",
    "date:inception_upper": "1984-11-30",
    "iso:country": "US",
    "media:created": -1,
    "media:fingerprint": "d41480753becb58f9b4826970aa0669bada73b7c",
    "media:imagehash_avg": "a:7efedae2e2f63e00",
    "media:imagehash_diff": "d:a0b0928e86aefce0",
    "media:medium": "image",
    "media:mimetype": "image/tiff",
    "media:placetype": "installation",
    "media:properties": {
      "colours": [
        {
          "hex": "#daf1e9",
          "name": "#daf1e9",
          "reference": "vibrant"
        },
        {
          "hex": "#9e7a71",
          "name": "#9e7a71",
          "reference": "vibrant"
        },
        {
          "hex": "#cabea9",
          "name": "#cabea9",
          "reference": "vibrant"
        },
        {
          "hex": "#433b40",
          "name": "#433b40",
          "reference": "vibrant"
        }
      ],
      "depicts": [
        1226617941
      ],
      "sizes": {
        "b": {
          "extension": "jpg",
          "height": 726,
          "mimetype": "image/jpeg",
          "secret": "VE6JEVGpflgLhZoI8Z3m0zvfwLasHm6Q",
          "width": 1024
        },
        "c": {
          "extension": "jpg",
          "height": 567,
          "mimetype": "image/jpeg",
          "secret": "VE6JEVGpflgLhZoI8Z3m0zvfwLasHm6Q",
          "width": 800
        },
        "dc": {
          "extension": "jpg",
          "height": 567,
          "mimetype": "image/jpeg",
          "secret": "VE6JEVGpflgLhZoI8Z3m0zvfwLasHm6Q",
          "width": 800
        },
        "ds": {
          "extension": "jpg",
          "height": 320,
          "mimetype": "image/jpeg",
          "secret": "VE6JEVGpflgLhZoI8Z3m0zvfwLasHm6Q",
          "width": 320
        },
        "k": {
          "extension": "jpg",
          "height": 1452,
          "mimetype": "image/jpeg",
          "secret": "VE6JEVGpflgLhZoI8Z3m0zvfwLasHm6Q",
          "width": 2048
        },
        "n": {
          "extension": "jpg",
          "height": 226,
          "mimetype": "image/jpeg",
          "secret": "VE6JEVGpflgLhZoI8Z3m0zvfwLasHm6Q",
          "width": 320
        },
        "o": {
          "extension": "jpg",
          "height": 3014,
          "mimetype": "image/jpeg",
          "secret": "D8sA2ibJWITKLHq8iMSDN5I0grWbUv4u",
          "width": 4251
        },
        "s": {
          "extension": "jpg",
          "height": 320,
          "mimetype": "image/jpeg",
          "secret": "VE6JEVGpflgLhZoI8Z3m0zvfwLasHm6Q",
          "width": 320
        },
        "z": {
          "extension": "jpg",
          "height": 453,
          "mimetype": "image/jpeg",
          "secret": "VE6JEVGpflgLhZoI8Z3m0zvfwLasHm6Q",
          "width": 640
        }
      }
    },
    "sfomuseum:placetype": "image",
    "wof:depicts": [
      1159554801,
      102527513,
      1159554841,
      1360516129,
      1226617941,
      1159554819
    ],
    "wof:name": "Installation view of \"Art and Travel\"",
    "wof:placetype": "custom",
    "wof:placetype_alt": [
      "image"
    ]
  },
  "geometry": {"type":"Point","coordinates":[-122.387197,37.619087]}
}
