{
  "type": "Feature", 
  "properties": {
    "iso:country": "US", 
    "media:created": 1503686287, 
    "media:fingerprint": "a599f61a438bbb7444187f040fbf5b869abbb84d", 
    "media:medium": "image", 
    "media:mimetype": "image/jpeg", 
    "media:properties": {
      "colours": [
        {
          "hex": "#c25f3e", 
          "name": "#c25f3e", 
          "reference": "vibrant"
        }, 
        {
          "hex": "#d57594", 
          "name": "#d57594", 
          "reference": "vibrant"
        }, 
        {
          "hex": "#6f2c26", 
          "name": "#6f2c26", 
          "reference": "vibrant"
        }, 
        {
          "hex": "#517da1", 
          "name": "#517da1", 
          "reference": "vibrant"
        }, 
        {
          "hex": "#d9c5b5", 
          "name": "#d9c5b5", 
          "reference": "vibrant"
        }
      ], 
      "depicts": [1159160631], 
      "sizes": {
        "b": {
          "extension": "jpg", 
          "height": 682, 
          "mimetype": "image/jpeg", 
          "secret": "7XmuoBNFjIkQS36rTgxHWIG0IWAoMX7Y", 
          "width": 1024
        }, 
        "c": {
          "extension": "jpg", 
          "height": 533, 
          "mimetype": "image/jpeg", 
          "secret": "7XmuoBNFjIkQS36rTgxHWIG0IWAoMX7Y", 
          "width": 800
        }, 
        "dc": {
          "extension": "jpg", 
          "height": 533, 
          "mimetype": "image/jpeg", 
          "secret": "7XmuoBNFjIkQS36rTgxHWIG0IWAoMX7Y", 
          "width": 800
        }, 
        "ds": {
          "extension": "jpg", 
          "height": 320, 
          "mimetype": "image/jpeg", 
          "secret": "7XmuoBNFjIkQS36rTgxHWIG0IWAoMX7Y", 
          "width": 320
        }, 
        "k": {
          "extension": "jpg", 
          "height": 1365, 
          "mimetype": "image/jpeg", 
          "secret": "7XmuoBNFjIkQS36rTgxHWIG0IWAoMX7Y", 
          "width": 2048
        }, 
        "n": {
          "extension": "jpg", 
          "height": 213, 
          "mimetype": "image/jpeg", 
          "secret": "7XmuoBNFjIkQS36rTgxHWIG0IWAoMX7Y", 
          "width": 320
        }, 
        "o": {
          "extension": "jpg", 
          "height": 2400, 
          "mimetype": "image/jpeg", 
          "secret": "9eaLsctOnauYpZPHpgvJYcSRxCOx4MDN", 
          "width": 3600
        }, 
        "s": {
          "extension": "jpg", 
          "height": 320, 
          "mimetype": "image/jpeg", 
          "secret": "7XmuoBNFjIkQS36rTgxHWIG0IWAoMX7Y", 
          "width": 320
        }, 
        "z": {
          "extension": "jpg", 
          "height": 426, 
          "mimetype": "image/jpeg", 
          "secret": "7XmuoBNFjIkQS36rTgxHWIG0IWAoMX7Y", 
          "width": 640
        }
      }
    }, 
    "sfomuseum:placetype": "image", 
    "wof:depicts": [
      1159160631, 
      1159157045, 
      1159157271, 
      102527513, 
      1159157333, 
      1159157047, 
      1159157335
    ], 
    "wof:name": "Installation view of \"Empowering Threads: Textiles of Jolom Mayaetik\"", 
    "wof:placetype": "media" 
  }, 
  "geometry": {"coordinates":[-122.389131,37.616029],"type":"Point"}
}
