{
  "type": "Feature", 
  "properties": {
    "iso:country": "US", 
    "media:created": 1479238789, 
    "media:fingerprint": "9fddce8ec42d236d54fec5a040b0e6b6cc4e90df", 
    "media:medium": "image", 
    "media:mimetype": "image/jpeg", 
    "media:properties": {
      "colours": [
        {
          "hex": "#2a8acd", 
          "name": "#2a8acd", 
          "reference": "vibrant"
        }, 
        {
          "hex": "#e7be88", 
          "name": "#e7be88", 
          "reference": "vibrant"
        }, 
        {
          "hex": "#304766", 
          "name": "#304766", 
          "reference": "vibrant"
        }, 
        {
          "hex": "#877158", 
          "name": "#877158", 
          "reference": "vibrant"
        }, 
        {
          "hex": "#ccb39f", 
          "name": "#ccb39f", 
          "reference": "vibrant"
        }
      ], 
      "depicts": [1226619799], 
      "sizes": {
        "b": {
          "extension": "jpg", 
          "height": 768, 
          "mimetype": "image/jpeg", 
          "secret": "iKkzvO2QqAs6m5qEaufWcm98oTqkDXJR", 
          "width": 500
        }, 
        "c": {
          "extension": "jpg", 
          "height": 600, 
          "mimetype": "image/jpeg", 
          "secret": "iKkzvO2QqAs6m5qEaufWcm98oTqkDXJR", 
          "width": 391
        }, 
        "dc": {
          "extension": "jpg", 
          "height": 600, 
          "mimetype": "image/jpeg", 
          "secret": "iKkzvO2QqAs6m5qEaufWcm98oTqkDXJR", 
          "width": 391
        }, 
        "ds": {
          "extension": "jpg", 
          "height": 320, 
          "mimetype": "image/jpeg", 
          "secret": "iKkzvO2QqAs6m5qEaufWcm98oTqkDXJR", 
          "width": 320
        }, 
        "k": {
          "extension": "jpg", 
          "height": 1536, 
          "mimetype": "image/jpeg", 
          "secret": "iKkzvO2QqAs6m5qEaufWcm98oTqkDXJR", 
          "width": 1000
        }, 
        "n": {
          "extension": "jpg", 
          "height": 240, 
          "mimetype": "image/jpeg", 
          "secret": "iKkzvO2QqAs6m5qEaufWcm98oTqkDXJR", 
          "width": 156
        }, 
        "o": {
          "extension": "jpg", 
          "height": 3600, 
          "mimetype": "image/jpeg", 
          "secret": "Qi4JSyTRgumPfNPJtcIUZkqD9ZtPDvOF", 
          "width": 2346
        }, 
        "s": {
          "extension": "jpg", 
          "height": 320, 
          "mimetype": "image/jpeg", 
          "secret": "iKkzvO2QqAs6m5qEaufWcm98oTqkDXJR", 
          "width": 320
        }, 
        "z": {
          "extension": "jpg", 
          "height": 480, 
          "mimetype": "image/jpeg", 
          "secret": "iKkzvO2QqAs6m5qEaufWcm98oTqkDXJR", 
          "width": 312
        }
      }
    }, 
    "sfomuseum:placetype": "image", 
    "wof:depicts": [
      102527513, 
      1159396193, 
      1360516255, 
      1159396321, 
      1226619799, 
      1159157325
    ], 
    "wof:name": "Installation view of \"The Mysterious Talking Board: Ouija and Beyond\"", 
    "wof:placetype": "media" 
  }, 
  "geometry": {"coordinates":[-122.382712,37.617422],"type":"Point"}
}
