{
  "type": "Feature",
  "properties": {
    "date:cessation_lower": "1991-06-30",
    "date:cessation_upper": "1991-06-30",
    "date:inception_lower": "1991-05-01",
    "date:inception_upper": "1991-05-01",
    "iso:country": "US",
    "media:created": -1,
    "media:fingerprint": "3265b2983406e3f0ba67be460f3ae47fc86c15d7",
    "media:imagehash_avg": "a:46cfeeca7e7e0200",
    "media:imagehash_diff": "d:969e9c9a9ac8ce86",
    "media:medium": "image",
    "media:mimetype": "image/tiff",
    "media:properties": {
      "colours": [
        {
          "hex": "#d0e7f2",
          "name": "#d0e7f2",
          "reference": "vibrant"
        },
        {
          "hex": "#937b75",
          "name": "#937b75",
          "reference": "vibrant"
        },
        {
          "hex": "#a8b7cf",
          "name": "#a8b7cf",
          "reference": "vibrant"
        },
        {
          "hex": "#3a252d",
          "name": "#3a252d",
          "reference": "vibrant"
        }
      ],
      "depicts": [
        1226607773
      ],
      "sizes": {
        "b": {
          "extension": "jpg",
          "height": 768,
          "mimetype": "image/jpeg",
          "secret": "CIoSYyabS0mSkImjPIdqaRtSjDBav4l9",
          "width": 544
        },
        "c": {
          "extension": "jpg",
          "height": 600,
          "mimetype": "image/jpeg",
          "secret": "CIoSYyabS0mSkImjPIdqaRtSjDBav4l9",
          "width": 425
        },
        "dc": {
          "extension": "jpg",
          "height": 600,
          "mimetype": "image/jpeg",
          "secret": "CIoSYyabS0mSkImjPIdqaRtSjDBav4l9",
          "width": 425
        },
        "ds": {
          "extension": "jpg",
          "height": 320,
          "mimetype": "image/jpeg",
          "secret": "CIoSYyabS0mSkImjPIdqaRtSjDBav4l9",
          "width": 320
        },
        "k": {
          "extension": "jpg",
          "height": 1536,
          "mimetype": "image/jpeg",
          "secret": "CIoSYyabS0mSkImjPIdqaRtSjDBav4l9",
          "width": 1089
        },
        "n": {
          "extension": "jpg",
          "height": 240,
          "mimetype": "image/jpeg",
          "secret": "CIoSYyabS0mSkImjPIdqaRtSjDBav4l9",
          "width": 170
        },
        "o": {
          "extension": "jpg",
          "height": 4251,
          "mimetype": "image/jpeg",
          "secret": "AoQqVibCLZNyOHzCBm69BVsAs9mwsaUH",
          "width": 3014
        },
        "s": {
          "extension": "jpg",
          "height": 320,
          "mimetype": "image/jpeg",
          "secret": "CIoSYyabS0mSkImjPIdqaRtSjDBav4l9",
          "width": 320
        },
        "z": {
          "extension": "jpg",
          "height": 480,
          "mimetype": "image/jpeg",
          "secret": "CIoSYyabS0mSkImjPIdqaRtSjDBav4l9",
          "width": 340
        }
      }
    },
    "sfomuseum:placetype": "image",
    "wof:depicts": [
      1360516471,
      102527513,
      1159554829,
      1226607773,
      1159554803
    ],
    "wof:name": "Installation view of \"Bowling: A Unique American Art Form\"",
    "wof:placetype": "media"
  },
  "geometry": {"coordinates":[-122.38274,37.617227],"type":"Point"}
}
