{
  "type": "Feature", 
  "properties": {
    "iso:country": "US", 
    "media:created": -1, 
    "media:fingerprint": "ac07cfdd916280527c415ccc5ba09621425f44f4", 
    "media:medium": "image", 
    "media:mimetype": "image/tiff", 
    "media:properties": {
      "colours": [
        {
          "hex": "#77272a", 
          "name": "#77272a", 
          "reference": "vibrant"
        }, 
        {
          "hex": "#927570", 
          "name": "#927570", 
          "reference": "vibrant"
        }, 
        {
          "hex": "#cdc2b4", 
          "name": "#cdc2b4", 
          "reference": "vibrant"
        }, 
        {
          "hex": "#3e363a", 
          "name": "#3e363a", 
          "reference": "vibrant"
        }
      ], 
      "depicts": [1226612107], 
      "sizes": {
        "b": {
          "extension": "jpg", 
          "height": 724, 
          "mimetype": "image/jpeg", 
          "secret": "uR6U6mv4qI1RED5IhlPsS0vl0gO0XyfS", 
          "width": 1024
        }, 
        "c": {
          "extension": "jpg", 
          "height": 565, 
          "mimetype": "image/jpeg", 
          "secret": "uR6U6mv4qI1RED5IhlPsS0vl0gO0XyfS", 
          "width": 800
        }, 
        "dc": {
          "extension": "jpg", 
          "height": 565, 
          "mimetype": "image/jpeg", 
          "secret": "uR6U6mv4qI1RED5IhlPsS0vl0gO0XyfS", 
          "width": 800
        }, 
        "ds": {
          "extension": "jpg", 
          "height": 320, 
          "mimetype": "image/jpeg", 
          "secret": "uR6U6mv4qI1RED5IhlPsS0vl0gO0XyfS", 
          "width": 320
        }, 
        "k": {
          "extension": "jpg", 
          "height": 1448, 
          "mimetype": "image/jpeg", 
          "secret": "uR6U6mv4qI1RED5IhlPsS0vl0gO0XyfS", 
          "width": 2048
        }, 
        "n": {
          "extension": "jpg", 
          "height": 226, 
          "mimetype": "image/jpeg", 
          "secret": "uR6U6mv4qI1RED5IhlPsS0vl0gO0XyfS", 
          "width": 320
        }, 
        "o": {
          "extension": "jpg", 
          "height": 3014, 
          "mimetype": "image/jpeg", 
          "secret": "2EQaRPu7ujyxw5WCTeAYraAuG0yMzltj", 
          "width": 4262
        }, 
        "s": {
          "extension": "jpg", 
          "height": 320, 
          "mimetype": "image/jpeg", 
          "secret": "uR6U6mv4qI1RED5IhlPsS0vl0gO0XyfS", 
          "width": 320
        }, 
        "z": {
          "extension": "jpg", 
          "height": 452, 
          "mimetype": "image/jpeg", 
          "secret": "uR6U6mv4qI1RED5IhlPsS0vl0gO0XyfS", 
          "width": 640
        }
      }
    }, 
    "sfomuseum:placetype": "image", 
    "wof:depicts": [
      1226612107, 
      1159554819, 
      102527513, 
      1159554841, 
      1360516129, 
      1159554801
    ], 
    "wof:name": "Installation view of \"Airport Cafe\"", 
    "wof:placetype": "media" 
  }, 
  "geometry": {"coordinates":[-122.387197,37.619087],"type":"Point"}
}
