{
  "type": "Feature",
  "properties": {
    "iso:country": "US",
    "media:created": 1545308562,
    "media:fingerprint": "14f73ef415537d0f41beafef7ba18ec7f7fa389c",
    "media:imagehash_avg": "a:70efff1f1c1ce080",
    "media:imagehash_diff": "d:c49fbfb7b0390002",
    "media:medium": "image",
    "media:mimetype": "image/jpeg",
    "media:properties": {
      "colours": [
        {
          "hex": "#8f323f",
          "name": "#8f323f",
          "reference": "vibrant"
        }, 
        {
          "hex": "#898279",
          "name": "#898279",
          "reference": "vibrant"
        }, 
        {
          "hex": "#aabbcc",
          "name": "#aabbcc",
          "reference": "vibrant"
        }, 
        {
          "hex": "#444144",
          "name": "#444144",
          "reference": "vibrant"
        }
      ],
      "depicts": [
        1360702457
      ],
      "sizes": {
        "b": {
          "extension": "jpg",
          "height": 682,
          "mimetype": "image/jpeg",
          "secret": "4rk9p64ep8AG8375lZUwV9x3RBSb0QNa",
          "width": 1024
        },
        "c": {
          "extension": "jpg",
          "height": 533,
          "mimetype": "image/jpeg",
          "secret": "4rk9p64ep8AG8375lZUwV9x3RBSb0QNa",
          "width": 800
        },
        "dc": {
          "extension": "jpg",
          "height": 533,
          "mimetype": "image/jpeg",
          "secret": "4rk9p64ep8AG8375lZUwV9x3RBSb0QNa",
          "width": 800
        },
        "ds": {
          "extension": "jpg",
          "height": 320,
          "mimetype": "image/jpeg",
          "secret": "4rk9p64ep8AG8375lZUwV9x3RBSb0QNa",
          "width": 320
        },
        "k": {
          "extension": "jpg",
          "height": 1365,
          "mimetype": "image/jpeg",
          "secret": "4rk9p64ep8AG8375lZUwV9x3RBSb0QNa",
          "width": 2048
        },
        "n": {
          "extension": "jpg",
          "height": 213,
          "mimetype": "image/jpeg",
          "secret": "4rk9p64ep8AG8375lZUwV9x3RBSb0QNa",
          "width": 320
        },
        "o": {
          "extension": "jpg",
          "height": 2400,
          "mimetype": "image/jpeg",
          "secret": "o0WBPt7xUpZcGPIjykKupV19IAMv5VXW",
          "width": 3600
        },
        "s": {
          "extension": "jpg",
          "height": 320,
          "mimetype": "image/jpeg",
          "secret": "4rk9p64ep8AG8375lZUwV9x3RBSb0QNa",
          "width": 320
        },
        "z": {
          "extension": "jpg",
          "height": 426,
          "mimetype": "image/jpeg",
          "secret": "4rk9p64ep8AG8375lZUwV9x3RBSb0QNa",
          "width": 640
        }
      }
    },
    "sfomuseum:placetype": "image",
    "wof:depicts": [
      102527513, 
      1159396301, 
      1360702457, 
      1159157307, 
      1159157053, 
      1159157271
    ],
    "wof:name": "Installation view of \"The Modern Consumer – 1950s Products and Styles\"",
    "wof:placetype": "media"
  },
  "geometry": {"coordinates":[-122.387197,37.619087],"type":"Point"}
}
