{
  "type": "Feature", 
  "properties": {
    "iso:country": "US", 
    "media:created": -1, 
    "media:fingerprint": "466976b78b70bf103d265efb9fc643a233b6652b", 
    "media:medium": "image", 
    "media:mimetype": "image/tiff", 
    "media:properties": {
      "colours": [
        {
          "hex": "#747b88", 
          "name": "#747b88", 
          "reference": "vibrant"
        }, 
        {
          "hex": "#b1b4c1", 
          "name": "#b1b4c1", 
          "reference": "vibrant"
        }, 
        {
          "hex": "#50332a", 
          "name": "#50332a", 
          "reference": "vibrant"
        }
      ], 
      "depicts": [1226611157], 
      "sizes": {
        "b": {
          "extension": "jpg", 
          "height": 768, 
          "mimetype": "image/jpeg", 
          "secret": "s1XsZQp2NdNQx6pNS6IVOn34Ruh6KlIz", 
          "width": 544
        }, 
        "c": {
          "extension": "jpg", 
          "height": 600, 
          "mimetype": "image/jpeg", 
          "secret": "s1XsZQp2NdNQx6pNS6IVOn34Ruh6KlIz", 
          "width": 425
        }, 
        "dc": {
          "extension": "jpg", 
          "height": 600, 
          "mimetype": "image/jpeg", 
          "secret": "s1XsZQp2NdNQx6pNS6IVOn34Ruh6KlIz", 
          "width": 425
        }, 
        "ds": {
          "extension": "jpg", 
          "height": 320, 
          "mimetype": "image/jpeg", 
          "secret": "s1XsZQp2NdNQx6pNS6IVOn34Ruh6KlIz", 
          "width": 320
        }, 
        "k": {
          "extension": "jpg", 
          "height": 1536, 
          "mimetype": "image/jpeg", 
          "secret": "s1XsZQp2NdNQx6pNS6IVOn34Ruh6KlIz", 
          "width": 1089
        }, 
        "n": {
          "extension": "jpg", 
          "height": 240, 
          "mimetype": "image/jpeg", 
          "secret": "s1XsZQp2NdNQx6pNS6IVOn34Ruh6KlIz", 
          "width": 170
        }, 
        "o": {
          "extension": "jpg", 
          "height": 4251, 
          "mimetype": "image/jpeg", 
          "secret": "XYe2dOZzh92NbuIUvJyWNqjd6xWuJZhu", 
          "width": 3014
        }, 
        "s": {
          "extension": "jpg", 
          "height": 320, 
          "mimetype": "image/jpeg", 
          "secret": "s1XsZQp2NdNQx6pNS6IVOn34Ruh6KlIz", 
          "width": 320
        }, 
        "z": {
          "extension": "jpg", 
          "height": 480, 
          "mimetype": "image/jpeg", 
          "secret": "s1XsZQp2NdNQx6pNS6IVOn34Ruh6KlIz", 
          "width": 340
        }
      }
    }, 
    "sfomuseum:placetype": "image", 
    "wof:depicts": [
      1226611157, 
      102527513, 
      1360516127, 
      1159554803, 
      1159554821, 
      1159554855
    ], 
    "wof:name": "Installation view of \"Boomerang\"", 
    "wof:placetype": "media" 
  }, 
  "geometry": {"coordinates":[-122.387197,37.619087],"type":"Point"}
}
