{
  "type": "Feature",
  "properties": {
    "iso:country": "US",
    "media:created": 1552673716,
    "media:fingerprint": "748149efe09db6e1df7e5a8fa261100740f84b0f",
    "media:imagehash_avg": "a:ff7cff3f0e000000",
    "media:imagehash_diff": "d:0af8f878b8f8f9eb",
    "media:medium": "image",
    "media:mimetype": "image/jpeg",
    "media:properties": {
      "colours": [
        {
          "hex": "#207fd3",
          "name": "#207fd3",
          "reference": "vibrant"
        }, 
        {
          "hex": "#e1d06d",
          "name": "#e1d06d",
          "reference": "vibrant"
        }, 
        {
          "hex": "#054dad",
          "name": "#054dad",
          "reference": "vibrant"
        }, 
        {
          "hex": "#68859c",
          "name": "#68859c",
          "reference": "vibrant"
        }, 
        {
          "hex": "#c6bfba",
          "name": "#c6bfba",
          "reference": "vibrant"
        }
      ],
      "depicts": [
        1377462865
      ],
      "sizes": {
        "b": {
          "extension": "jpg",
          "height": 768,
          "mimetype": "image/jpeg",
          "secret": "6O5buvFbrXsSwrmaGXnT1Ya86u2PIZts",
          "width": 614
        },
        "c": {
          "extension": "jpg",
          "height": 600,
          "mimetype": "image/jpeg",
          "secret": "6O5buvFbrXsSwrmaGXnT1Ya86u2PIZts",
          "width": 479
        },
        "dc": {
          "extension": "jpg",
          "height": 600,
          "mimetype": "image/jpeg",
          "secret": "6O5buvFbrXsSwrmaGXnT1Ya86u2PIZts",
          "width": 479
        },
        "ds": {
          "extension": "jpg",
          "height": 320,
          "mimetype": "image/jpeg",
          "secret": "6O5buvFbrXsSwrmaGXnT1Ya86u2PIZts",
          "width": 320
        },
        "k": {
          "extension": "jpg",
          "height": 1536,
          "mimetype": "image/jpeg",
          "secret": "6O5buvFbrXsSwrmaGXnT1Ya86u2PIZts",
          "width": 1228
        },
        "n": {
          "extension": "jpg",
          "height": 240,
          "mimetype": "image/jpeg",
          "secret": "6O5buvFbrXsSwrmaGXnT1Ya86u2PIZts",
          "width": 191
        },
        "o": {
          "extension": "jpg",
          "height": 3600,
          "mimetype": "image/jpeg",
          "secret": "tu5bgvGnHMWNZzMm7IzwuY1Ml3bZHM7c",
          "width": 2879
        },
        "s": {
          "extension": "jpg",
          "height": 320,
          "mimetype": "image/jpeg",
          "secret": "6O5buvFbrXsSwrmaGXnT1Ya86u2PIZts",
          "width": 320
        },
        "z": {
          "extension": "jpg",
          "height": 480,
          "mimetype": "image/jpeg",
          "secret": "6O5buvFbrXsSwrmaGXnT1Ya86u2PIZts",
          "width": 383
        }
      }
    },
    "sfomuseum:placetype": "image",
    "wof:depicts": [
      1377462865, 
      102527513
    ],
    "wof:name": "Installation view of \"Streamlines: Aerodynamic Consumer Designs for the Air Age\"",
    "wof:placetype": "media"
  },
  "geometry": {"coordinates":[-122.387939,37.614512],"type":"Point"}
}
