{
  "type": "Feature",
  "properties": {
    "date:cessation_lower": "1996-09-15",
    "date:cessation_upper": "1996-09-15",
    "date:inception_lower": "1996-03-15",
    "date:inception_upper": "1996-03-15",
    "iso:country": "US",
    "media:created": -1,
    "media:fingerprint": "fcc7cfee440be33332e223b2d29e72ff47812efd",
    "media:imagehash_avg": "a:78ffff0000000400",
    "media:imagehash_diff": "d:c0a88ed8f8dccccc",
    "media:medium": "image",
    "media:mimetype": "image/tiff",
    "media:placetype": "installation",
    "media:properties": {
      "colours": [
        {
          "hex": "#e8f4ed",
          "name": "#e8f4ed",
          "reference": "vibrant"
        },
        {
          "hex": "#968966",
          "name": "#968966",
          "reference": "vibrant"
        },
        {
          "hex": "#bcc0ca",
          "name": "#bcc0ca",
          "reference": "vibrant"
        },
        {
          "hex": "#3d3e60",
          "name": "#3d3e60",
          "reference": "vibrant"
        }
      ],
      "depicts": [
        1226611157
      ],
      "sizes": {
        "b": {
          "extension": "jpg",
          "height": 726,
          "mimetype": "image/jpeg",
          "secret": "km2QuWl637tZ61rHbEUTo2xhOIwJtbJj",
          "width": 1024
        },
        "c": {
          "extension": "jpg",
          "height": 567,
          "mimetype": "image/jpeg",
          "secret": "km2QuWl637tZ61rHbEUTo2xhOIwJtbJj",
          "width": 800
        },
        "dc": {
          "extension": "jpg",
          "height": 567,
          "mimetype": "image/jpeg",
          "secret": "km2QuWl637tZ61rHbEUTo2xhOIwJtbJj",
          "width": 800
        },
        "ds": {
          "extension": "jpg",
          "height": 320,
          "mimetype": "image/jpeg",
          "secret": "km2QuWl637tZ61rHbEUTo2xhOIwJtbJj",
          "width": 320
        },
        "k": {
          "extension": "jpg",
          "height": 1452,
          "mimetype": "image/jpeg",
          "secret": "km2QuWl637tZ61rHbEUTo2xhOIwJtbJj",
          "width": 2048
        },
        "n": {
          "extension": "jpg",
          "height": 226,
          "mimetype": "image/jpeg",
          "secret": "km2QuWl637tZ61rHbEUTo2xhOIwJtbJj",
          "width": 320
        },
        "o": {
          "extension": "jpg",
          "height": 3014,
          "mimetype": "image/jpeg",
          "secret": "65ifE3soR2a41SlKN0JjDXacZeNjBz3Q",
          "width": 4251
        },
        "s": {
          "extension": "jpg",
          "height": 320,
          "mimetype": "image/jpeg",
          "secret": "km2QuWl637tZ61rHbEUTo2xhOIwJtbJj",
          "width": 320
        },
        "z": {
          "extension": "jpg",
          "height": 453,
          "mimetype": "image/jpeg",
          "secret": "km2QuWl637tZ61rHbEUTo2xhOIwJtbJj",
          "width": 640
        }
      }
    },
    "sfomuseum:placetype": "image",
    "wof:depicts": [
      1226611157,
      1360516127,
      1159554821,
      1159554803,
      102527513,
      1159554855
    ],
    "wof:name": "Installation view of \"Boomerang\"",
    "wof:placetype": "media",
    "wof:placetype_alt": [
      "image"
    ]
  },
  "geometry": {"coordinates":[-122.387197,37.619087],"type":"Point"}
}
