{
  "type": "Feature", 
  "properties": {
    "iso:country": "US", 
    "media:created": 1455291744, 
    "media:fingerprint": "1b14b9e3b517398f770a37dbcafe3b2a071448ca", 
    "media:medium": "image", 
    "media:mimetype": "image/jpeg", 
    "media:properties": {
      "colours": [
        {
          "hex": "#ee373e", 
          "name": "#ee373e", 
          "reference": "vibrant"
        }, 
        {
          "hex": "#a36764", 
          "name": "#a36764", 
          "reference": "vibrant"
        }, 
        {
          "hex": "#c1c4c8", 
          "name": "#c1c4c8", 
          "reference": "vibrant"
        }, 
        {
          "hex": "#393836", 
          "name": "#393836", 
          "reference": "vibrant"
        }
      ], 
      "depicts": [1159160583], 
      "sizes": {
        "b": {
          "extension": "jpg", 
          "height": 682, 
          "mimetype": "image/jpeg", 
          "secret": "GqiRnoIXc0smsrJD642jfWbgyKPJQFRv", 
          "width": 1024
        }, 
        "c": {
          "extension": "jpg", 
          "height": 533, 
          "mimetype": "image/jpeg", 
          "secret": "GqiRnoIXc0smsrJD642jfWbgyKPJQFRv", 
          "width": 800
        }, 
        "dc": {
          "extension": "jpg", 
          "height": 533, 
          "mimetype": "image/jpeg", 
          "secret": "GqiRnoIXc0smsrJD642jfWbgyKPJQFRv", 
          "width": 800
        }, 
        "ds": {
          "extension": "jpg", 
          "height": 320, 
          "mimetype": "image/jpeg", 
          "secret": "GqiRnoIXc0smsrJD642jfWbgyKPJQFRv", 
          "width": 320
        }, 
        "k": {
          "extension": "jpg", 
          "height": 1365, 
          "mimetype": "image/jpeg", 
          "secret": "GqiRnoIXc0smsrJD642jfWbgyKPJQFRv", 
          "width": 2048
        }, 
        "n": {
          "extension": "jpg", 
          "height": 213, 
          "mimetype": "image/jpeg", 
          "secret": "GqiRnoIXc0smsrJD642jfWbgyKPJQFRv", 
          "width": 320
        }, 
        "o": {
          "extension": "jpg", 
          "height": 2400, 
          "mimetype": "image/jpeg", 
          "secret": "4inIPeaE2oLGEafGn8QkhDA5AsmrJeTe", 
          "width": 3600
        }, 
        "s": {
          "extension": "jpg", 
          "height": 320, 
          "mimetype": "image/jpeg", 
          "secret": "GqiRnoIXc0smsrJD642jfWbgyKPJQFRv", 
          "width": 320
        }, 
        "z": {
          "extension": "jpg", 
          "height": 426, 
          "mimetype": "image/jpeg", 
          "secret": "GqiRnoIXc0smsrJD642jfWbgyKPJQFRv", 
          "width": 640
        }
      }
    }, 
    "sfomuseum:placetype": "image", 
    "wof:depicts": [1159160583, 1159396153, 102527513, 1159396321, 1360516271], 
    "wof:name": "Installation view of \"Essential Style: Antique and Vintage Handbags\"", 
    "wof:placetype": "media" 
  }, 
  "geometry": {"coordinates":[-122.38902,37.614533],"type":"Point"}
}
