{
  "type": "Feature", 
  "properties": {
    "iso:country": "US", 
    "media:created": 1385421565, 
    "media:fingerprint": "11be4989e67dece4c49ba5afbcc320c7a876ae51", 
    "media:medium": "image", 
    "media:mimetype": "image/jpeg", 
    "media:properties": {
      "colours": [
        {
          "hex": "#a21d17", 
          "name": "#a21d17", 
          "reference": "vibrant"
        }, 
        {
          "hex": "#8c1c19", 
          "name": "#8c1c19", 
          "reference": "vibrant"
        }, 
        {
          "hex": "#b25e56", 
          "name": "#b25e56", 
          "reference": "vibrant"
        }, 
        {
          "hex": "#c1bdb8", 
          "name": "#c1bdb8", 
          "reference": "vibrant"
        }, 
        {
          "hex": "#454642", 
          "name": "#454642", 
          "reference": "vibrant"
        }
      ], 
      "depicts": [1159160467], 
      "sizes": {
        "b": {
          "extension": "jpg", 
          "height": 768, 
          "mimetype": "image/jpeg", 
          "secret": "q0jeG2UhL9gzBPriLPHdvVtA0P0ovVh5", 
          "width": 844
        }, 
        "c": {
          "extension": "jpg", 
          "height": 600, 
          "mimetype": "image/jpeg", 
          "secret": "q0jeG2UhL9gzBPriLPHdvVtA0P0ovVh5", 
          "width": 659
        }, 
        "dc": {
          "extension": "jpg", 
          "height": 600, 
          "mimetype": "image/jpeg", 
          "secret": "q0jeG2UhL9gzBPriLPHdvVtA0P0ovVh5", 
          "width": 659
        }, 
        "ds": {
          "extension": "jpg", 
          "height": 320, 
          "mimetype": "image/jpeg", 
          "secret": "q0jeG2UhL9gzBPriLPHdvVtA0P0ovVh5", 
          "width": 320
        }, 
        "k": {
          "extension": "jpg", 
          "height": 1536, 
          "mimetype": "image/jpeg", 
          "secret": "q0jeG2UhL9gzBPriLPHdvVtA0P0ovVh5", 
          "width": 1688
        }, 
        "n": {
          "extension": "jpg", 
          "height": 240, 
          "mimetype": "image/jpeg", 
          "secret": "q0jeG2UhL9gzBPriLPHdvVtA0P0ovVh5", 
          "width": 263
        }, 
        "o": {
          "extension": "jpg", 
          "height": 2400, 
          "mimetype": "image/jpeg", 
          "secret": "cNaqzMBzckX7TtOlcdn8EQA9umHwkgcW", 
          "width": 2639
        }, 
        "s": {
          "extension": "jpg", 
          "height": 320, 
          "mimetype": "image/jpeg", 
          "secret": "q0jeG2UhL9gzBPriLPHdvVtA0P0ovVh5", 
          "width": 320
        }, 
        "z": {
          "extension": "jpg", 
          "height": 480, 
          "mimetype": "image/jpeg", 
          "secret": "q0jeG2UhL9gzBPriLPHdvVtA0P0ovVh5", 
          "width": 527
        }
      }
    }, 
    "sfomuseum:placetype": "image", 
    "wof:depicts": [
      102527513, 
      1360541657, 
      1159396321, 
      1159160467, 
      1360521563, 
      1159396153
    ], 
    "wof:name": "Installation view of \"Airline Identity: Marks, Brands and Logos\"", 
    "wof:placetype": "media" 
  }, 
  "geometry": {"coordinates":[-122.387989,37.614385],"type":"Point"}
}
