{
  "type": "Feature", 
  "properties": {
    "iso:country": "US", 
    "media:created": 1538417423, 
    "media:fingerprint": "74d415961352b5c8175b9f42d6722438f9d22428", 
    "media:medium": "image", 
    "media:mimetype": "image/jpeg", 
    "media:properties": {
      "colours": [
        {
          "hex": "#dc2a38", 
          "name": "#dc2a38", 
          "reference": "vibrant"
        }, 
        {
          "hex": "#e8c470", 
          "name": "#e8c470", 
          "reference": "vibrant"
        }, 
        {
          "hex": "#84251d", 
          "name": "#84251d", 
          "reference": "vibrant"
        }, 
        {
          "hex": "#8e7b6a", 
          "name": "#8e7b6a", 
          "reference": "vibrant"
        }, 
        {
          "hex": "#cfb9a6", 
          "name": "#cfb9a6", 
          "reference": "vibrant"
        }
      ], 
      "depicts": [1360664647], 
      "sizes": {
        "b": {
          "extension": "jpg", 
          "height": 682, 
          "mimetype": "image/jpeg", 
          "secret": "j2DeFdZxfBX37uwvC3GmVAbVxkfv8Pjz", 
          "width": 1024
        }, 
        "c": {
          "extension": "jpg", 
          "height": 533, 
          "mimetype": "image/jpeg", 
          "secret": "j2DeFdZxfBX37uwvC3GmVAbVxkfv8Pjz", 
          "width": 800
        }, 
        "dc": {
          "extension": "jpg", 
          "height": 533, 
          "mimetype": "image/jpeg", 
          "secret": "j2DeFdZxfBX37uwvC3GmVAbVxkfv8Pjz", 
          "width": 800
        }, 
        "ds": {
          "extension": "jpg", 
          "height": 320, 
          "mimetype": "image/jpeg", 
          "secret": "j2DeFdZxfBX37uwvC3GmVAbVxkfv8Pjz", 
          "width": 320
        }, 
        "k": {
          "extension": "jpg", 
          "height": 1365, 
          "mimetype": "image/jpeg", 
          "secret": "j2DeFdZxfBX37uwvC3GmVAbVxkfv8Pjz", 
          "width": 2048
        }, 
        "n": {
          "extension": "jpg", 
          "height": 213, 
          "mimetype": "image/jpeg", 
          "secret": "j2DeFdZxfBX37uwvC3GmVAbVxkfv8Pjz", 
          "width": 320
        }, 
        "o": {
          "extension": "jpg", 
          "height": 2400, 
          "mimetype": "image/jpeg", 
          "secret": "LONmN4aLNGlcxRxETWnvdlKEXJwaKWvm", 
          "width": 3600
        }, 
        "s": {
          "extension": "jpg", 
          "height": 320, 
          "mimetype": "image/jpeg", 
          "secret": "j2DeFdZxfBX37uwvC3GmVAbVxkfv8Pjz", 
          "width": 320
        }, 
        "z": {
          "extension": "jpg", 
          "height": 426, 
          "mimetype": "image/jpeg", 
          "secret": "j2DeFdZxfBX37uwvC3GmVAbVxkfv8Pjz", 
          "width": 640
        }
      }
    }, 
    "sfomuseum:placetype": "image", 
    "wof:depicts": [
      1159157067, 
      1360664647, 
      1159157271, 
      1159396121, 
      102527513, 
      1159396181
    ], 
    "wof:name": "Installation view of \"Down-Home Music: The Story of Arhoolie Records\"", 
    "wof:placetype": "media" 
  }, 
  "geometry": {"coordinates":[-122.382712,37.617422],"type":"Point"}
}
