{
  "type": "Feature",
  "properties": {
    "date:cessation_lower": "2018-02-26",
    "date:cessation_upper": "2018-02-26",
    "date:inception_lower": "2017-06-23",
    "date:inception_upper": "2017-06-23",
    "iso:country": "US",
    "media:created": 1498759371,
    "media:fingerprint": "41f7d1ad3b4bf018b2bdf2a5157b8d7769b4b407",
    "media:imagehash_avg": "a:ffffe7ee203c0000",
    "media:imagehash_diff": "d:438f8fdc6ccccccd",
    "media:medium": "image",
    "media:mimetype": "image/jpeg",
    "media:placetype": "installation",
    "media:properties": {
      "colours": [
        {
          "hex": "#ac332c",
          "name": "#ac332c",
          "reference": "vibrant"
        },
        {
          "hex": "#a76b66",
          "name": "#a76b66",
          "reference": "vibrant"
        },
        {
          "hex": "#c1beb8",
          "name": "#c1beb8",
          "reference": "vibrant"
        },
        {
          "hex": "#643b3a",
          "name": "#643b3a",
          "reference": "vibrant"
        }
      ],
      "depicts": [
        1159160725
      ],
      "sizes": {
        "b": {
          "extension": "jpg",
          "height": 682,
          "mimetype": "image/jpeg",
          "secret": "KThit4z52kdQeE7QX0FvpYHEiWBVkb7d",
          "width": 1024
        },
        "c": {
          "extension": "jpg",
          "height": 533,
          "mimetype": "image/jpeg",
          "secret": "KThit4z52kdQeE7QX0FvpYHEiWBVkb7d",
          "width": 800
        },
        "dc": {
          "extension": "jpg",
          "height": 533,
          "mimetype": "image/jpeg",
          "secret": "KThit4z52kdQeE7QX0FvpYHEiWBVkb7d",
          "width": 800
        },
        "ds": {
          "extension": "jpg",
          "height": 320,
          "mimetype": "image/jpeg",
          "secret": "KThit4z52kdQeE7QX0FvpYHEiWBVkb7d",
          "width": 320
        },
        "k": {
          "extension": "jpg",
          "height": 1365,
          "mimetype": "image/jpeg",
          "secret": "KThit4z52kdQeE7QX0FvpYHEiWBVkb7d",
          "width": 2048
        },
        "n": {
          "extension": "jpg",
          "height": 213,
          "mimetype": "image/jpeg",
          "secret": "KThit4z52kdQeE7QX0FvpYHEiWBVkb7d",
          "width": 320
        },
        "o": {
          "extension": "jpg",
          "height": 2400,
          "mimetype": "image/jpeg",
          "secret": "uPMURD2d3codCm9l2FH1n6gwf4621XQG",
          "width": 3600
        },
        "s": {
          "extension": "jpg",
          "height": 320,
          "mimetype": "image/jpeg",
          "secret": "KThit4z52kdQeE7QX0FvpYHEiWBVkb7d",
          "width": 320
        },
        "z": {
          "extension": "jpg",
          "height": 426,
          "mimetype": "image/jpeg",
          "secret": "KThit4z52kdQeE7QX0FvpYHEiWBVkb7d",
          "width": 640
        }
      }
    },
    "sfomuseum:placetype": "image",
    "wof:depicts": [
      1159157307,
      1159160725,
      1159268871,
      102527513,
      1159396301,
      1159157053,
      1159157271
    ],
    "wof:name": "Installation view of \"Flying the Main Line: A History of United Airlines\"",
    "wof:placetype": "custom",
    "wof:placetype_alt": [
      "image"
    ]
  },
  "geometry": {"type":"Point","coordinates":[-122.387109,37.618847]}
}
