{
  "type": "Feature", 
  "properties": {
    "iso:country": "US", 
    "media:created": 1527796281, 
    "media:fingerprint": "48260952e95aa759821f23e9fe8d0b9ac0274d16", 
    "media:medium": "image", 
    "media:mimetype": "image/jpeg", 
    "media:properties": {
      "colours": [
        {
          "hex": "#f5e3c6", 
          "name": "#f5e3c6", 
          "reference": "vibrant"
        }, 
        {
          "hex": "#5e7697", 
          "name": "#5e7697", 
          "reference": "vibrant"
        }, 
        {
          "hex": "#a2b9cf", 
          "name": "#a2b9cf", 
          "reference": "vibrant"
        }, 
        {
          "hex": "#535332", 
          "name": "#535332", 
          "reference": "vibrant"
        }
      ], 
      "depicts": [1226619815], 
      "sizes": {
        "b": {
          "extension": "jpg", 
          "height": 696, 
          "mimetype": "image/jpeg", 
          "secret": "2YJUugAuRZuzLb1CYeoHT59eBUCuVy31", 
          "width": 1024
        }, 
        "c": {
          "extension": "jpg", 
          "height": 544, 
          "mimetype": "image/jpeg", 
          "secret": "2YJUugAuRZuzLb1CYeoHT59eBUCuVy31", 
          "width": 800
        }, 
        "dc": {
          "extension": "jpg", 
          "height": 544, 
          "mimetype": "image/jpeg", 
          "secret": "2YJUugAuRZuzLb1CYeoHT59eBUCuVy31", 
          "width": 800
        }, 
        "ds": {
          "extension": "jpg", 
          "height": 320, 
          "mimetype": "image/jpeg", 
          "secret": "2YJUugAuRZuzLb1CYeoHT59eBUCuVy31", 
          "width": 320
        }, 
        "k": {
          "extension": "jpg", 
          "height": 1393, 
          "mimetype": "image/jpeg", 
          "secret": "2YJUugAuRZuzLb1CYeoHT59eBUCuVy31", 
          "width": 2048
        }, 
        "n": {
          "extension": "jpg", 
          "height": 217, 
          "mimetype": "image/jpeg", 
          "secret": "2YJUugAuRZuzLb1CYeoHT59eBUCuVy31", 
          "width": 320
        }, 
        "o": {
          "extension": "jpg", 
          "height": 2449, 
          "mimetype": "image/jpeg", 
          "secret": "Wact926849AofNCMZ0ryK1tm64r6Krub", 
          "width": 3600
        }, 
        "s": {
          "extension": "jpg", 
          "height": 320, 
          "mimetype": "image/jpeg", 
          "secret": "2YJUugAuRZuzLb1CYeoHT59eBUCuVy31", 
          "width": 320
        }, 
        "z": {
          "extension": "jpg", 
          "height": 435, 
          "mimetype": "image/jpeg", 
          "secret": "2YJUugAuRZuzLb1CYeoHT59eBUCuVy31", 
          "width": 640
        }
      }
    }, 
    "sfomuseum:placetype": "image", 
    "wof:depicts": [
      102527513, 
      1159157045, 
      1159157333, 
      1159157047, 
      1159157335, 
      1226619815, 
      1159157271
    ], 
    "wof:name": "Installation view of \"Isamu Noguchi: Inside and Out\"", 
    "wof:placetype": "media" 
  }, 
  "geometry": {"coordinates":[-122.389131,37.616029],"type":"Point"}
}
