{
  "type": "Feature",
  "properties": {
    "iso:country": "US",
    "media:created": -1,
    "media:fingerprint": "64dc8e896a506cd55d4484ae3016b4fae2c8baee",
    "media:imagehash_avg": "a:1e7efefefe7e0000",
    "media:imagehash_diff": "d:f486b8acb4b494f0",
    "media:medium": "image",
    "media:mimetype": "image/tiff",
    "media:properties": {
      "colours": [
        {
          "hex": "#8f4541",
          "name": "#8f4541",
          "reference": "vibrant"
        }, 
        {
          "hex": "#eaf5d9",
          "name": "#eaf5d9",
          "reference": "vibrant"
        }, 
        {
          "hex": "#616d9c",
          "name": "#616d9c",
          "reference": "vibrant"
        }, 
        {
          "hex": "#d7dcc1",
          "name": "#d7dcc1",
          "reference": "vibrant"
        }, 
        {
          "hex": "#483b43",
          "name": "#483b43",
          "reference": "vibrant"
        }
      ],
      "depicts": [
        1226612107
      ],
      "sizes": {
        "b": {
          "extension": "jpg",
          "height": 768,
          "mimetype": "image/jpeg",
          "secret": "Sz2ExTatn3n3bnQRmN7K86xHFEiUApGJ",
          "width": 543
        },
        "c": {
          "extension": "jpg",
          "height": 600,
          "mimetype": "image/jpeg",
          "secret": "Sz2ExTatn3n3bnQRmN7K86xHFEiUApGJ",
          "width": 424
        },
        "dc": {
          "extension": "jpg",
          "height": 600,
          "mimetype": "image/jpeg",
          "secret": "Sz2ExTatn3n3bnQRmN7K86xHFEiUApGJ",
          "width": 424
        },
        "ds": {
          "extension": "jpg",
          "height": 320,
          "mimetype": "image/jpeg",
          "secret": "Sz2ExTatn3n3bnQRmN7K86xHFEiUApGJ",
          "width": 320
        },
        "k": {
          "extension": "jpg",
          "height": 1536,
          "mimetype": "image/jpeg",
          "secret": "Sz2ExTatn3n3bnQRmN7K86xHFEiUApGJ",
          "width": 1086
        },
        "n": {
          "extension": "jpg",
          "height": 240,
          "mimetype": "image/jpeg",
          "secret": "Sz2ExTatn3n3bnQRmN7K86xHFEiUApGJ",
          "width": 169
        },
        "o": {
          "extension": "jpg",
          "height": 4262,
          "mimetype": "image/jpeg",
          "secret": "3PQnkEcOLdQTd0h8hMl7y38rn4Stvxmr",
          "width": 3014
        },
        "s": {
          "extension": "jpg",
          "height": 320,
          "mimetype": "image/jpeg",
          "secret": "Sz2ExTatn3n3bnQRmN7K86xHFEiUApGJ",
          "width": 320
        },
        "z": {
          "extension": "jpg",
          "height": 480,
          "mimetype": "image/jpeg",
          "secret": "Sz2ExTatn3n3bnQRmN7K86xHFEiUApGJ",
          "width": 339
        }
      }
    },
    "sfomuseum:placetype": "image",
    "wof:depicts": [
      1360516129, 
      1159554801, 
      102527513, 
      1159554841, 
      1226612107, 
      1159554819
    ],
    "wof:name": "Installation view of \"Airport Cafe\"",
    "wof:placetype": "media"
  },
  "geometry": {"coordinates":[-122.387197,37.619087],"type":"Point"}
}
