{
  "type": "Feature",
  "properties": {
    "date:cessation_lower": "2004-03-30",
    "date:cessation_upper": "2004-03-30",
    "date:inception_lower": "2003-04-30",
    "date:inception_upper": "2003-04-30",
    "iso:country": "US",
    "media:created": 1054068338,
    "media:fingerprint": "e212b64f8ca1ee106486e4691040fc7de4049718",
    "media:imagehash_avg": "a:0c3e3e3e3e1e0000",
    "media:imagehash_diff": "d:bcfcf4f0f0b4bcfc",
    "media:medium": "image",
    "media:mimetype": "image/jpeg",
    "media:placetype": "installation",
    "media:properties": {
      "colours": [
        {
          "hex": "#c48b28",
          "name": "#c48b28",
          "reference": "vibrant"
        },
        {
          "hex": "#f7bd77",
          "name": "#f7bd77",
          "reference": "vibrant"
        },
        {
          "hex": "#694616",
          "name": "#694616",
          "reference": "vibrant"
        },
        {
          "hex": "#a8774b",
          "name": "#a8774b",
          "reference": "vibrant"
        }
      ],
      "depicts": [
        1159159445
      ],
      "sizes": {
        "b": {
          "extension": "jpg",
          "height": 768,
          "mimetype": "image/jpeg",
          "secret": "v7zbxchsVp93kIzG6SelqLk7R9kjZ4u2",
          "width": 1024
        },
        "c": {
          "extension": "jpg",
          "height": 600,
          "mimetype": "image/jpeg",
          "secret": "v7zbxchsVp93kIzG6SelqLk7R9kjZ4u2",
          "width": 800
        },
        "dc": {
          "extension": "jpg",
          "height": 600,
          "mimetype": "image/jpeg",
          "secret": "v7zbxchsVp93kIzG6SelqLk7R9kjZ4u2",
          "width": 800
        },
        "ds": {
          "extension": "jpg",
          "height": 320,
          "mimetype": "image/jpeg",
          "secret": "v7zbxchsVp93kIzG6SelqLk7R9kjZ4u2",
          "width": 320
        },
        "k": {
          "extension": "jpg",
          "height": 1536,
          "mimetype": "image/jpeg",
          "secret": "v7zbxchsVp93kIzG6SelqLk7R9kjZ4u2",
          "width": 2048
        },
        "n": {
          "extension": "jpg",
          "height": 240,
          "mimetype": "image/jpeg",
          "secret": "v7zbxchsVp93kIzG6SelqLk7R9kjZ4u2",
          "width": 320
        },
        "o": {
          "extension": "jpg",
          "height": 1920,
          "mimetype": "image/jpeg",
          "secret": "JOKQq0L4MwkFGYBom0qcaKueZAlTvSmK",
          "width": 2560
        },
        "s": {
          "extension": "jpg",
          "height": 320,
          "mimetype": "image/jpeg",
          "secret": "v7zbxchsVp93kIzG6SelqLk7R9kjZ4u2",
          "width": 320
        },
        "z": {
          "extension": "jpg",
          "height": 480,
          "mimetype": "image/jpeg",
          "secret": "v7zbxchsVp93kIzG6SelqLk7R9kjZ4u2",
          "width": 640
        }
      }
    },
    "sfomuseum:placetype": "image",
    "wof:depicts": [
      1360521557,
      1159159445,
      1159396319,
      102527513,
      1360521543
    ],
    "wof:name": "Installation view of \"Mapping America\"",
    "wof:placetype": "media",
    "wof:placetype_alt": [
      "image"
    ]
  },
  "geometry": {"coordinates":[-122.38274,37.617227],"type":"Point"}
}
