{
  "type": "Feature", 
  "properties": {
    "iso:country": "US", 
    "media:created": 1054071326, 
    "media:fingerprint": "a6b5425f6bf984a2931de175e5e0ccd212832935", 
    "media:medium": "image", 
    "media:mimetype": "image/jpeg", 
    "media:properties": {
      "colours": [
        {
          "hex": "#5792c2", 
          "name": "#5792c2", 
          "reference": "vibrant"
        }, 
        {
          "hex": "#6db4c7", 
          "name": "#6db4c7", 
          "reference": "vibrant"
        }, 
        {
          "hex": "#1b3935", 
          "name": "#1b3935", 
          "reference": "vibrant"
        }, 
        {
          "hex": "#65999b", 
          "name": "#65999b", 
          "reference": "vibrant"
        }, 
        {
          "hex": "#bbcdbd", 
          "name": "#bbcdbd", 
          "reference": "vibrant"
        }
      ], 
      "depicts": [1159159593], 
      "sizes": {
        "b": {
          "extension": "jpg", 
          "height": 768, 
          "mimetype": "image/jpeg", 
          "secret": "prJ7OyWZpUCDbxP6XnLMBpg3h0EbXbsd", 
          "width": 1024
        }, 
        "c": {
          "extension": "jpg", 
          "height": 600, 
          "mimetype": "image/jpeg", 
          "secret": "prJ7OyWZpUCDbxP6XnLMBpg3h0EbXbsd", 
          "width": 800
        }, 
        "dc": {
          "extension": "jpg", 
          "height": 600, 
          "mimetype": "image/jpeg", 
          "secret": "prJ7OyWZpUCDbxP6XnLMBpg3h0EbXbsd", 
          "width": 800
        }, 
        "ds": {
          "extension": "jpg", 
          "height": 320, 
          "mimetype": "image/jpeg", 
          "secret": "prJ7OyWZpUCDbxP6XnLMBpg3h0EbXbsd", 
          "width": 320
        }, 
        "k": {
          "extension": "jpg", 
          "height": 1536, 
          "mimetype": "image/jpeg", 
          "secret": "prJ7OyWZpUCDbxP6XnLMBpg3h0EbXbsd", 
          "width": 2048
        }, 
        "n": {
          "extension": "jpg", 
          "height": 240, 
          "mimetype": "image/jpeg", 
          "secret": "prJ7OyWZpUCDbxP6XnLMBpg3h0EbXbsd", 
          "width": 320
        }, 
        "o": {
          "extension": "jpg", 
          "height": 1920, 
          "mimetype": "image/jpeg", 
          "secret": "y6edIFsuE86hPEZzFfh54tcbGUScZJhL", 
          "width": 2560
        }, 
        "s": {
          "extension": "jpg", 
          "height": 320, 
          "mimetype": "image/jpeg", 
          "secret": "prJ7OyWZpUCDbxP6XnLMBpg3h0EbXbsd", 
          "width": 320
        }, 
        "z": {
          "extension": "jpg", 
          "height": 480, 
          "mimetype": "image/jpeg", 
          "secret": "prJ7OyWZpUCDbxP6XnLMBpg3h0EbXbsd", 
          "width": 640
        }
      }
    }, 
    "sfomuseum:placetype": "image", 
    "wof:depicts": [1159396319, 102527513, 1360516477, 1159159593, 1159396115], 
    "wof:name": "Installation view of \"The Flight Bag: Icon of Air Travel\"", 
    "wof:placetype": "media" 
  }, 
  "geometry": {"coordinates":[-122.385472,37.613926],"type":"Point"}
}
