{
  "type": "Feature", 
  "properties": {
    "iso:country": "US", 
    "media:created": 1360968219, 
    "media:fingerprint": "92af6efe6556c69682a0ab6ee2dd00b3b1cb7371", 
    "media:medium": "image", 
    "media:mimetype": "image/jpeg", 
    "media:properties": {
      "colours": [
        {
          "hex": "#ad693c", 
          "name": "#ad693c", 
          "reference": "vibrant"
        }, 
        {
          "hex": "#c6b688", 
          "name": "#c6b688", 
          "reference": "vibrant"
        }, 
        {
          "hex": "#916642", 
          "name": "#916642", 
          "reference": "vibrant"
        }, 
        {
          "hex": "#af9666", 
          "name": "#af9666", 
          "reference": "vibrant"
        }, 
        {
          "hex": "#afbfbe", 
          "name": "#afbfbe", 
          "reference": "vibrant"
        }
      ], 
      "depicts": [1159160359], 
      "sizes": {
        "b": {
          "extension": "jpg", 
          "height": 768, 
          "mimetype": "image/jpeg", 
          "secret": "2HnKEloFK2C2OJRh2b19gDN60L9vELYt", 
          "width": 512
        }, 
        "c": {
          "extension": "jpg", 
          "height": 600, 
          "mimetype": "image/jpeg", 
          "secret": "2HnKEloFK2C2OJRh2b19gDN60L9vELYt", 
          "width": 400
        }, 
        "dc": {
          "extension": "jpg", 
          "height": 600, 
          "mimetype": "image/jpeg", 
          "secret": "2HnKEloFK2C2OJRh2b19gDN60L9vELYt", 
          "width": 400
        }, 
        "ds": {
          "extension": "jpg", 
          "height": 320, 
          "mimetype": "image/jpeg", 
          "secret": "2HnKEloFK2C2OJRh2b19gDN60L9vELYt", 
          "width": 320
        }, 
        "k": {
          "extension": "jpg", 
          "height": 1536, 
          "mimetype": "image/jpeg", 
          "secret": "2HnKEloFK2C2OJRh2b19gDN60L9vELYt", 
          "width": 1024
        }, 
        "n": {
          "extension": "jpg", 
          "height": 240, 
          "mimetype": "image/jpeg", 
          "secret": "2HnKEloFK2C2OJRh2b19gDN60L9vELYt", 
          "width": 160
        }, 
        "o": {
          "extension": "jpg", 
          "height": 3600, 
          "mimetype": "image/jpeg", 
          "secret": "ImGje2mReE85rtbQa7RmlWbXvSoFZg0P", 
          "width": 2400
        }, 
        "s": {
          "extension": "jpg", 
          "height": 320, 
          "mimetype": "image/jpeg", 
          "secret": "2HnKEloFK2C2OJRh2b19gDN60L9vELYt", 
          "width": 320
        }, 
        "z": {
          "extension": "jpg", 
          "height": 480, 
          "mimetype": "image/jpeg", 
          "secret": "2HnKEloFK2C2OJRh2b19gDN60L9vELYt", 
          "width": 320
        }
      }
    }, 
    "sfomuseum:placetype": "image", 
    "wof:depicts": [1159396333, 1360516283, 102527513, 1159160359, 1159396159], 
    "wof:name": "Installation view of \"Souvenirs: Tokens of Travel\"", 
    "wof:placetype": "media" 
  }, 
  "geometry": {"coordinates":[-122.389725,37.616594],"type":"Point"}
}
