{
  "type": "Feature",
  "properties": {
    "date:cessation_lower": "2013-10-28",
    "date:cessation_upper": "2013-10-28",
    "date:inception_lower": "2013-03-15",
    "date:inception_upper": "2013-03-15",
    "iso:country": "US",
    "media:created": 1363802664,
    "media:fingerprint": "fe1410c4901b87b6c935bd03d958cf140095a398",
    "media:imagehash_avg": "a:00f0ff6e0e067e00",
    "media:imagehash_diff": "d:c0008a8e989cccf8",
    "media:medium": "image",
    "media:mimetype": "image/jpeg",
    "media:placetype": "installation",
    "media:properties": {
      "colours": [
        {
          "hex": "#6372a8",
          "name": "#6372a8",
          "reference": "vibrant"
        },
        {
          "hex": "#afb4c0",
          "name": "#afb4c0",
          "reference": "vibrant"
        },
        {
          "hex": "#42332d",
          "name": "#42332d",
          "reference": "vibrant"
        }
      ],
      "depicts": [
        1159160335
      ],
      "sizes": {
        "b": {
          "extension": "jpg",
          "height": 682,
          "mimetype": "image/jpeg",
          "secret": "PX8n19cAkSJLHrCpjN828enicbh8Tugq",
          "width": 1024
        },
        "c": {
          "extension": "jpg",
          "height": 533,
          "mimetype": "image/jpeg",
          "secret": "PX8n19cAkSJLHrCpjN828enicbh8Tugq",
          "width": 800
        },
        "dc": {
          "extension": "jpg",
          "height": 533,
          "mimetype": "image/jpeg",
          "secret": "PX8n19cAkSJLHrCpjN828enicbh8Tugq",
          "width": 800
        },
        "ds": {
          "extension": "jpg",
          "height": 320,
          "mimetype": "image/jpeg",
          "secret": "PX8n19cAkSJLHrCpjN828enicbh8Tugq",
          "width": 320
        },
        "k": {
          "extension": "jpg",
          "height": 1365,
          "mimetype": "image/jpeg",
          "secret": "PX8n19cAkSJLHrCpjN828enicbh8Tugq",
          "width": 2048
        },
        "n": {
          "extension": "jpg",
          "height": 213,
          "mimetype": "image/jpeg",
          "secret": "PX8n19cAkSJLHrCpjN828enicbh8Tugq",
          "width": 320
        },
        "o": {
          "extension": "jpg",
          "height": 2400,
          "mimetype": "image/jpeg",
          "secret": "G5f6Ge4toqPmMWLmKdvIonHZnNhnPjqb",
          "width": 3600
        },
        "s": {
          "extension": "jpg",
          "height": 320,
          "mimetype": "image/jpeg",
          "secret": "PX8n19cAkSJLHrCpjN828enicbh8Tugq",
          "width": 320
        },
        "z": {
          "extension": "jpg",
          "height": 426,
          "mimetype": "image/jpeg",
          "secret": "PX8n19cAkSJLHrCpjN828enicbh8Tugq",
          "width": 640
        }
      }
    },
    "sfomuseum:placetype": "image",
    "wof:depicts": [
      1159396141,
      1159396333,
      1360516121,
      1159160335,
      102527513,
      1159396295
    ],
    "wof:name": "Installation view of \"The Art of Recology: The Artist in Residence Program 1990-2013\"",
    "wof:placetype": "media",
    "wof:placetype_alt": [
      "image"
    ]
  },
  "geometry": {"coordinates":[-122.387197,37.619087],"type":"Point"}
}
