{
  "type": "Feature", 
  "properties": {
    "iso:country": "US", 
    "media:created": 1360969102, 
    "media:fingerprint": "ffeab022b90e216fb14036288cac41bb6cd1de0f", 
    "media:medium": "image", 
    "media:mimetype": "image/jpeg", 
    "media:properties": {
      "colours": [
        {
          "hex": "#b8692d", 
          "name": "#b8692d", 
          "reference": "vibrant"
        }, 
        {
          "hex": "#e1d7aa", 
          "name": "#e1d7aa", 
          "reference": "vibrant"
        }, 
        {
          "hex": "#633725", 
          "name": "#633725", 
          "reference": "vibrant"
        }, 
        {
          "hex": "#5d758c", 
          "name": "#5d758c", 
          "reference": "vibrant"
        }, 
        {
          "hex": "#d0c8a0", 
          "name": "#d0c8a0", 
          "reference": "vibrant"
        }
      ], 
      "depicts": [1159160359], 
      "sizes": {
        "b": {
          "extension": "jpg", 
          "height": 682, 
          "mimetype": "image/jpeg", 
          "secret": "V1hQA9pbRmxrn5Gno67rMfDHN1uOKWyt", 
          "width": 1024
        }, 
        "c": {
          "extension": "jpg", 
          "height": 533, 
          "mimetype": "image/jpeg", 
          "secret": "V1hQA9pbRmxrn5Gno67rMfDHN1uOKWyt", 
          "width": 800
        }, 
        "dc": {
          "extension": "jpg", 
          "height": 533, 
          "mimetype": "image/jpeg", 
          "secret": "V1hQA9pbRmxrn5Gno67rMfDHN1uOKWyt", 
          "width": 800
        }, 
        "ds": {
          "extension": "jpg", 
          "height": 320, 
          "mimetype": "image/jpeg", 
          "secret": "V1hQA9pbRmxrn5Gno67rMfDHN1uOKWyt", 
          "width": 320
        }, 
        "k": {
          "extension": "jpg", 
          "height": 1365, 
          "mimetype": "image/jpeg", 
          "secret": "V1hQA9pbRmxrn5Gno67rMfDHN1uOKWyt", 
          "width": 2048
        }, 
        "n": {
          "extension": "jpg", 
          "height": 213, 
          "mimetype": "image/jpeg", 
          "secret": "V1hQA9pbRmxrn5Gno67rMfDHN1uOKWyt", 
          "width": 320
        }, 
        "o": {
          "extension": "jpg", 
          "height": 2400, 
          "mimetype": "image/jpeg", 
          "secret": "wa4zeOXiPWcvEiel5DXP8kWtPWvnbi35", 
          "width": 3600
        }, 
        "s": {
          "extension": "jpg", 
          "height": 320, 
          "mimetype": "image/jpeg", 
          "secret": "V1hQA9pbRmxrn5Gno67rMfDHN1uOKWyt", 
          "width": 320
        }, 
        "z": {
          "extension": "jpg", 
          "height": 426, 
          "mimetype": "image/jpeg", 
          "secret": "V1hQA9pbRmxrn5Gno67rMfDHN1uOKWyt", 
          "width": 640
        }
      }
    }, 
    "sfomuseum:placetype": "image", 
    "wof:depicts": [1159396159, 1360516283, 1159396333, 1159160359, 102527513], 
    "wof:name": "Installation view of \"Souvenirs: Tokens of Travel\"", 
    "wof:placetype": "media" 
  }, 
  "geometry": {"coordinates":[-122.389725,37.616594],"type":"Point"}
}
