{
  "type": "Feature", 
  "properties": {
    "iso:country": "US", 
    "media:created": 1538413470, 
    "media:fingerprint": "cdb6830cd7f5a92eef277cb4c976a7979f160322", 
    "media:medium": "image", 
    "media:mimetype": "image/jpeg", 
    "media:properties": {
      "colours": [
        {
          "hex": "#3499cf", 
          "name": "#3499cf", 
          "reference": "vibrant"
        }, 
        {
          "hex": "#40abea", 
          "name": "#40abea", 
          "reference": "vibrant"
        }, 
        {
          "hex": "#3877a4", 
          "name": "#3877a4", 
          "reference": "vibrant"
        }, 
        {
          "hex": "#a47256", 
          "name": "#a47256", 
          "reference": "vibrant"
        }, 
        {
          "hex": "#b5c6d0", 
          "name": "#b5c6d0", 
          "reference": "vibrant"
        }
      ], 
      "depicts": [1360664647], 
      "sizes": {
        "b": {
          "extension": "jpg", 
          "height": 682, 
          "mimetype": "image/jpeg", 
          "secret": "3xdibGhNB2QMYMAxVOWUpOlfihestRKn", 
          "width": 1024
        }, 
        "c": {
          "extension": "jpg", 
          "height": 533, 
          "mimetype": "image/jpeg", 
          "secret": "3xdibGhNB2QMYMAxVOWUpOlfihestRKn", 
          "width": 800
        }, 
        "dc": {
          "extension": "jpg", 
          "height": 533, 
          "mimetype": "image/jpeg", 
          "secret": "3xdibGhNB2QMYMAxVOWUpOlfihestRKn", 
          "width": 800
        }, 
        "ds": {
          "extension": "jpg", 
          "height": 320, 
          "mimetype": "image/jpeg", 
          "secret": "3xdibGhNB2QMYMAxVOWUpOlfihestRKn", 
          "width": 320
        }, 
        "k": {
          "extension": "jpg", 
          "height": 1365, 
          "mimetype": "image/jpeg", 
          "secret": "3xdibGhNB2QMYMAxVOWUpOlfihestRKn", 
          "width": 2048
        }, 
        "n": {
          "extension": "jpg", 
          "height": 213, 
          "mimetype": "image/jpeg", 
          "secret": "3xdibGhNB2QMYMAxVOWUpOlfihestRKn", 
          "width": 320
        }, 
        "o": {
          "extension": "jpg", 
          "height": 2400, 
          "mimetype": "image/jpeg", 
          "secret": "ETjP2Z7D2L9Jp32SjyTKoDWfumEp7P1V", 
          "width": 3600
        }, 
        "s": {
          "extension": "jpg", 
          "height": 320, 
          "mimetype": "image/jpeg", 
          "secret": "3xdibGhNB2QMYMAxVOWUpOlfihestRKn", 
          "width": 320
        }, 
        "z": {
          "extension": "jpg", 
          "height": 426, 
          "mimetype": "image/jpeg", 
          "secret": "3xdibGhNB2QMYMAxVOWUpOlfihestRKn", 
          "width": 640
        }
      }
    }, 
    "sfomuseum:placetype": "image", 
    "wof:depicts": [
      1159157067, 
      1159157271, 
      1360664647, 
      1159396121, 
      102527513, 
      1159396181
    ], 
    "wof:name": "Installation view of \"Down-Home Music: The Story of Arhoolie Records\"", 
    "wof:placetype": "media" 
  }, 
  "geometry": {"coordinates":[-122.382712,37.617422],"type":"Point"}
}
