{
  "type": "Feature",
  "properties": {
    "iso:country": "US",
    "media:created": -1,
    "media:fingerprint": "249b5a2b90b46d372f8727ca3b161b90be10573a",
    "media:imagehash_avg": "a:003f7d18001cfe1e",
    "media:imagehash_diff": "d:fbfbe1ebf2b8f8fc",
    "media:medium": "image",
    "media:mimetype": "image/tiff",
    "media:properties": {
      "colours": [
        {
          "hex": "#ca967b",
          "name": "#ca967b",
          "reference": "vibrant"
        }, 
        {
          "hex": "#f1dabd",
          "name": "#f1dabd",
          "reference": "vibrant"
        }, 
        {
          "hex": "#a57157",
          "name": "#a57157",
          "reference": "vibrant"
        }, 
        {
          "hex": "#c3c9dc",
          "name": "#c3c9dc",
          "reference": "vibrant"
        }, 
        {
          "hex": "#463942",
          "name": "#463942",
          "reference": "vibrant"
        }
      ],
      "depicts": [
        1226612107
      ],
      "sizes": {
        "b": {
          "extension": "jpg",
          "height": 726,
          "mimetype": "image/jpeg",
          "secret": "v6UKbXPRDaq4Ba3S8udoYWJfgV1Lqguq",
          "width": 1024
        },
        "c": {
          "extension": "jpg",
          "height": 567,
          "mimetype": "image/jpeg",
          "secret": "v6UKbXPRDaq4Ba3S8udoYWJfgV1Lqguq",
          "width": 800
        },
        "dc": {
          "extension": "jpg",
          "height": 567,
          "mimetype": "image/jpeg",
          "secret": "v6UKbXPRDaq4Ba3S8udoYWJfgV1Lqguq",
          "width": 800
        },
        "ds": {
          "extension": "jpg",
          "height": 320,
          "mimetype": "image/jpeg",
          "secret": "v6UKbXPRDaq4Ba3S8udoYWJfgV1Lqguq",
          "width": 320
        },
        "k": {
          "extension": "jpg",
          "height": 1452,
          "mimetype": "image/jpeg",
          "secret": "v6UKbXPRDaq4Ba3S8udoYWJfgV1Lqguq",
          "width": 2048
        },
        "n": {
          "extension": "jpg",
          "height": 226,
          "mimetype": "image/jpeg",
          "secret": "v6UKbXPRDaq4Ba3S8udoYWJfgV1Lqguq",
          "width": 320
        },
        "o": {
          "extension": "jpg",
          "height": 3014,
          "mimetype": "image/jpeg",
          "secret": "eIBuD1EWe8zZKoQ8tCyqVHjE2G8iDaWU",
          "width": 4251
        },
        "s": {
          "extension": "jpg",
          "height": 320,
          "mimetype": "image/jpeg",
          "secret": "v6UKbXPRDaq4Ba3S8udoYWJfgV1Lqguq",
          "width": 320
        },
        "z": {
          "extension": "jpg",
          "height": 453,
          "mimetype": "image/jpeg",
          "secret": "v6UKbXPRDaq4Ba3S8udoYWJfgV1Lqguq",
          "width": 640
        }
      }
    },
    "sfomuseum:placetype": "image",
    "wof:depicts": [
      1159554819, 
      102527513, 
      1159554841, 
      1360516129, 
      1226612107, 
      1159554801
    ],
    "wof:name": "Installation view of \"Airport Cafe\"",
    "wof:placetype": "media"
  },
  "geometry": {"coordinates":[-122.387197,37.619087],"type":"Point"}
}
