{
  "type": "Feature", 
  "properties": {
    "iso:country": "US", 
    "media:created": -1, 
    "media:fingerprint": "b98b92f83da849a3dc7111caff19d973d51849e3", 
    "media:medium": "image", 
    "media:mimetype": "image/tiff", 
    "media:properties": {
      "colours": [
        {
          "hex": "#ca5b34", 
          "name": "#ca5b34", 
          "reference": "vibrant"
        }, 
        {
          "hex": "#e9b386", 
          "name": "#e9b386", 
          "reference": "vibrant"
        }, 
        {
          "hex": "#88513f", 
          "name": "#88513f", 
          "reference": "vibrant"
        }, 
        {
          "hex": "#8f7160", 
          "name": "#8f7160", 
          "reference": "vibrant"
        }, 
        {
          "hex": "#ba9a97", 
          "name": "#ba9a97", 
          "reference": "vibrant"
        }
      ], 
      "depicts": [1226612107], 
      "sizes": {
        "b": {
          "extension": "jpg", 
          "height": 726, 
          "mimetype": "image/jpeg", 
          "secret": "mLhpk4EiwfQtLRezcSehAP6Cc172yn5u", 
          "width": 1024
        }, 
        "c": {
          "extension": "jpg", 
          "height": 567, 
          "mimetype": "image/jpeg", 
          "secret": "mLhpk4EiwfQtLRezcSehAP6Cc172yn5u", 
          "width": 800
        }, 
        "dc": {
          "extension": "jpg", 
          "height": 567, 
          "mimetype": "image/jpeg", 
          "secret": "mLhpk4EiwfQtLRezcSehAP6Cc172yn5u", 
          "width": 800
        }, 
        "ds": {
          "extension": "jpg", 
          "height": 320, 
          "mimetype": "image/jpeg", 
          "secret": "mLhpk4EiwfQtLRezcSehAP6Cc172yn5u", 
          "width": 320
        }, 
        "k": {
          "extension": "jpg", 
          "height": 1452, 
          "mimetype": "image/jpeg", 
          "secret": "mLhpk4EiwfQtLRezcSehAP6Cc172yn5u", 
          "width": 2048
        }, 
        "n": {
          "extension": "jpg", 
          "height": 226, 
          "mimetype": "image/jpeg", 
          "secret": "mLhpk4EiwfQtLRezcSehAP6Cc172yn5u", 
          "width": 320
        }, 
        "o": {
          "extension": "jpg", 
          "height": 3014, 
          "mimetype": "image/jpeg", 
          "secret": "XiWZwf8I2k8u3bugP8zYqNHNzoX0QCh8", 
          "width": 4251
        }, 
        "s": {
          "extension": "jpg", 
          "height": 320, 
          "mimetype": "image/jpeg", 
          "secret": "mLhpk4EiwfQtLRezcSehAP6Cc172yn5u", 
          "width": 320
        }, 
        "z": {
          "extension": "jpg", 
          "height": 453, 
          "mimetype": "image/jpeg", 
          "secret": "mLhpk4EiwfQtLRezcSehAP6Cc172yn5u", 
          "width": 640
        }
      }
    }, 
    "sfomuseum:placetype": "image", 
    "wof:depicts": [
      1159554841, 
      1226612107, 
      1360516129, 
      1159554801, 
      1159554819, 
      102527513
    ], 
    "wof:name": "Installation view of \"Airport Cafe\"", 
    "wof:placetype": "media" 
  }, 
  "geometry": {"coordinates":[-122.387197,37.619087],"type":"Point"}
}
