{
  "type": "Feature", 
  "properties": {
    "iso:country": "US", 
    "media:created": -1, 
    "media:fingerprint": "46d4a51355ad631b8401324464521ef31dadb47b", 
    "media:medium": "image", 
    "media:mimetype": "image/tiff", 
    "media:properties": {
      "colours": [
        {
          "hex": "#bbe3f3", 
          "name": "#bbe3f3", 
          "reference": "vibrant"
        }, 
        {
          "hex": "#72789a", 
          "name": "#72789a", 
          "reference": "vibrant"
        }, 
        {
          "hex": "#9ab6d1", 
          "name": "#9ab6d1", 
          "reference": "vibrant"
        }, 
        {
          "hex": "#3b3d5c", 
          "name": "#3b3d5c", 
          "reference": "vibrant"
        }
      ], 
      "depicts": [1226608683], 
      "sizes": {
        "b": {
          "extension": "jpg", 
          "height": 726, 
          "mimetype": "image/jpeg", 
          "secret": "hwU6FcbCvTI48pSdKFGs7HXhDgFQF4v1", 
          "width": 1024
        }, 
        "c": {
          "extension": "jpg", 
          "height": 567, 
          "mimetype": "image/jpeg", 
          "secret": "hwU6FcbCvTI48pSdKFGs7HXhDgFQF4v1", 
          "width": 800
        }, 
        "dc": {
          "extension": "jpg", 
          "height": 567, 
          "mimetype": "image/jpeg", 
          "secret": "hwU6FcbCvTI48pSdKFGs7HXhDgFQF4v1", 
          "width": 800
        }, 
        "ds": {
          "extension": "jpg", 
          "height": 320, 
          "mimetype": "image/jpeg", 
          "secret": "hwU6FcbCvTI48pSdKFGs7HXhDgFQF4v1", 
          "width": 320
        }, 
        "k": {
          "extension": "jpg", 
          "height": 1452, 
          "mimetype": "image/jpeg", 
          "secret": "hwU6FcbCvTI48pSdKFGs7HXhDgFQF4v1", 
          "width": 2048
        }, 
        "n": {
          "extension": "jpg", 
          "height": 226, 
          "mimetype": "image/jpeg", 
          "secret": "hwU6FcbCvTI48pSdKFGs7HXhDgFQF4v1", 
          "width": 320
        }, 
        "o": {
          "extension": "jpg", 
          "height": 3014, 
          "mimetype": "image/jpeg", 
          "secret": "BObzCOfhzMdAnL7A1gXa3unY3XnHLsxO", 
          "width": 4251
        }, 
        "s": {
          "extension": "jpg", 
          "height": 320, 
          "mimetype": "image/jpeg", 
          "secret": "hwU6FcbCvTI48pSdKFGs7HXhDgFQF4v1", 
          "width": 320
        }, 
        "z": {
          "extension": "jpg", 
          "height": 453, 
          "mimetype": "image/jpeg", 
          "secret": "hwU6FcbCvTI48pSdKFGs7HXhDgFQF4v1", 
          "width": 640
        }
      }
    }, 
    "sfomuseum:placetype": "image", 
    "wof:depicts": [102527513, 1159554829, 1360516467, 1226608683, 1159554803], 
    "wof:name": "Installation view of \"Ancestor Figures from New Guinea\"", 
    "wof:placetype": "media" 
  }, 
  "geometry": {"coordinates":[-122.38274,37.617227],"type":"Point"}
}
