{
  "type": "Feature", 
  "properties": {
    "iso:country": "US", 
    "media:created": -1, 
    "media:fingerprint": "776197f688aaa96cecc4c1d682d41891682c4958", 
    "media:medium": "image", 
    "media:mimetype": "image/tiff", 
    "media:properties": {
      "colours": [
        {
          "hex": "#e8f4f0", 
          "name": "#e8f4f0", 
          "reference": "vibrant"
        }, 
        {
          "hex": "#7d898b", 
          "name": "#7d898b", 
          "reference": "vibrant"
        }, 
        {
          "hex": "#b8c5c6", 
          "name": "#b8c5c6", 
          "reference": "vibrant"
        }, 
        {
          "hex": "#6f403b", 
          "name": "#6f403b", 
          "reference": "vibrant"
        }
      ], 
      "depicts": [1226603769], 
      "sizes": {
        "b": {
          "extension": "jpg", 
          "height": 726, 
          "mimetype": "image/jpeg", 
          "secret": "3VP5TtjcB9s0uhC5cQM2TW6cDE6qHA02", 
          "width": 1024
        }, 
        "c": {
          "extension": "jpg", 
          "height": 567, 
          "mimetype": "image/jpeg", 
          "secret": "3VP5TtjcB9s0uhC5cQM2TW6cDE6qHA02", 
          "width": 800
        }, 
        "dc": {
          "extension": "jpg", 
          "height": 567, 
          "mimetype": "image/jpeg", 
          "secret": "3VP5TtjcB9s0uhC5cQM2TW6cDE6qHA02", 
          "width": 800
        }, 
        "ds": {
          "extension": "jpg", 
          "height": 320, 
          "mimetype": "image/jpeg", 
          "secret": "3VP5TtjcB9s0uhC5cQM2TW6cDE6qHA02", 
          "width": 320
        }, 
        "k": {
          "extension": "jpg", 
          "height": 1452, 
          "mimetype": "image/jpeg", 
          "secret": "3VP5TtjcB9s0uhC5cQM2TW6cDE6qHA02", 
          "width": 2048
        }, 
        "n": {
          "extension": "jpg", 
          "height": 226, 
          "mimetype": "image/jpeg", 
          "secret": "3VP5TtjcB9s0uhC5cQM2TW6cDE6qHA02", 
          "width": 320
        }, 
        "o": {
          "extension": "jpg", 
          "height": 3014, 
          "mimetype": "image/jpeg", 
          "secret": "LyKeZRjG5bsAXWE43pZQ9eEhs2QaSTFC", 
          "width": 4251
        }, 
        "s": {
          "extension": "jpg", 
          "height": 320, 
          "mimetype": "image/jpeg", 
          "secret": "3VP5TtjcB9s0uhC5cQM2TW6cDE6qHA02", 
          "width": 320
        }, 
        "z": {
          "extension": "jpg", 
          "height": 453, 
          "mimetype": "image/jpeg", 
          "secret": "3VP5TtjcB9s0uhC5cQM2TW6cDE6qHA02", 
          "width": 640
        }
      }
    }, 
    "sfomuseum:placetype": "image", 
    "wof:depicts": [1226603769, 1159157883, 1159554817, 1159554803, 102527513], 
    "wof:name": "Installation view of \"Barbie® Takes A Vacation to Exotic Places\"", 
    "wof:placetype": "media" 
  }, 
  "geometry": {"coordinates":[-122.385472,37.613926],"type":"Point"}
}
