{
  "type": "Feature",
  "properties": {
    "iso:country": "US",
    "media:created": 1479233515,
    "media:fingerprint": "a8338e6e4fa2345ba809910d55d2b8418bba5113",
    "media:imagehash_avg": "a:878301030fcf9f3f",
    "media:imagehash_diff": "d:3e3e5b4e5d99397c",
    "media:medium": "image",
    "media:mimetype": "image/jpeg",
    "media:properties": {
      "colours": [
        {
          "hex": "#976f35",
          "name": "#976f35",
          "reference": "vibrant"
        }, 
        {
          "hex": "#ddab8e",
          "name": "#ddab8e",
          "reference": "vibrant"
        }, 
        {
          "hex": "#755335",
          "name": "#755335",
          "reference": "vibrant"
        }, 
        {
          "hex": "#8a7768",
          "name": "#8a7768",
          "reference": "vibrant"
        }, 
        {
          "hex": "#abafb5",
          "name": "#abafb5",
          "reference": "vibrant"
        }
      ],
      "depicts": [
        1226619799
      ],
      "sizes": {
        "b": {
          "extension": "jpg",
          "height": 682,
          "mimetype": "image/jpeg",
          "secret": "DOqy7n5MOoYMAC95PqycLsASyGQfWtJi",
          "width": 1024
        },
        "c": {
          "extension": "jpg",
          "height": 533,
          "mimetype": "image/jpeg",
          "secret": "DOqy7n5MOoYMAC95PqycLsASyGQfWtJi",
          "width": 800
        },
        "dc": {
          "extension": "jpg",
          "height": 533,
          "mimetype": "image/jpeg",
          "secret": "DOqy7n5MOoYMAC95PqycLsASyGQfWtJi",
          "width": 800
        },
        "ds": {
          "extension": "jpg",
          "height": 320,
          "mimetype": "image/jpeg",
          "secret": "DOqy7n5MOoYMAC95PqycLsASyGQfWtJi",
          "width": 320
        },
        "k": {
          "extension": "jpg",
          "height": 1365,
          "mimetype": "image/jpeg",
          "secret": "DOqy7n5MOoYMAC95PqycLsASyGQfWtJi",
          "width": 2048
        },
        "n": {
          "extension": "jpg",
          "height": 213,
          "mimetype": "image/jpeg",
          "secret": "DOqy7n5MOoYMAC95PqycLsASyGQfWtJi",
          "width": 320
        },
        "o": {
          "extension": "jpg",
          "height": 2400,
          "mimetype": "image/jpeg",
          "secret": "pAlrmQBqsjWjE0gGxwHj4lw8fVMUOtQg",
          "width": 3600
        },
        "s": {
          "extension": "jpg",
          "height": 320,
          "mimetype": "image/jpeg",
          "secret": "DOqy7n5MOoYMAC95PqycLsASyGQfWtJi",
          "width": 320
        },
        "z": {
          "extension": "jpg",
          "height": 426,
          "mimetype": "image/jpeg",
          "secret": "DOqy7n5MOoYMAC95PqycLsASyGQfWtJi",
          "width": 640
        }
      }
    },
    "sfomuseum:placetype": "image",
    "wof:depicts": [
      1360516255, 
      1159396321, 
      102527513, 
      1159396193, 
      1226619799, 
      1159157325
    ],
    "wof:name": "Installation view of \"The Mysterious Talking Board: Ouija and Beyond\"",
    "wof:placetype": "media"
  },
  "geometry": {"coordinates":[-122.382712,37.617422],"type":"Point"}
}
