{
  "type": "Feature", 
  "properties": {
    "iso:country": "US", 
    "media:created": 1377885064, 
    "media:fingerprint": "363695b26a8c1565b2fb3e7c22fc312231ba2096", 
    "media:medium": "image", 
    "media:mimetype": "image/jpeg", 
    "media:properties": {
      "colours": [
        {
          "hex": "#b07e1c", 
          "name": "#b07e1c", 
          "reference": "vibrant"
        }, 
        {
          "hex": "#f8f1e6", 
          "name": "#f8f1e6", 
          "reference": "vibrant"
        }, 
        {
          "hex": "#8c6213", 
          "name": "#8c6213", 
          "reference": "vibrant"
        }, 
        {
          "hex": "#988977", 
          "name": "#988977", 
          "reference": "vibrant"
        }, 
        {
          "hex": "#d1c1ae", 
          "name": "#d1c1ae", 
          "reference": "vibrant"
        }
      ], 
      "depicts": [1159160349], 
      "sizes": {
        "b": {
          "extension": "jpg", 
          "height": 682, 
          "mimetype": "image/jpeg", 
          "secret": "fvSK1Ol5Y0snmYx1EyYmym0cQ62onJRw", 
          "width": 1024
        }, 
        "c": {
          "extension": "jpg", 
          "height": 533, 
          "mimetype": "image/jpeg", 
          "secret": "fvSK1Ol5Y0snmYx1EyYmym0cQ62onJRw", 
          "width": 800
        }, 
        "dc": {
          "extension": "jpg", 
          "height": 533, 
          "mimetype": "image/jpeg", 
          "secret": "fvSK1Ol5Y0snmYx1EyYmym0cQ62onJRw", 
          "width": 800
        }, 
        "ds": {
          "extension": "jpg", 
          "height": 320, 
          "mimetype": "image/jpeg", 
          "secret": "fvSK1Ol5Y0snmYx1EyYmym0cQ62onJRw", 
          "width": 320
        }, 
        "k": {
          "extension": "jpg", 
          "height": 1365, 
          "mimetype": "image/jpeg", 
          "secret": "fvSK1Ol5Y0snmYx1EyYmym0cQ62onJRw", 
          "width": 2048
        }, 
        "n": {
          "extension": "jpg", 
          "height": 213, 
          "mimetype": "image/jpeg", 
          "secret": "fvSK1Ol5Y0snmYx1EyYmym0cQ62onJRw", 
          "width": 320
        }, 
        "o": {
          "extension": "jpg", 
          "height": 2400, 
          "mimetype": "image/jpeg", 
          "secret": "I3zOraWMHEnZmb6Q6iNCbofGPQWnESx9", 
          "width": 3600
        }, 
        "s": {
          "extension": "jpg", 
          "height": 320, 
          "mimetype": "image/jpeg", 
          "secret": "fvSK1Ol5Y0snmYx1EyYmym0cQ62onJRw", 
          "width": 320
        }, 
        "z": {
          "extension": "jpg", 
          "height": 426, 
          "mimetype": "image/jpeg", 
          "secret": "fvSK1Ol5Y0snmYx1EyYmym0cQ62onJRw", 
          "width": 640
        }
      }
    }, 
    "sfomuseum:placetype": "image", 
    "wof:depicts": [
      102527513, 
      1159396333, 
      1360516193, 
      1360516183, 
      1159396159, 
      1159160349
    ], 
    "wof:name": "Installation view of \"America’s Cup, Sailing for International Sport’s Greatest Trophy 1851-1937\"", 
    "wof:placetype": "media" 
  }, 
  "geometry": {"coordinates":[-122.388942,37.615424],"type":"Point"}
}
